Workbook

Sheet Cálculo
T1: Variação
C2: FY | W2: Delta
B3: ="EBITDA "&D15 -> EBITDA FY26'B | C3: =[1]DRE!$O$30/1000 -> 632.04404 | E3: Cálculo | F3: Manual | H3: =H17+H19 -> 1046295.7 | M3: Atualizar | T3: =B3 -> EBITDA FY26'B | U3: =C3 -> 632.04404 | V3: 701.06246 | W3: =U3-V3 -> -69.018412
B4: Forex | C4: =SUM(E4:F4) -> 70.572859 | D4: 26.209989 | E4: =J153/1000 -> 70.572859 | F4: =SUMIF($J$155:$J$181,B4,$I$155:$I$181)/1000 -> 0 | H4: =F17+F19 -> 1840632.9 | T4: =B4 -> Forex | U4: =C4 -> 70.572859 | V4: -41.322712 | W4: =U4-V4 -> 111.89557
B5: Price | C5: =SUM(E5:F5) -> 286.54894 | D5: 17.600765 | E5: =M48/1000 -> 286.54894 | F5: =SUMIF($J$155:$J$181,B5,$I$155:$I$181)/1000 -> 0 | H5: =H3/H4*1000 -> 568.44344 | J5: Sales | K5: Var Vol (kt) | L5: Vol/Mix impact | M5: Price impact | P5: Price impact | Q5: Forex | T5: =B5 -> Price | U5: =C5 -> 286.54894 | V5: -79.358523 | W5: =U5-V5 -> 365.90747
B6: Volume | C6: =SUM(E6:F6) -> -23.126221 | D6: 4.2158522 | E6: =L114/1000 -> -23.126221 | F6: =SUMIF($J$155:$J$181,B6,$I$155:$I$181)/1000 -> 0 | H6: =H5-G18 -> 51.826059 | J6: External | K6: =SUM(J83,J84,J88,J94,J95,J99,J100,J104) -> 364878.98 | L6: =SUM(K83,K84,K88,K94,K95,K99,K100,K104) -> 4125.244 | M6: =SUM(M17,M18,M22,M28,M29,M33,M34,M38,M44) -> 175788.85 | P6: =SUM(P17,P18,P22,P28,P29,P33,P34,P38,P44) -> 177667.05 | Q6: =SUM(Q17,Q18,Q22,Q29,Q34,Q38,Q44) -> 0 | T6: =B6 -> Volume | U6: =C6 -> -23.126221 | V6: 3.2696067 | W6: =U6-V6 -> -26.395828 | X6: -85996.796 | Z6: =M6-X6 -> 261785.65
B7: Mix | C7: =SUM(E7:F7) -> 16.44584 | D7: 1.1809201 | E7: =I114/1000+I166/1000 -> 16.44584 | F7: =SUMIF($J$155:$J$181,B7,$I$155:$I$181)/1000 -> 0 | H7: =H6*F18 -> 51687532 | J7: Domestic | K7: =SUM(J86:J87,J89:J93,J96:J98,J101:J103,J105:J113) -> 58125.113 | L7: =SUM(K86:K87,K89:K93,K96:K98,K101:K103,K105:K109,K111,K110,K112,K113) -> 9448.1482 | M7: =SUM(M20:M21,M23:M27,M30:M32,M35:M37,M39:M47) -> 52139.579 | P7: =SUM(P20:P21,P23:P27,P30:P32,P35:P37,P39:P43,P45,P46,P47) -> 193662.29 | Q7: =SUM(Q20:Q21,Q23:Q27,Q30:Q32,Q35:Q37,Q39:Q47,Q28,Q33) -> 143400.91 | T7: =B7 -> Mix | U7: =C7 -> 16.44584 | V7: 11.585407 | W7: =U7-V7 -> 4.8604336 | X7: 121689.4 | Z7: =M7-X7 -> -69549.819
B8: Fixed cost | C8: =SUM(E8:F8) -> -34.290559 | D8: 0 | E8: =J126/1000 -> -34.290559 | F8: =SUMIF($J$155:$J$181,B8,$I$155:$I$181)/1000 -> 0 | J8: Total | K8: =SUM(K6:K7) -> 423004.09 | L8: =SUM(L6:L7) -> 13573.392 | M8: =SUM(M6:M7) -> 227928.43 | P8: =SUM(P6:P7) -> 371329.34 | Q8: =SUM(Q6:Q7) -> 143400.91 | T8: =B8 -> Fixed cost | U8: =C8 -> -34.290559 | V8: -4.2325994 | W8: =U8-V8 -> -30.057959 | X8: 35692.602 | Z8: =M8-X8 -> 192235.83
B9: Input price | C9: =SUM(E9:F9) -> -177.47195 | D9: -60.287404 | E9: =J145/1000 -> -177.47195 | F9: =SUMIF($J$155:$J$181,B9,$I$155:$I$181)/1000 -> 0 | P9: =P8-P48 -> -58620.514 | T9: =B9 -> Input price | U9: =C9 -> -177.47195 | V9: 76.679374 | W9: =U9-V9 -> -254.15132 | Z9: =X9-M9 -> 0
B10: Usage | C10: =SUM(E10:F10) -> -12.829343 | D10: -3.3109603 | E10: =J148/1000 -> -12.829343 | F10: =SUMIF($J$155:$J$181,B10,$I$155:$I$181)/1000 -> 0 | J10: Industry | K10: =SUM(J86:J87,J90,J93,J97,J102,J105,J108,J91,J98,J103,J106,J110,J111,J112,J113) -> 45691.088 | L10: =SUM(K86:K87,K90,K93,K97,K102,K105,K108,K91,K98,K103,K106,K111,K110,K112) -> 4371.2704 | M10: =SUM(M20:M21,M24,M27,M31,M36,M39,M42,M25,M32,M37,M40)+M47+M46+M45 -> 40156.697 | P10: =SUM(P20:P21,P24,P27,P31,P36,P39,P42,P25,P32,P37,P40,P45) -> 144239.63 | Q10: =SUM(Q20:Q21,Q24,Q27,Q31,Q36,Q39,Q42:Q47,Q25,Q32,Q37,Q40)-Q43 -> 104082.93 | T10: =B10 -> Usage | U10: =C10 -> -12.829343 | V10: 2.1295159 | W10: =U10-V10 -> -14.958859 | X10: 129883.42 | Z10: =M10-X10 -> -89726.719
B11: Others | C11: =SUM(E11:F11) -> -5.7640204 | D11: -2.376185 | F11: =SUMIF($J$155:$J$181,B11,$I$155:$I$181)/1000 -> -5.7640204 | J11: Auto | K11: =SUM(J89,J92,J96,J101,J107,J109) -> 12434.025 | L11: =SUM(K89,K92,K96,K101,K107,K109) -> 5076.8778 | M11: =SUM(M23,M26,M30,M35,M41,M43) -> 11982.881 | N11: =M10-M20-M21 -> 40575.522 | P11: =SUM(P23,P26,P30,P35,P41,P43) -> 49422.664 | Q11: =SUM(Q23,Q26,Q30,Q35,Q41,Q43,Q28,Q33) -> 39317.984 | T11: =B11 -> Others | U11: =C11 -> -5.7640204 | V11: -5.0983695 | W11: =U11-V11 -> -0.66565089 | X11: -8194.0185 | Y11: 130619.12 | Z11: =M11-X11 -> 20176.9
B12: Stock variation | C12: =C13-SUM(C3:C11) -> -4.4371962 | D12: -25.205747 | F12: =SUMIF($J$155:$J$181,B12,$I$155:$I$181)/1000 -> -3.8604225 | J12: Check | K12: =K7-K10-K11 -> 0 | L12: =L7-L10-L11 -> 0 | M12: =M7-M10-M11 -> 0 | P12: =P7-P10-P11 -> 0 | Q12: =Q7-Q10-Q11 -> 0 | T12: =B12 -> Stock variation | U12: =C12 -> -4.4371962 | V12: 46.24153 | W12: =U12-V12 -> -50.678726 | Z12: =N11-Y11 -> -90043.601
B13: ="EBITDA "&G15 -> EBITDA FY26'F7 | C13: =[2]DRE!$O$30/1000 -> 747.6924 | F13: =F48-F14 -> 0 | J13: Industry & Down KUSD | K13: =SUM(H24:H25,H27,H31:H32,H36:H37,H39:H40,H42) -> 2460560.9 | N13: =K10-J86-J87 -> 45737.768 | P13: =P8/1000 -> 371.32934 | T13: =B13 -> EBITDA FY26'F7 | U13: =C13 -> 747.6924 | V13: 710.95569 | W13: =U13-V13 -> 36.736715 | Z13: =Z10-Z12 -> 316.88205
C14: ='[3]Shipments & Prices'!$O$8*1000-C48 -> -0.38 | E14: =E48-'[3]Shipments & Prices'!$O$234 -> 0.1558374 | F14: ='[4]Shipments & Prices'!$O$20*1000 -> 7106558.5 | H14: ='[4]Shipments & Prices'!$O$234-H48 -> 0 | J14: Auto KUSD | K14: =SUM(H23,H26,H30,H35,H41,H43,H20,H21) -> 930071.95
D15: FY26'B | G15: FY26'F7 | V15: =V10-U10 -> 14.958859
B16: Sales | C16: kt | D16: USD/t | E16: kUSD | F16: kt | G16: USD/t | H16: kUSD | I16: Sales Mix | J16: Mix Working | K16: Var Price USD | L16: Var Price BRL | M16: Price impact | O16: Var Price USD | P16: Price impact | Q16: Forex
B17: Slab Calvert | C17: ='[3]Shipments & Prices'!$O$23*1000 -> 961000 | D17: =IF(ISERROR((+E17/C17)*1000),0,(+E17/C17)*1000) -> 521.64672 | E17: ='[3]Shipments & Prices'!$O$237 -> 501302.5 | F17: ='[4]Shipments & Prices'!$O$23*1000 -> 966247.87 | G17: =IF(ISERROR((+H17/F17)*1000),0,(+H17/F17)*1000) -> 611.989 | H17: ='[4]Shipments & Prices'!$O$237 -> 591333.07 | I17: =(F17-J17)*D17/1000 -> 11455.529 | J17: =$F$48*C17/$C$48 -> 944287.55 | K17: =G17-D17 -> 90.342283 | M17: =K17*F17/1000 -> 87293.039 | N17: =H17-E17 -> 90030.573 | O17: =G17-D17 -> 90.342283 | P17: =O17*F17/1000 -> 87293.039 | Q17: =P17-M17 -> 0 | R17: =C17-F17 -> -5247.87
B18: Slabs Others Intragroup | C18: =[5]TUBARÃO_VEGA!$O$614*1000 -> 400000 | D18: =IF(ISERROR((+E18/C18)*1000),0,(+E18/C18)*1000) -> 444.574 | E18: =[5]TUBARÃO_VEGA!$O$626 -> 177829.6 | F18: ='[4]Shipments & Prices'!$O$614*1000 -> 997327.08 | G18: =IF(ISERROR((+H18/F18)*1000),0,(+H18/F18)*1000) -> 516.61738 | H18: ='[4]Shipments & Prices'!$O$626 -> 515236.51 | I18: =(F18-J18)*D18/1000 -> 268648.67 | J18: =$F$48*C18/$C$48 -> 393043.73 | K18: =G18-D18 -> 72.04338 | M18: =K18*F18/1000 -> 71850.814 | O18: =G18-D18 -> 72.04338 | P18: =O18*F18/1000 -> 71850.814 | Q18: =P18-M18 -> 0 | T18: 1789
B19: Slabs 3rd Party | C19: =[5]TUBARÃO_VEGA!$O$615*1000 -> 1423164.4 | D19: =IF(ISERROR((+E19/C19)*1000),0,(+E19/C19)*1000) -> 453.281 | E19: =[5]TUBARÃO_VEGA!$O$627 -> 645093.38 | F19: ='[4]Shipments & Prices'!$O$615*1000 -> 874385.04 | G19: =IF(ISERROR((+H19/F19)*1000),0,(+H19/F19)*1000) -> 520.32299 | H19: ='[4]Shipments & Prices'!$O$627 -> 454962.64 | I19: =(F19-J19)*D19/1000 -> -237532.63 | J19: =$F$48*C19/$C$48 -> 1398414.6 | K19: =G19-D19 -> 67.04199 | M19: =K19*F19/1000 -> 58620.514 | O19: =G19-D19 -> 67.04199 | P19: =O19*F19/1000 -> 58620.514 | Q19: =P19-M19 -> 0
B20: Slab DM | C20: ='[3]Shipments & Prices'!$O$25*1000 -> 31000 | D20: =IF(ISERROR((+E20/C20)*1000),0,(+E20/C20)*1000) -> 451.10154 | E20: ='[3]Shipments & Prices'!$O$239 -> 13984.148 | F20: ='[4]Shipments & Prices'!$O$25*1000 -> 32424.16 | G20: =IF(ISERROR((+H20/F20)*1000),0,(+H20/F20)*1000) -> 464.42371 | H20: ='[4]Shipments & Prices'!$O$239 -> 15058.549 | I20: =(F20-J20)*D20/1000 -> 885.6347 | J20: =$F$48*C20/$C$48 -> 30460.889 | L20: =(G20*$H$152)-(D20*$E$152) -> -31.991604 | M20: =L20*F20/1000/$E$152 -> -192.09276 | O20: =G20-D20 -> 13.32217 | P20: =O20*F20/1000 -> 431.96016 | Q20: =P20-M20 -> 624.05292 | R20: =R17/1000 -> -5.24787 | T20: =T18-C13 -> 1041.3076
B21: Plates DM | C21: ='[3]Shipments & Prices'!$O$28*1000 -> 18000 | D21: =IF(ISERROR((+E21/C21)*1000),0,(+E21/C21)*1000) -> 685.40017 | E21: ='[3]Shipments & Prices'!$O$242 -> 12337.203 | F21: ='[4]Shipments & Prices'!$O$28*1000 -> 16529.16 | G21: =IF(ISERROR((+H21/F21)*1000),0,(+H21/F21)*1000) -> 700.72228 | H21: ='[4]Shipments & Prices'!$O$242 -> 11582.351 | I21: =(F21-J21)*D21/1000 -> -793.56156 | J21: =$F$48*C21/$C$48 -> 17686.968 | L21: =(G21*$H$152)-(D21*$E$152) -> -74.072135 | M21: =L21*F21/1000/$E$152 -> -226.73151 | O21: =G21-D21 -> 15.32211 | P21: =O21*F21/1000 -> 253.26161 | Q21: =P21-M21 -> 479.99312 | AF21: Budget vs MRF10
B22: HRC Export | C22: ='[3]Shipments & Prices'!$O$30*1000 -> 433467 | D22: =IF(ISERROR((+E22/C22)*1000),0,(+E22/C22)*1000) -> 482.26451 | E22: ='[3]Shipments & Prices'!$O$244 -> 209045.75 | F22: ='[4]Shipments & Prices'!$O$30*1000 -> 197566.82 | G22: =IF(ISERROR((+H22/F22)*1000),0,(+H22/F22)*1000) -> 557.07307 | H22: ='[4]Shipments & Prices'!$O$244 -> 110059.16 | I22: =(F22-J22)*D22/1000 -> -110130.84 | J22: =$F$48*C22/$C$48 -> 425928.71 | K22: =G22-D22 -> 74.80856 | M22: =K22*F22/1000 -> 14779.689 | O22: =G22-D22 -> 74.80856 | P22: =O22*F22/1000 -> 14779.689 | Q22: =P22-M22 -> 0
B23: HRC DM Auto | C23: ='[3]Shipments & Prices'!$O$34*1000 -> 85817.96 | D23: =IF(ISERROR((+E23/C23)*1000),0,(+E23/C23)*1000) -> 681.44089 | E23: ='[3]Shipments & Prices'!$O$248 -> 58479.867 | F23: ='[4]Shipments & Prices'!$O$34*1000 -> 100236.84 | G23: =IF(ISERROR((+H23/F23)*1000),0,(+H23/F23)*1000) -> 725.82997 | H23: ='[4]Shipments & Prices'!$O$248 -> 72754.902 | I23: =(F23-J23)*D23/1000 -> 10842.62 | J23: =$F$48*C23/$C$48 -> 84325.527 | L23: =(G23*$H$152)-(D23*$E$152) -> 77.270714 | M23: =L23*F23/1000/$E$152 -> 1434.3282 | O23: =G23-D23 -> 44.38907 | P23: =O23*F23/1000 -> 4449.4202 | Q23: =P23-M23 -> 3015.092
B24: HRC DM Industry | C24: =('[3]Shipments & Prices'!$O$35)*1000 -> 1438681.3 | D24: =IF(ISERROR((+E24/C24)*1000),0,(+E24/C24)*1000) -> 658.77201 | E24: ='[3]Shipments & Prices'!$O$249 -> 947762.99 | F24: =('[4]Shipments & Prices'!$O$35)*1000 -> 1441770.7 | G24: =IF(ISERROR((+H24/F24)*1000),0,(+H24/F24)*1000) -> 693.84696 | H24: ='[4]Shipments & Prices'!$O$249 -> 1000368.2 | I24: =(F24-J24)*D24/1000 -> 18517.47 | J24: =$F$48*C24/$C$48 -> 1413661.7 | L24: =(G24*$H$152)-(D24*$E$152) -> 34.131787 | M24: =L24*F24/1000/$E$152 -> 9113.0022 | O24: =G24-D24 -> 35.074948 | P24: =O24*F24/1000 -> 50570.033 | Q24: =P24-M24 -> 41457.031 | R24: =C24+C25 -> 1866055.1 | S24: =(T24/R24)*1000 -> 680.92612 | T24: =E24+E25 -> 1270645.7
B25: HRC DM Downstream | C25: =+'[3]Shipments & Prices'!$O$36*1000 -> 427373.81 | D25: =IF(ISERROR((+E25/C25)*1000),0,(+E25/C25)*1000) -> 755.50415 | E25: =+'[3]Shipments & Prices'!$O$250 -> 322882.69 | F25: =+'[4]Shipments & Prices'!$O$36*1000 -> 446359.43 | G25: =IF(ISERROR((+H25/F25)*1000),0,(+H25/F25)*1000) -> 799.87146 | H25: ='[4]Shipments & Prices'!$O$250 -> 357030.17 | I25: =(F25-J25)*D25/1000 -> 19958.87 | J25: =$F$48*C25/$C$48 -> 419941.49 | L25: =(G25*$H$152)-(D25*$E$152) -> 60.583747 | M25: =L25*F25/1000/$E$152 -> 5007.8013 | O25: =G25-D25 -> 44.367302 | P25: =O25*F25/1000 -> 19803.764 | Q25: =P25-M25 -> 14795.962 | R25: =F24+F25 -> 1888130.2 | S25: =(T25/R25)*1000 -> 718.91146 | T25: =H24+H25 -> 1357398.4
B26: P&O DM Auto | C26: ='[3]Shipments & Prices'!$O$44*1000 -> 102999.19 | D26: =IF(ISERROR((+E26/C26)*1000),0,(+E26/C26)*1000) -> 859.20611 | E26: ='[3]Shipments & Prices'!$O$258 -> 88497.533 | F26: ='[4]Shipments & Prices'!$O$44*1000 -> 90523.858 | G26: =IF(ISERROR((+H26/F26)*1000),0,(+H26/F26)*1000) -> 914.47188 | H26: ='[4]Shipments & Prices'!$O$258 -> 82781.523 | I26: =(F26-J26)*D26/1000 -> -9179.8489 | J26: =$F$48*C26/$C$48 -> 101207.96 | L26: =(G26*$H$152)-(D26*$E$152) -> 93.789581 | M26: =L26*F26/1000/$E$152 -> 1572.2583 | O26: =G26-D26 -> 55.265775 | P26: =O26*F26/1000 -> 5002.8712 | Q26: =P26-M26 -> 3430.6129 | V26: =23/5.25 -> 4.3809524
B27: P&O DM Industry | C27: ='[3]Shipments & Prices'!$O$45*1000 -> 0 | D27: =G27 -> 723.2675 | E27: ='[3]Shipments & Prices'!$O$259 -> 0 | F27: ='[4]Shipments & Prices'!$O$45*1000 -> 45424.208 | G27: =IF(ISERROR((+H27/F27)*1000),0,(+H27/F27)*1000) -> 723.2675 | H27: ='[4]Shipments & Prices'!$O$259 -> 32853.853 | I27: =(F27-J27)*D27/1000 -> 32853.853 | J27: =$F$48*C27/$C$48 -> 0 | L27: =(G27*$H$152)-(D27*$E$152) -> -161.85682 | M27: =L27*F27/1000/$E$152 -> -1361.5219 | O27: =G27-D27 -> 0 | P27: =O27*F27/1000 -> 0 | Q27: =P27-M27 -> 1361.5219
B28: CRC EM Auto | C28: ='[3]Shipments & Prices'!$O$48*1000 -> 1220.3924 | D28: =IF(ISERROR((+E28/C28)*1000),0,(+E28/C28)*1000) -> 882.99234 | E28: ='[3]Shipments & Prices'!$O$262 -> 1077.5971 | F28: ='[4]Shipments & Prices'!$O$48*1000 -> 1887.8106 | G28: =IF(ISERROR((+H28/F28)*1000),0,(+H28/F28)*1000) -> 937.18709 | H28: ='[4]Shipments & Prices'!$O$262 -> 1769.2317 | I28: =(F28-J28)*D28/1000 -> 608.0653 | J28: =$F$48*C28/$C$48 -> 1199.1689 | L28: =(G28*$H$152)-(D28*$E$152) -> 82.922743 | M28: =L28*F28/1000/$E$152 -> 28.989339 | O28: =G28-D28 -> 54.194756 | P28: =O28*F28/1000 -> 102.30943 | Q28: =P28-M28 -> 73.320093
B29: CRC EM Industry | C29: ='[3]Shipments & Prices'!$O$49*1000 -> 492.26 | D29: =IF(ISERROR((+E29/C29)*1000),0,(+E29/C29)*1000) -> 323.31493 | E29: ='[3]Shipments & Prices'!$O$263 -> 159.15501 | F29: ='[4]Shipments & Prices'!$O$49*1000 -> 4847.375 | G29: =IF(ISERROR((+H29/F29)*1000),0,(+H29/F29)*1000) -> 603.52341 | H29: ='[4]Shipments & Prices'!$O$263 -> 2925.5043 | I29: =(F29-J29)*D29/1000 -> 1410.8415 | J29: =$F$48*C29/$C$48 -> 483.69926 | K29: =G29-D29 -> 280.20848 | M29: =K29*F29/1000 -> 1358.2756 | O29: =G29-D29 -> 280.20848 | P29: =O29*F29/1000 -> 1358.2756 | Q29: =P29-M29 -> 0
B30: CRC DM Auto | C30: ='[3]Shipments & Prices'!$O$51*1000 -> 90127.47 | D30: =IF(ISERROR((+E30/C30)*1000),0,(+E30/C30)*1000) -> 922.02223 | E30: ='[3]Shipments & Prices'!$O$265 -> 83099.531 | F30: ='[4]Shipments & Prices'!$O$51*1000 -> 95622.293 | G30: =IF(ISERROR((+H30/F30)*1000),0,(+H30/F30)*1000) -> 982.99579 | H30: ='[4]Shipments & Prices'!$O$265 -> 93996.312 | I30: =(F30-J30)*D30/1000 -> 6511.5067 | J30: =$F$48*C30/$C$48 -> 88560.092 | L30: =(G30*$H$152)-(D30*$E$152) -> 109.27698 | M30: =L30*F30/1000/$E$152 -> 1935.0584 | O30: =G30-D30 -> 60.973563 | P30: =O30*F30/1000 -> 5830.4319 | Q30: =P30-M30 -> 3895.3736
B31: CRC DM Industry | C31: =('[3]Shipments & Prices'!$O$52)*1000 -> 265325.54 | D31: =IF(ISERROR((+E31/C31)*1000),0,(+E31/C31)*1000) -> 788.21579 | E31: ='[3]Shipments & Prices'!$O$266 -> 209133.78 | F31: =('[4]Shipments & Prices'!$O$52)*1000 -> 286122.32 | G31: =IF(ISERROR((+H31/F31)*1000),0,(+H31/F31)*1000) -> 844.90554 | H31: ='[4]Shipments & Prices'!$O$266 -> 241746.33 | I31: =(F31-J31)*D31/1000 -> 20029.329 | J31: =$F$48*C31/$C$48 -> 260711.35 | L31: =(G31*$H$152)-(D31*$E$152) -> 117.04702 | M31: =L31*F31/1000/$E$152 -> 6201.8085 | O31: =G31-D31 -> 56.689756 | P31: =O31*F31/1000 -> 16220.205 | Q31: =P31-M31 -> 10018.396 | R31: =C31+C32 -> 375627.51 | S31: =(T31/R31)*1000 -> 801.51349 | T31: =E31+E32 -> 301070.52
B32: CRC DM Downstream | C32: =+'[3]Shipments & Prices'!$O$53*1000 -> 110301.97 | D32: =IF(ISERROR((+E32/C32)*1000),0,(+E32/C32)*1000) -> 833.50042 | E32: =+'[3]Shipments & Prices'!$O$267 -> 91936.738 | F32: =+'[4]Shipments & Prices'!$O$53*1000 -> 117390.91 | G32: =IF(ISERROR((+H32/F32)*1000),0,(+H32/F32)*1000) -> 892.1814 | H32: =+'[4]Shipments & Prices'!$O$267 -> 104733.99 | I32: =(F32-J32)*D32/1000 -> 7507.4783 | J32: =$F$48*C32/$C$48 -> 108383.74 | L32: =(G32*$H$152)-(D32*$E$152) -> 117.21996 | M32: =L32*F32/1000/$E$152 -> 2548.2515 | O32: =G32-D32 -> 58.680977 | P32: =O32*F32/1000 -> 6888.6133 | Q32: =P32-M32 -> 4340.3619 | R32: =F31+F32 -> 403513.23 | S32: =(T32/R32)*1000 -> 858.65913 | T32: =H31+H32 -> 346480.32
B33: HDG EM Auto | C33: ='[3]Shipments & Prices'!$O$61*1000 -> 49551.853 | D33: =IF(ISERROR((+E33/C33)*1000),0,(+E33/C33)*1000) -> 1018.0181 | E33: ='[3]Shipments & Prices'!$O$275 -> 50444.681 | F33: ='[4]Shipments & Prices'!$O$61*1000 -> 41148.524 | G33: =IF(ISERROR((+H33/F33)*1000),0,(+H33/F33)*1000) -> 1058.4157 | H33: ='[4]Shipments & Prices'!$O$275 -> 43552.244 | I33: =(F33-J33)*D33/1000 -> -7677.4736 | J33: =$F$48*C33/$C$48 -> 48690.112 | L33: =(G33*$H$152)-(D33*$E$152) -> -18.710747 | M33: =L33*F33/1000/$E$152 -> -142.57771 | O33: =G33-D33 -> 40.397668 | P33: =O33*F33/1000 -> 1662.3044 | Q33: =P33-M33 -> 1804.8821
B34: HDG EM Industry | C34: ='[3]Shipments & Prices'!$O$62*1000 -> 1014.12 | D34: =IF(ISERROR((+E34/C34)*1000),0,(+E34/C34)*1000) -> 323.31493 | E34: ='[3]Shipments & Prices'!$O$276 -> 327.88014 | F34: ='[4]Shipments & Prices'!$O$62*1000 -> 2599.121 | G34: =IF(ISERROR((+H34/F34)*1000),0,(+H34/F34)*1000) -> 562.09665 | H34: ='[4]Shipments & Prices'!$O$276 -> 1460.9572 | I34: =(F34-J34)*D34/1000 -> 518.15655 | J34: =$F$48*C34/$C$48 -> 996.48376 | K34: =G34-D34 -> 238.78171 | M34: =K34*F34/1000 -> 620.62257 | O34: =G34-D34 -> 238.78171 | P34: =O34*F34/1000 -> 620.62257 | Q34: =P34-M34 -> 0 | W34: =220-167 -> 53
B35: HDG DM Auto | C35: ='[3]Shipments & Prices'!$O$64*1000 -> 463694.03 | D35: =IF(ISERROR((+E35/C35)*1000),0,(+E35/C35)*1000) -> 1045.0986 | E35: ='[3]Shipments & Prices'!$O$278 -> 484605.99 | F35: ='[4]Shipments & Prices'!$O$64*1000 -> 463787.29 | G35: =IF(ISERROR((+H35/F35)*1000),0,(+H35/F35)*1000) -> 1098.849 | H35: ='[4]Shipments & Prices'!$O$278 -> 509632.21 | I35: =(F35-J35)*D35/1000 -> 8525.0978 | J35: =$F$48*C35/$C$48 -> 455630.07 | L35: =(G35*$H$152)-(D35*$E$152) -> 44.345684 | M35: =L35*F35/1000/$E$152 -> 3808.6971 | O35: =G35-D35 -> 53.750413 | P35: =O35*F35/1000 -> 24928.758 | Q35: =P35-M35 -> 21120.061
B36: HDG DM Industry | C36: =('[3]Shipments & Prices'!$O$65)*1000 -> 416584.71 | D36: =IF(ISERROR((+E36/C36)*1000),0,(+E36/C36)*1000) -> 848.78295 | E36: ='[3]Shipments & Prices'!$O$279 -> 353590 | F36: =('[4]Shipments & Prices'!$O$65)*1000 -> 438619.17 | G36: =IF(ISERROR((+H36/F36)*1000),0,(+H36/F36)*1000) -> 912.55186 | H36: ='[4]Shipments & Prices'!$O$279 -> 400262.74 | I36: =(F36-J36)*D36/1000 -> 24851.647 | J36: =$F$48*C36/$C$48 -> 409340.02 | L36: =(G36*$H$152)-(D36*$E$152) -> 140.13614 | M36: =L36*F36/1000/$E$152 -> 11382.666 | O36: =G36-D36 -> 63.768902 | P36: =O36*F36/1000 -> 27970.263 | Q36: =P36-M36 -> 16587.597 | R36: =C36+C37 -> 500124.04 | S36: =(T36/R36)*1000 -> 854.04782 | T36: =E36+E37 -> 427129.85
B37: HDG DM Downstream | C37: =+'[3]Shipments & Prices'!$O$66*1000 -> 83539.33 | D37: =IF(ISERROR((+E37/C37)*1000),0,(+E37/C37)*1000) -> 880.30207 | E37: =+'[3]Shipments & Prices'!$O$280 -> 73539.846 | F37: =+'[4]Shipments & Prices'!$O$66*1000 -> 76159.621 | G37: =IF(ISERROR((+H37/F37)*1000),0,(+H37/F37)*1000) -> 950.63961 | H37: =+'[4]Shipments & Prices'!$O$280 -> 72400.352 | I37: =(F37-J37)*D37/1000 -> -5217.4647 | J37: =$F$48*C37/$C$48 -> 82086.524 | L37: =(G37*$H$152)-(D37*$E$152) -> 167.08325 | M37: =L37*F37/1000/$E$152 -> 2356.481 | O37: =G37-D37 -> 70.337531 | P37: =O37*F37/1000 -> 5356.8797 | Q37: =P37-M37 -> 3000.3988 | R37: =F36+F37 -> 514778.79 | S37: =(T37/R37)*1000 -> 918.1868 | T37: =H36+H37 -> 472663.09
B38: AlZn Export | C38: ='[3]Shipments & Prices'!$O$74*1000 -> 0 | D38: =IF(ISERROR((+E38/C38)*1000),0,(+E38/C38)*1000) -> 0 | E38: ='[3]Shipments & Prices'!$O$288 -> 0 | F38: ='[4]Shipments & Prices'!$O$74*1000 -> 0 | G38: =IF(ISERROR((+H38/F38)*1000),0,(+H38/F38)*1000) -> 0 | H38: ='[4]Shipments & Prices'!$O$288 -> 0 | I38: =(F38-J38)*D38/1000 -> 0 | J38: =$F$48*C38/$C$48 -> 0 | K38: =G38-D38 -> 0 | M38: =K38*F38/1000 -> 0 | O38: =G38-D38 -> 0 | P38: =O38*F38/1000 -> 0 | Q38: =P38-M38 -> 0
B39: AlZn DM Industry | C39: =('[3]Shipments & Prices'!$O$79)*1000 -> 181457.09 | D39: =IF(ISERROR((+E39/C39)*1000),0,(+E39/C39)*1000) -> 973.02161 | E39: ='[3]Shipments & Prices'!$O$293 -> 176561.67 | F39: =('[4]Shipments & Prices'!$O$79)*1000 -> 136271.79 | G39: =IF(ISERROR((+H39/F39)*1000),0,(+H39/F39)*1000) -> 1027.641 | H39: ='[4]Shipments & Prices'!$O$293 -> 140038.48 | I39: =(F39-J39)*D39/1000 -> -40895.746 | J39: =$F$48*C39/$C$48 -> 178301.43 | L39: =(G39*$H$152)-(D39*$E$152) -> 64.973401 | M39: =L39*F39/1000/$E$152 -> 1639.6373 | O39: =G39-D39 -> 54.619373 | P39: =O39*F39/1000 -> 7443.0797 | Q39: =P39-M39 -> 5803.4424 | R39: =C39+C40 -> 287792.97 | S39: =(T39/R39)*1000 -> 1015.5456 | T39: =E39+E40 -> 292266.87
B40: ALZn DM Downstream | C40: =+'[3]Shipments & Prices'!$O$80*1000 -> 106335.88 | D40: =IF(ISERROR((+E40/C40)*1000),0,(+E40/C40)*1000) -> 1088.1106 | E40: =+'[3]Shipments & Prices'!$O$294 -> 115705.2 | F40: =+'[4]Shipments & Prices'!$O$80*1000 -> 88523.367 | G40: =IF(ISERROR((+H40/F40)*1000),0,(+H40/F40)*1000) -> 1184.3833 | H40: =+'[4]Shipments & Prices'!$O$294 -> 104845.6 | I40: =(F40-J40)*D40/1000 -> -17369.792 | J40: =$F$48*C40/$C$48 -> 104486.63 | L40: =(G40*$H$152)-(D40*$E$152) -> 254.82436 | M40: =L40*F40/1000/$E$152 -> 4177.3908 | O40: =G40-D40 -> 96.272637 | P40: =O40*F40/1000 -> 8522.378 | Q40: =P40-M40 -> 4344.9871 | R40: =F39+F40 -> 224795.16 | S40: =(T40/R40)*1000 -> 1089.3654 | T40: =H39+H40 -> 244884.07
B41: Usibor DM Auto | C41: ='[3]Shipments & Prices'!$O$90*1000 -> 94231.595 | D41: =IF(ISERROR((+E41/C41)*1000),0,(+E41/C41)*1000) -> 1291.3711 | E41: ='[3]Shipments & Prices'!$O$304 -> 121687.96 | F41: ='[4]Shipments & Prices'!$O$90*1000 -> 99323.021 | G41: =IF(ISERROR((+H41/F41)*1000),0,(+H41/F41)*1000) -> 1381.2513 | H41: ='[4]Shipments & Prices'!$O$304 -> 137190.05 | I41: =(F41-J41)*D41/1000 -> 8691.1575 | J41: =$F$48*C41/$C$48 -> 92592.843 | L41: =(G41*$H$152)-(D41*$E$152) -> 176.24927 | M41: =L41*F41/1000/$E$152 -> 3241.7797 | O41: =G41-D41 -> 89.880255 | P41: =O41*F41/1000 -> 8927.1784 | Q41: =P41-M41 -> 5685.3988
B42: AlSi DM Industry | C42: ='[3]Shipments & Prices'!$O$91*1000 -> 7737.54 | D42: =IF(ISERROR((+E42/C42)*1000),0,(+E42/C42)*1000) -> 848.71896 | E42: ='[3]Shipments & Prices'!$O$305 -> 6566.9969 | F42: ='[4]Shipments & Prices'!$O$91*1000 -> 7661.225 | G42: =IF(ISERROR((+H42/F42)*1000),0,(+H42/F42)*1000) -> 819.85822 | H42: ='[4]Shipments & Prices'!$O$305 -> 6281.1183 | I42: =(F42-J42)*D42/1000 -> 49.434597 | J42: =$F$48*C42/$C$48 -> 7602.9789 | L42: =(G42*$H$152)-(D42*$E$152) -> -339.32045 | M42: =L42*F42/1000/$E$152 -> -481.40931 | O42: =G42-D42 -> -28.860744 | P42: =O42*F42/1000 -> -221.10865 | Q42: =P42-M42 -> 260.30066
B43: Auto Imports/PP DM | C43: ='[3]Shipments & Prices'!$O$107*1000 -> 3816.3262 | D43: =IF(ISERROR((+E43/C43)*1000),0,(+E43/C43)*1000) -> 1872.4827 | E43: ='[3]Shipments & Prices'!$O$321 -> 7146.0046 | F43: ='[4]Shipments & Prices'!$O$107*1000+'[4]Shipments & Prices'!$O$105*1000 -> 3627.2929 | G43: =IF(ISERROR((+H43/F43)*1000),0,(+H43/F43)*1000) -> 1950.779 | H43: ='[4]Shipments & Prices'!$O$321+'[4]Shipments & Prices'!$O$319 -> 7076.0467 | I43: =(F43-J43)*D43/1000 -> -229.68763 | J43: =$F$48*C43/$C$48 -> 3749.9576 | L43: =(G43*$H$152)-(D43*$E$152) -> -13.756064 | M43: =L43*F43/1000/$E$152 -> -9.2402355 | O43: =G43-D43 -> 78.296316 | P43: =O43*F43/1000 -> 284.00367 | Q43: =P43-M43 -> 293.24391
B44: Magnelis DM Industry | C44: ='[3]Shipments & Prices'!$O$95*1000 -> 0 | D44: =G44 -> 481.23641 | E44: ='[3]Shipments & Prices'!$O$309 -> 0 | F44: ='[4]Shipments & Prices'!$O$95*1000 -> 10000 | G44: =IF(ISERROR((+H44/F44)*1000),0,(+H44/F44)*1000) -> 481.23641 | H44: ='[4]Shipments & Prices'!$O$309 -> 4812.3641 | I44: =(F44-J44)*D44/1000 -> 4812.3641 | J44: =$F$48*C44/$C$48 -> 0 | K44: =G44-D44 -> 0 | M44: =K44*F44/1000 -> 0 | O44: =G44-D44 -> 0 | P44: =O44*F44/1000 -> 0 | Q44: =P44-M44 -> 0
B45: Industry Imports | C45: ='[3]Shipments & Prices'!$O$98*1000 -> 35399.97 | D45: =IF(ISERROR((+E45/C45)*1000),0,(+E45/C45)*1000) -> 948.71897 | E45: ='[3]Shipments & Prices'!$O$312 -> 33584.623 | F45: =('[4]Shipments & Prices'!$O$98)*1000 -> 17169.268 | G45: =IF(ISERROR((+H45/F45)*1000),0,(+H45/F45)*1000) -> 1006.98 | H45: ='[4]Shipments & Prices'!$O$312 -> 17289.109 | I45: =(F45-J45)*D45/1000 -> -16711.753 | J45: =$F$48*C45/$C$48 -> 34784.34 | L45: =(G45*$H$152)-(D45*$E$152) -> 89.261878 | M45: =L45*F45/1000/$E$152 -> 283.80761 | O45: =G45-D45 -> 58.261011 | P45: =O45*F45/1000 -> 1000.2989 | Q45: =P45-M45 -> 716.4913
B46: Magnelis DM Downstream | C46: ='[3]Shipments & Prices'!$O$97*1000 -> 0 | D46: =G46 -> 1007.5183 | E46: ='[3]Shipments & Prices'!$O$311 -> 0 | F46: ='[4]Shipments & Prices'!$O$97*1000 -> 7002.88 | G46: =IF(ISERROR((+H46/F46)*1000),0,(+H46/F46)*1000) -> 1007.5183 | H46: ='[4]Shipments & Prices'!$O$311 -> 7055.5294 | I46: =(F46-J46)*D46/1000 -> 7055.5294 | J46: =$F$48*C46/$C$48 -> 0 | L46: =(G46*$H$152)-(D46*$E$152) -> -225.46804 | M46: =L46*F46/1000/$E$152 -> -292.39363 | O46: =G46-D46 -> 0 | P46: =O46*F46/1000 -> 0 | Q46: =P46-M46 -> 292.39363
B47: HRC Aperam baixo carbono | I47: =(F47-J47)*D47/1000 -> 0 | J47: =$F$48*C47/$C$48 -> 0 | L47: =(G47*$H$152)-(D47*$E$152) -> 0 | M47: =L47*F47/1000/$E$152 -> 0 | O47: =G47-D47 -> 0 | P47: =O47*F47/1000 -> 0 | Q47: =P47-M47 -> 0
B48: Total Sales | C48: =SUM(C17:C47) -> 7232333.7 | D48: =+E48/C48*1000 -> 661.80343 | E48: =SUM(E17:E47) -> 4786383.3 | F48: =SUM(F17:F47) -> 7106558.5 | G48: =+H48/F48*1000 -> 723.42881 | H48: =SUM(H17:H47) -> 5141089.1 | I48: =SUM(I17:I47) -> 7994.4599 | J48: =SUM(J17:J47) -> 7106558.5 | M48: =SUM(M17:M47) -> 286548.94 | P48: =SUM(P17:P47) -> 429949.86 | Q48: =SUM(Q17:Q47) -> 143400.91
B49: Variable Costs | C49: kt | D49: USD/t | E49: kUSD | F49: kt | G49: USD/t | H49: kUSD | I49: Cost Mix | AE49: =AE42-AE43-AE48 -> 0 | AH49: =AH42-AH43-AH48 -> 0
A50: 30 | B50: Slab Calvert | C50: =C17 -> 961000 | D50: ='[6]Mensal MRF USD2'!$T$259+A50 -> 437.37405 | E50: =D50*C50/1000 -> 420316.46 | F50: =F17 -> 966247.87 | I50: =(J17-F50)*D50/1000 -> -9604.874
A51: 9 | B51: Slabs Others Intragroup | C51: =C18 -> 400000 | D51: ='[6]Mensal MRF USD2'!$T$259+A51 -> 416.37405 | E51: =D51*C51/1000 -> 166549.62 | F51: =F18 -> 997327.08 | I51: =(J18-F51)*D51/1000 -> -251607.91
A52: 9 | B52: Slabs 3rd Party | C52: =C19 -> 1423164.4 | D52: ='[6]Mensal MRF USD2'!$T$259+A52 -> 416.37405 | E52: =D52*C52/1000 -> 592568.72 | F52: =F19 -> 874385.04 | I52: =(J19-F52)*D52/1000 -> 218192.3 | K52: =F48-C48 -> -125775.25
A53: 43 | B53: Slab DM | C53: =C20 -> 31000 | D53: ='[6]Mensal MRF USD2'!$T$259+A53 -> 450.37405 | E53: =D53*C53/1000 -> 13961.596 | F53: =F20 -> 32424.16 | I53: =(J20-F53)*D53/1000 -> -884.20644
B54: Plates DM | C54: =C21 -> 18000 | D54: =$D$51+A54 -> 416.37405 | E54: =D54*C54/1000 -> 7494.7329 | F54: =F21 -> 16529.16 | I54: =(J21-F54)*D54/1000 -> 482.08106
A55: 9 | B55: HRC Export | C55: =C22 -> 433467 | D55: =$D$56+A55 -> 446.21225 | E55: =D55*C55/1000 -> 193418.29 | F55: =F22 -> 197566.82 | I55: =(J22-F55)*D55/1000 -> 101897.87
B56: HRC DM Auto | C56: =C23 -> 85817.96 | D56: ='[6]Mensal MRF USD2'!$T$279 -> 437.21225 | E56: =D56*C56/1000 -> 37520.663 | F56: =F23 -> 100236.84 | I56: =(J23-F56)*D56/1000 -> -6956.6212
B57: HRC DM Industry | C57: =C24 -> 1438681.3 | D57: =D56 -> 437.21225 | E57: =D57*C57/1000 -> 629009.1 | F57: =F24 -> 1441770.7 | I57: =(J24-F57)*D57/1000 -> -12289.631
A58: 80 | B58: HRC DM Downstream | C58: =C25 -> 427373.81 | D58: =D57+A58 -> 517.21225 | E58: =D58*C58/1000 -> 221042.97 | F58: =F25 -> 446359.43 | I58: =(J25-F58)*D58/1000 -> -13663.687
A59: =(195+170)/$E$152 -> 67.592593 | B59: P&O DM Auto | C59: =C26 -> 102999.19 | D59: =D58 -> 517.21225 | E59: =D59*C59/1000 -> 53272.443 | F59: =F26 -> 90523.858 | I59: =(J26-F59)*D59/1000 -> 5525.9503
A60: =(40+50)/$E$152 -> 16.666667 | B60: P&O DM Industry | C60: =C27 -> 0 | D60: =$D$56+A60 -> 453.87892 | E60: =D60*C60/1000 -> 0 | F60: =F27 -> 45424.208 | I60: =(J27-F60)*D60/1000 -> -20617.09
A61: =21*0 -> 0 | B61: CRC EM Auto | C61: =C28 -> 1220.3924 | D61: =$D$63+A61 -> 494.72402 | E61: =D61*C61/1000 -> 603.75742 | F61: =F28 -> 1887.8106 | I61: =(J28-F61)*D61/1000 -> -340.68757
A62: =21*0 -> 0 | B62: CRC EM Industry | C62: =C29 -> 492.26 | D62: =$D$63+A62 -> 494.72402 | E62: =D62*C62/1000 -> 243.53285 | F62: =F29 -> 4847.375 | I62: =(J29-F62)*D62/1000 -> -2158.8152
B63: CRC DM Auto | C63: =C30 -> 90127.47 | D63: ='[7]Mensal USD'!$R$21 -> 494.72402 | E63: =D63*C63/1000 -> 44588.225 | F63: =F30 -> 95622.293 | I63: =(J30-F63)*D63/1000 -> -3493.8407
B64: CRC DM Industry | C64: =C31 -> 265325.54 | D64: =D63 -> 494.72402 | E64: =D64*C64/1000 -> 131262.92 | F64: =F31 -> 286122.32 | I64: =(J31-F64)*D64/1000 -> -12571.418
A65: 80 | B65: CRC DM Downstream | C65: =C32 -> 110301.97 | D65: =D64+A65 -> 574.72402 | E65: =D65*C65/1000 -> 63393.192 | F65: =F32 -> 117390.91 | I65: =(J32-F65)*D65/1000 -> -5176.6358
A66: =21*0 -> 0 | B66: HDG EM Auto | C66: =C33 -> 49551.853 | D66: =$D$68+A66 -> 572.5625 | E66: =D66*C66/1000 -> 28371.533 | F66: =F33 -> 41148.524 | I66: =(J33-F66)*D66/1000 -> 4318.031
A67: =21*0 -> 0 | B67: HDG EM Industry | C67: =C34 -> 1014.12 | D67: =$D$69+A67 -> 592.20466 | E67: =D67*C67/1000 -> 600.56659 | F67: =F34 -> 2599.121 | I67: =(J34-F67)*D67/1000 -> -949.08924
B68: HDG DM Auto | C68: =C35 -> 463694.03 | D68: ='[7]Mensal USD'!$R$31 -> 572.5625 | E68: =D68*C68/1000 -> 265493.81 | F68: =F35 -> 463787.29 | I68: =(J35-F68)*D68/1000 -> -4670.5174
B69: HDG DM Industry | C69: =C36 -> 416584.71 | D69: ='[7]Mensal USD'!$R$51 -> 592.20466 | E69: =D69*C69/1000 -> 246703.41 | F69: =F36 -> 438619.17 | I69: =(J36-F69)*D69/1000 -> -17339.251
A70: 80 | B70: HDG DM Downstream | C70: =C37 -> 83539.33 | D70: =D69+A70 -> 672.20466 | E70: =D70*C70/1000 -> 56155.527 | F70: =F37 -> 76159.621 | I70: =(J37-F70)*D70/1000 -> 3984.0916
A71: =21*0 -> 0 | B71: AlZn Export | C71: =C38 -> 0 | D71: =$D$72+A71 -> 663.85931 | E71: =D71*C71/1000 -> 0 | F71: =F38 -> 0 | I71: =(J38-F71)*D71/1000 -> 0
B72: AlZn DM Industry | C72: =C39 -> 181457.09 | D72: ='[7]Mensal USD'!$R$61 -> 663.85931 | E72: =D72*C72/1000 -> 120461.98 | F72: =F39 -> 136271.79 | I72: =(J39-F72)*D72/1000 -> 27901.766
A73: 80 | B73: ALZn DM Downstream | C73: =C40 -> 106335.88 | D73: =D72+A73 -> 743.85931 | E73: =D73*C73/1000 -> 79098.934 | F73: =F40 -> 88523.367 | I73: =(J40-F73)*D73/1000 -> 11874.419
B74: Usibor DM Auto | C74: =C41 -> 94231.595 | D74: ='[7]Mensal USD'!$R$71 -> 572.84269 | E74: =D74*C74/1000 -> 53979.88 | F74: =F41 -> 99323.021 | I74: =(J41-F74)*D74/1000 -> -3855.3334
B75: AlSi DM Industry | C75: =C42 -> 7737.54 | D75: =D74 -> 572.84269 | E75: =D75*C75/1000 -> 4432.3932 | F75: =F42 -> 7661.225 | I75: =(J42-F75)*D75/1000 -> -33.365871
B76: Auto Imports/PP DM | C76: =C43 -> 3816.3262 | D76: =D72 -> 663.85931 | E76: =D76*C76/1000 -> 2533.5037 | F76: =F43 -> 3627.2929 | I76: =(J43-F76)*D76/1000 -> 81.432139
B77: =B44 -> Magnelis DM Industry | C77: =C44 -> 0 | D77: =D71 -> 663.85931 | E77: =D77*C77/1000 -> 0 | F77: =F44 -> 10000 | I77: =(J44-F77)*D77/1000 -> -6638.5931
B78: =B45 -> Industry Imports | C78: =C45 -> 35399.97 | D78: =D72 -> 663.85931 | E78: =D78*C78/1000 -> 23500.6 | F78: =F45 -> 17169.268 | I78: =(J45-F78)*D78/1000 -> 11693.93
B79: =B46 -> Magnelis DM Downstream | C79: =C46 -> 0 | D79: =D77 -> 663.85931 | E79: =D79*C79/1000 -> 0 | F79: =F46 -> 7002.88 | I79: =(J46-F79)*D79/1000 -> -4648.9271
B80: =B47 -> HRC Aperam baixo carbono | C80: =C47 -> 0 | D80: =D47-30 -> -30 | E80: =D80*C80/1000 -> 0 | F80: =F47 -> 0 | I80: =(J47-F80)*D80/1000 -> 0
B81: Total Variable Cost | C81: =SUM(C50:C80) -> 7232333.7 | D81: =+E81/C81*1000 -> 477.93402 | E81: =SUM(E50:E80) -> 3456578.3 | F81: =SUM(F50:F80) -> 7106558.5 | I81: =SUM(I50:I80) -> 8451.3804
B82: Contribution | C82: kt | D82: USD/t | E82: kUSD | F82: kt | I82: Mix | J82: Var Vol | K82: Vol & Mix | L82: Volume
B83: Slab Calvert | C83: =C50 -> 961000 | D83: =D17-D50 -> 84.272668 | E83: =E17-E50 -> 80986.034 | F83: =F50 -> 966247.87 | I83: =+I17+I50 -> 1850.6547 | J83: =F17-C17 -> 5247.87 | K83: =J83*D83/1000 -> 442.25201 | L83: =K83-I83 -> -1408.4027 | M83: =J83/C83 -> 0.0054608429 | P83: =I83+L83 -> 442.25201
B84: Slabs Others Intragroup | C84: =C51 -> 400000 | D84: =D18-D51 -> 28.199955 | E84: =E18-E51 -> 11279.982 | F84: =F51 -> 997327.08 | I84: =+I18+I51 -> 17040.763 | J84: =F18-C18 -> 597327.08 | K84: =J84*D84/1000 -> 16844.597 | L84: =K84-I84 -> -196.16663 | M84: =J84/C84 -> 1.4933177 | P84: =I84+L84 -> 16844.597
B85: Slabs 3rd Party | C85: =C52 -> 1423164.4 | D85: =D19-D52 -> 36.906952 | E85: =E19-E52 -> 52524.66 | F85: =F52 -> 874385.04 | I85: =+I19+I52 -> -19340.333 | J85: =F19-C19 -> -548779.34 | K85: =J85*D85/1000 -> -20253.773 | L85: =K85-I85 -> -913.4399
B86: Slab DM | C86: =C53 -> 31000 | D86: =D20-D53 -> 0.72748999 | E86: =E20-E53 -> 22.55219 | F86: =F53 -> 32424.16 | I86: =+I20+I53 -> 1.4282602 | J86: =F20-C20 -> 1424.16 | K86: =J86*D86/1000 -> 1.0360621 | L86: =K86-I86 -> -0.39219806 | M86: =J86/C86 -> 0.045940645 | P86: =I86+L86 -> 1.0360621
B87: Plates DM | C87: =C54 -> 18000 | D87: =D21-D54 -> 269.02612 | E87: =E21-E54 -> 4842.4702 | F87: =F54 -> 16529.16 | I87: =+I21+I54 -> -311.4805 | J87: =F21-C21 -> -1470.84 | K87: =J87*D87/1000 -> -395.69438 | L87: =K87-I87 -> -84.213882 | M87: =J87/C87 -> -0.081713333 | P87: =I87+L87 -> -395.69438
B88: HRC Export | C88: =C55 -> 433467 | D88: =D22-D55 -> 36.052263 | E88: =E22-E55 -> 15627.466 | F88: =F55 -> 197566.82 | I88: =+I22+I55 -> -8232.963 | J88: =F22-C22 -> -235900.18 | K88: =J88*D88/1000 -> -8504.7354 | L88: =K88-I88 -> -271.77237 | M88: =J88/C88 -> -0.54421716 | P88: =I88+L88 -> -8504.7354
B89: HRC DM Auto | C89: =C56 -> 85817.96 | D89: =D23-D56 -> 244.22864 | E89: =E23-E56 -> 20959.204 | F89: =F56 -> 100236.84 | I89: =+I23+I56 -> 3885.9985 | J89: =F23-C23 -> 14418.88 | K89: =J89*D89/1000 -> 3521.5036 | L89: =K89-I89 -> -364.49495 | M89: =J89/C89 -> 0.16801705 | O89: =K89 -> 3521.5036 | P89: =I89+L89 -> 3521.5036 | Q89: =C89*D89 -> 20959204 | R89: =C89 -> 85817.96 | S89: =F89 -> 100236.84
B90: HRC DM Industry | C90: =C57 -> 1438681.3 | D90: =D24-D57 -> 221.55976 | E90: =E24-E57 -> 318753.89 | F90: =F57 -> 1441770.7 | I90: =+I24+I57 -> 6227.8392 | J90: =F24-C24 -> 3089.416 | K90: =J90*D90/1000 -> 684.49027 | L90: =K90-I90 -> -5543.349 | M90: =J90/C90 -> 0.0021473943 | P90: =I90+L90 -> 684.49027
B91: HRC DM Downstream | C91: =C58 -> 427373.81 | D91: =D25-D58 -> 238.2919 | E91: =E25-E58 -> 101839.72 | F91: =F58 -> 446359.43 | I91: =+I25+I58 -> 6295.1832 | J91: =F25-C25 -> 18985.624 | K91: =J91*D91/1000 -> 4524.1206 | L91: =K91-I91 -> -1771.0626 | M91: =J91/C91 -> 0.04442393 | P91: =I91+L91 -> 4524.1206
B92: P&O DM Auto | C92: =C59 -> 102999.19 | D92: =D26-D59 -> 341.99386 | E92: =E26-E59 -> 35225.09 | F92: =F59 -> 90523.858 | I92: =+I26+I59 -> -3653.8985 | J92: =F26-C26 -> -12475.332 | K92: =J92*D92/1000 -> -4266.487 | L92: =K92-I92 -> -612.5885 | M92: =J92/C92 -> -0.12112068 | O92: =K92 -> -4266.487 | P92: =I92+L92 -> -4266.487 | Q92: =C92*D92 -> 35225090 | R92: =C92 -> 102999.19 | S92: =F92 -> 90523.858
B93: P&O DM Industry | C93: =C60 -> 0 | D93: =D27-D60 -> 269.38858 | E93: =E27-E60 -> 0 | F93: =F60 -> 45424.208 | I93: =+I27+I60 -> 12236.763 | J93: =F27-C27 -> 45424.208 | K93: =J93*D93/1000 -> 12236.763 | L93: =K93-I93 -> 0 | M93: =J93/C93 -> #DIV/0! | P93: =I93+L93 -> 12236.763
B94: CRC EM Auto | C94: =C61 -> 1220.3924 | D94: =D28-D61 -> 388.26831 | E94: =E28-E61 -> 473.83968 | F94: =F61 -> 1887.8106 | I94: =+I28+I61 -> 267.37773 | J94: =F28-C28 -> 667.41819 | K94: =J94*D94/1000 -> 259.13734 | L94: =K94-I94 -> -8.2403974 | M94: =J94/C94 -> 0.54688821 | O94: =K94 -> 259.13734 | P94: =I94+L94 -> 259.13734
B95: CRC EM Industry | C95: =C62 -> 492.26 | D95: =D29-D62 -> -171.40909 | E95: =E29-E62 -> -84.377839 | F95: =F62 -> 4847.375 | I95: =+I29+I62 -> -747.97369 | J95: =F29-C29 -> 4355.115 | K95: =J95*D95/1000 -> -746.5063 | L95: =K95-I95 -> 1.4673885 | M95: =J95/C95 -> 8.8471844 | P95: =I95+L95 -> -746.5063
B96: CRC DM Auto | C96: =C63 -> 90127.47 | D96: =D30-D63 -> 427.2982 | E96: =E30-E63 -> 38511.306 | F96: =F63 -> 95622.293 | I96: =+I30+I63 -> 3017.666 | J96: =F30-C30 -> 5494.8228 | K96: =J96*D96/1000 -> 2347.9279 | L96: =K96-I96 -> -669.73805 | M96: =J96/C96 -> 0.060967237 | O96: =K96 -> 2347.9279 | P96: =I96+L96 -> 2347.9279 | Q96: =C96*D96 -> 38511306 | R96: =C96 -> 90127.47 | S96: =F96 -> 95622.293
B97: CRC DM Industry | C97: =C64 -> 265325.54 | D97: =D31-D64 -> 293.49176 | E97: =E31-E64 -> 77870.861 | F97: =F64 -> 286122.32 | I97: =+I31+I64 -> 7457.9109 | J97: =F31-C31 -> 20796.778 | K97: =J97*D97/1000 -> 6103.6832 | L97: =K97-I97 -> -1354.2277 | M97: =J97/C97 -> 0.07838212 | P97: =I97+L97 -> 6103.6832
B98: CRC DM Downstream | C98: =C65 -> 110301.97 | D98: =D32-D65 -> 258.7764 | E98: =E32-E65 -> 28543.546 | F98: =F65 -> 117390.91 | I98: =+I32+I65 -> 2330.8425 | J98: =F32-C32 -> 7088.941 | K98: =J98*D98/1000 -> 1834.4506 | L98: =K98-I98 -> -496.39186 | M98: =J98/C98 -> 0.064268489 | P98: =I98+L98 -> 1834.4506 | W98: =160+217 -> 377
B99: HDG EM Auto | C99: =C66 -> 49551.853 | D99: =D33-D66 -> 445.45556 | E99: =E33-E66 -> 22073.148 | F99: =F66 -> 41148.524 | I99: =+I33+I66 -> -3359.4427 | J99: =F33-C33 -> -8403.3296 | K99: =J99*D99/1000 -> -3743.3099 | L99: =K99-I99 -> -383.8672 | M99: =J99/C99 -> -0.16958659 | O99: =K99 -> -3743.3099 | P99: =I99+L99 -> -3743.3099
B100: HDG EM Industry | C100: =C67 -> 1014.12 | D100: =D34-D67 -> -268.88972 | E100: =E34-E67 -> -272.68645 | F100: =F67 -> 2599.121 | I100: =+I34+I67 -> -430.93269 | J100: =F34-C34 -> 1585.001 | K100: =J100*D100/1000 -> -426.19048 | L100: =K100-I100 -> 4.7422045 | M100: =J100/C100 -> 1.5629324 | P100: =I100+L100 -> -426.19048
...

Sheet Analise mes carvão
C1: Bridge | D1: Var. | E1: KD | G1: IP
B2: Budget vs MRF1 | C2: =[18]Box!$U$6+[18]Box!$U$7 -> -23.455538 | D2: =C2 -> -23.455538 | E2: =F14 -> -23.830202 | F2: =C2-E2 -> 0.37466398
B3: Budget vs MRF2 | C3: =([19]Cálculo!$J$116+[19]Cálculo!$J$117)/1000 -> -35.675657 | D3: =C3-C2 -> -12.220118 | E3: ='[20]Bridge FY'!$F$5 -> -12.315596 | F3: =D3-E3 -> 0.09547828
B4: Budget vs MRF3 | C4: =[21]Box!$U$6+[21]Box!$U$7 -> -38.600114 | D4: =C4-C3 -> -2.9244573 | E4: =L14 -> -3 | F4: =D4-E4 -> 0.075542655
B5: Budget vs MRF4 | C5: =[22]Box!$U$6+[22]Box!$U$7 -> -29.067403 | D5: =C5-C4 -> 9.5327109 | E5: =O14 -> 7.2991734 | F5: =D5-E5 -> 2.2335375
B6: Budget vs MRF5 | C6: =[23]Box!$U$6+[23]Box!$U$7 -> -30.958568 | D6: =C6-C5 -> -1.8911646 | E6: =R14 -> 0 | F6: =D6-E6 -> -1.8911646
B7: Budget vs MRF6 | C7: =Box!$U$6+Box!$U$7 -> -95.378798 | D7: =C7-C6 -> -64.42023 | E7: =U14 -> 1.6357735 | F7: =D7-E7 -> -66.056003
D8: =SUM(D2:D7) -> -95.378798 | E8: =SUM(E2:E7) -> -30.210852
E10: MRF1 | H10: MRF2 | K10: mrf3 | N10: mrf4 | Q10: mrf5
E11: Input Price | H11: Input Price | K11: Input Price | N11: Input Price | Q11: Input Price | T11: Input Price
E13: =A13 -> 0 | F13: =F15+F16+F17 -> -23.830202 | H13: Impact | I13: MUSD | K13: Impact | L13: MUSD | N13: =K13 -> Impact | O13: MUSD | Q13: Impact | R13: MUSD | T13: Impact | U13: MUSD
E14: Coal | F14: -23.830202 | H14: Coal | I14: -12.315596 | K14: Coal | L14: -3 | N14: Coal | O14: 7.2991734 | Q14: Coal | R14: 0 | T14: Coal | U14: 1.6357735
E15: International ref. | F15: -12.762719 | H15: Internacional reference | I15: -14.315596 | K15: Mix | L15: -5 | N15: International ref. | O15: 12 | Q15: International ref. | R15: 0 | T15: Price (may) | U15: 3
E16: Starting balance | F16: -13.216352 | H16: Mix/Others | I16: 2 | K16: Q2 PCI ratio | L16: 4 | N16: Q3 PCI ratio | O16: 5.3 | Q16: Mix | R16: 0 | T16: AMS contract updates | U16: 6
E17: Mix / others | F17: 2.148869 | H17: Purchased Coke | I17: -0.49931138 | K17: Demurrage | L17: -2 | N17: Freight | O17: -2 | Q17: Purchased Coke | R17: 0 | T17: (Price) PCI index | U17: -1.2956606
E18: Purchased Coke | F18: -5.9951706 | H18: Iron ore | I18: 6.3784712 | K18: Purchased Coke | L18: 0 | N18: Purchased Coke | O18: 2.5347094 | Q18: Iron ore | R18: -11.161322 | T18: Demurrage | U18: -3.0685658
E19: Iron ore | F19: -32.404121 | H19: Internacional reference | I19: 5.8423735 | K19: Iron ore | L19: 3.6635359 | N19: Mix | O19: -8 | Q19: International ref. | R19: -11.161322 | T19: Mix | U19: -3
E20: International ref. | F20: -17.602787 | H20: VIU premium (Si, Al & P) | I20: 2 | K20: International ref. | L20: 11.963352 | N20: Iron ore | O20: 59.494899 | Q20: Scrap | R20: 0 | T20: Purchased Coke | U20: 0.38990434
E21: Netback freight | F21: -5.5778136 | H21: % Fe | I21: -1.4639022 | K21: Pellet premium in Q2 | L21: -12.301144 | N21: International ref. | O21: 49.727698 | Q21: Alloys | R21: 0.13 | T21: Iron ore | U21: 2.2260463
E22: Pellet premium | F22: -9.2235212 | H22: Alloys | I22: -0.06 | K22: VIU Vale contract | L22: 4.4431404 | N22: Netback freight | O22: 17.634238 | Q22: Zinc (Vega) | R22: -1.47 | T22: International ref. | U22: -6.2737641
E23: Alloys | F23: -0.29 | H23: Zinc (Vega) | I23: 0.63 | K23: Alloys | L23: -0.27 | N23: Pellet premium | O23: -6.2029299 | Q23: Fluxes | R23: 0 | T23: Pellet premium | U23: 3.1816105
E24: Zinc (Vega) | F24: 0.86 | H24: Fluxes | I24: 0 | K24: Zinc (Vega) | L24: 0.79 | N24: VIU Vale contract | O24: -1.4641068 | Q24: Total | R24: -12.401322 | T24: Vale contract specification H2 | U24: 5.3182
E25: Fluxes | F25: 2 | H25: Total | I25: -5.8664365 | K25: Fluxes | L25: 3 | N25: Scrap | O25: 1.0073149 | T25: Scrap | U25: 0
E26: Total | F26: -59.659494 | K26: Total | L26: 4.1835359 | N26: Alloys | O26: 0.62 | T26: Alloys | U26: -2.35
N27: Zinc (Vega) | O27: 2.95 | T27: Zinc (Vega) | U27: 1.05
N28: Fluxes | O28: 0 | T28: Fluxes | U28: 1.32
N29: Total | O29: 73.906097 | T29: Total | U29: 4.2717242

Sheet Box
CD1: Consolidado | CG1: Pecém | CK1: Tuper
B2: Volume & Mix | I2: Selling price | P2: Input price | W2: Usage | Z2: Usage - Op. Performance | AC2: Usage - Market driven | AG2: Exchange rate | AO2: Logistic | AR2: Stock Variation/Others | AW2: Fixed cost | AZ2: Vale issues | BE2: AMS consolidation | BH2: For information only - Blacks & Reds | BQ2: For information only - Demurrage | BV2: FIO - Middle East War (Iran) | CA2: For information only - Forex | CD2: For information only - Forex | CG2: For information only - Forex | CK2: For information only - Forex | CN2: For information only - Middle East war
B4: Vol (kt) | C4: =J4 -> FY26'B | D4: =K4 -> FY26'F7 | E4: Var | F4: ="CM "&C4 -> CM FY26'B | G4: MUSD | I4: NRP $/t | J4: =Cálculo!D15 -> FY26'B | K4: =Cálculo!G15 -> FY26'F7 | L4: Var | M4: ="Vol "&K4 -> Vol FY26'F7 | N4: MUSD | P4: Price $/t | Q4: =J16 -> FY26'B | R4: =K16 -> FY26'F7 | S4: Var | T4: Yield | U4: MUSD | W4: Usage | X4: MUSD | Z4: Usage | AA4: MUSD | AC4: Usage | AD4: MUSD | AG4: Forex | AH4: =Cálculo!G15 -> FY26'F7 | AI4: % BRL | AK4: =Cálculo!G15 -> FY26'F7 | AL4: =Cálculo!D15 -> FY26'B | AM4: MUSD | AO4: Logistic | AP4: MUSD | AR4: Others | AS4: =AL4 -> FY26'B | AT4: =AK4 -> FY26'F7 | AU4: MUSD | AW4: Fixed cost | AX4: MUSD | AZ4: Vale issues | BA4: FY20 | BB4: FY21 | BC4: MUSD | BE4: =BE2 -> AMS consolidation | BF4: MUSD | BH4: Price $/t | BI4: FY26'B | BJ4: FY26'F7 | BK4: Var | BL4: kt | BM4: $m | BQ4: Demurrage | BR4: FY25B | BS4: FY25F | BT4: $m | BV4: Impact | BW4: MUSD | CA4: Impact | CB4: MUSD | CD4: Impact | CE4: MUSD | CG4: Impact | CH4: MUSD | CK4: Impact | CL4: MUSD | CN4: Impact | CO4: MUSD
B5: Slab Calvert | C5: =Cálculo!C17/1000 -> 961 | D5: =Cálculo!F17/1000 -> 966.24787 | E5: =D5-C5 -> 5.24787 | F5: =Cálculo!D83 -> 84.272668 | G5: =E5*F5/1000 -> 0.44225201 | H5: =Cálculo!P83/1000 -> 0.44225201 | I5: Slab Calvert | J5: =Cálculo!D17 -> 521.64672 | K5: =Cálculo!G17 -> 611.989 | L5: =K5-J5 -> 90.342283 | M5: =D5 -> 966.24787 | N5: =L5*M5/1000 -> 87.293039 | P5: Blacks | U5: =U6+U7+U9+U10 -> -91.531139 | W5: ='[10]Bridges complementares'!$E$5 -> Operational performance | X5: ='[10]Bridges complementares'!$F$5 -> -4.0925449 | Z5: =W5 -> Operational performance | AA5: =X5 -> -4.0925449 | AC5: =W16 -> Market driven | AD5: =X16 -> -8.7367984 | AG5: Sales Ind | AH5: =Cálculo!G150/1000 -> 5141.0891 | AI5: =AJ5/AH5 -> 0.47860693 | AJ5: =Cálculo!K13/1000 -> 2460.5609 | AK5: =Cálculo!H152 -> 5.1762144 | AL5: =Cálculo!E152 -> 5.4 | AM5: =Cálculo!Q10/1000 -> 104.08293 | AO5: Volume/mix | AP5: -3 | AR5: =Cálculo!B175 -> Invest-ES | AS5: =Cálculo!E175/1000 -> 134.78471 | AT5: =Cálculo!H175/1000 -> 129.88814 | AU5: =Cálculo!I175/1000 -> -4.896564 | AW5: =[8]FYB26xFYMRF7!$P$21 -> Controllable | AX5: =[8]FYB26xFYMRF7!$Q$21 -> -2.8984408 | AZ5: Vale issues | BA5: =#REF! -> #REF! | BB5: =#REF! -> #REF! | BH5: Coal (2 month lag) | BI5: ='[24]Coal lag_2months'!$O$3 -> 183.25 | BJ5: ='[24]Coal lag_2months'!$O$10 -> 231.6375 | BK5: =BJ5-BI5 -> 48.3875 | BL5: =SUM(Cálculo!I128)*Cálculo!G144 -> 2769.4034 | BM5: =-BK5*BL5/1000 -> -134.00451 | BQ5: Inbound | BR5: =BR6+BR7 -> 25 | BS5: =BS6+BS7 -> 19.7 | BT5: =BT6+BT7 -> 5.3 | BV5: Netback freight | BW5: 3 | CA5: =AG5 -> Sales Ind | CB5: =AM5 -> 104.08293 | CD5: =CA5 -> Sales Ind | CE5: =CB5+CL5 -> 106.28293 | CG5: =CD7 -> COGS | CH5: -23 | CK5: =CD5 -> Sales Ind | CL5: 2.2 | CN5: Slab sales | CO5: 17
B6: Slabs Others Intragroup | C6: =Cálculo!C18/1000 -> 400 | D6: =Cálculo!F18/1000 -> 997.32708 | E6: =D6-C6 -> 597.32708 | F6: =Cálculo!D84 -> 28.199955 | G6: =E6*F6/1000 -> 16.844597 | H6: =Cálculo!P84/1000 -> 16.844597 | I6: Slabs Others Intragroup | J6: =Cálculo!D18 -> 444.574 | K6: =Cálculo!G18 -> 516.61738 | L6: =K6-J6 -> 72.04338 | M6: =D6 -> 997.32708 | N6: =L6*M6/1000 -> 71.850814 | P6: Coal | Q6: =Cálculo!D128 -> 192.44908 | R6: =Cálculo!G128 -> 209.83033 | S6: =R6-Q6 -> 17.381256 | T6: =Cálculo!I128 -> 0.39731562 | U6: =-S6*T6*$U$23/1000 -> -48.13571 | V6: =(Cálculo!J128+Cálculo!J129)/1000 -> -95.378798 | W6: ='[10]Bridges complementares'!E6 -> Ironmaking | X6: ='[10]Bridges complementares'!F6 -> -3.3995496 | Z6: =W6 -> Ironmaking | AA6: =X6 -> -3.3995496 | AC6: =W17 -> Alloys | AD6: =X17 -> -6.5367984 | AG6: Sales Auto | AI6: =AJ6/AH5 -> 0.18090952 | AJ6: =Cálculo!K14/1000 -> 930.07195 | AM6: =Cálculo!Q11/1000 -> 39.317984 | AO6: Cabotage freight to south | AP6: -3 | AR6: Extraordinary effects | AS6: =AS7 -> 0 | AT6: =AT7 -> 0.14979323 | AU6: =AU7 -> 0.14979323 | AW6: =[8]FYB26xFYMRF7!$P$22 -> 2025 CLA | AX6: =[8]FYB26xFYMRF7!$Q$22 -> -3.7644492 | AZ6: Total | BC6: =BC5 -> 0 | BE6: Total | BF6: =SUM(BF5:BF5) -> 0 | BH6: FC Latam basket/mix/open balance | BM6: =BM11-SUM(BM7:BM10,BM5:BM5) -> 96.789906 | BQ6: Coal | BR6: 23 | BS6: 17.7 | BT6: =-BS6+BR6 -> 5.3 | BV6: Natural gas | BW6: =-(0.3+0.8) -> -1.1 | CA6: =AG6 -> Sales Auto | CB6: =AM6 -> 39.317984 | CD6: =CA6 -> Sales Auto | CE6: =CB6 -> 39.317984 | CG6: =CD8 -> Forex from inventories | CH6: -8 | CK6: Total | CL6: =SUM(CL5:CL6) -> 2 | CN6: Index cost | CO6: -131
B7: Slabs 3rd Party | C7: =Cálculo!C19/1000 -> 1423.1644 | D7: =Cálculo!F19/1000 -> 874.38504 | E7: =D7-C7 -> -548.77934 | F7: =Cálculo!D85 -> 36.906952 | G7: =E7*F7/1000 -> -20.253773 | H7: =Cálculo!P85/1000 -> 0 | I7: Slabs 3rd Party | J7: =Cálculo!D19 -> 453.281 | K7: =Cálculo!G19 -> 520.32299 | L7: =K7-J7 -> 67.04199 | M7: =D7 -> 874.38504 | N7: =L7*M7/1000 -> 58.620514 | P7: PCI | Q7: =Cálculo!D129 -> 193.47908 | R7: =Cálculo!G129 -> 218.48672 | S7: =R7-Q7 -> 25.007643 | T7: =Cálculo!I129 -> 0.27102848 | U7: =-S7*T7*$U$23/1000 -> -47.243088 | W7: ='[10]Bridges complementares'!E7 -> Steelmaking | X7: ='[10]Bridges complementares'!F7 -> -3 | Z7: =W7 -> Steelmaking | AA7: =X7 -> -3 | AC7: =W18 -> Coated lines | AD7: =X18 -> -2.2 | AG7: COGS | AH7: =Cálculo!G151/1000 -> -4393.3967 | AI7: =AJ7/AH7 -> 0.4 | AJ7: =Cálculo!H151/1000 -> -1757.3587 | AM7: =AJ7-(AJ7*AK5)/AL5 -> -72.828056 | AO7: Total | AP7: =AP5+AP6 -> -6 | AR7: =Cálculo!B160 -> Legal contingency | AS7: =Cálculo!E160/1000 -> 0 | AT7: =Cálculo!H160/1000 -> 0.14979323 | AU7: =(Cálculo!I160)/1000 -> 0.14979323 | AW7: =[8]FYB26xFYMRF7!$P$23 -> Publicity | AX7: =[8]FYB26xFYMRF7!$Q$23 -> 0.86600845 | BH7: Freight | BM7: =[9]FY_Budget!$AH$13 -> -7.3567876 | BQ7: Coke | BR7: 2 | BS7: 2 | BT7: =-BS7+BR7 -> 0 | BV7: Sales freight | BW7: -0.7 | CA7: =AG7 -> COGS | CB7: =AM7 -> -72.828056 | CD7: =CA7 -> COGS | CE7: =CB7+CH5 -> -95.828056 | CG7: Total | CH7: =SUM(CH5:CH6) -> -31 | CN7: Freight cost | CO7: 35
B8: HRC | C8: =Cálculo!C22/1000 -> 433.467 | D8: =Cálculo!F22/1000 -> 197.56682 | E8: =D8-C8 -> -235.90018 | F8: =Cálculo!D88 -> 36.052263 | G8: =E8*F8/1000 -> -8.5047354 | H8: =Cálculo!P88/1000 -> -8.5047354 | I8: HRC | J8: =Cálculo!D22 -> 482.26451 | K8: =Cálculo!G22 -> 557.07307 | L8: =K8-J8 -> 74.80856 | M8: =D8 -> 197.56682 | N8: =L8*M8/1000 -> 14.779689 | P8: Antracite | Q8: =Cálculo!D130 -> 0 | R8: =Cálculo!G130 -> 0 | S8: =R8-Q8 -> 0 | T8: =Cálculo!I130 -> 0 | U8: =-S8*T8*$U$23/1000 -> 0 | V8: =U6+U7 -> -95.378798 | W8: ='[10]Bridges complementares'!E8 -> Contractors | X8: ='[10]Bridges complementares'!F8 -> -2.4892741 | Z8: =W8 -> Contractors | AA8: =X8 -> -2.4892741 | AC8: Total | AD8: =AD5 -> -8.7367984 | AG8: Total | AM8: =SUM(AM5:AM7) -> 70.572859 | AR8: SV/Others | AU8: =Cálculo!C12-SUM(AU5:AU6) -> 0.30957452 | AW8: =[8]FYB26xFYMRF7!$P$24 -> Non-controllable | AX8: =[8]FYB26xFYMRF7!$Q$24 -> -5.4086265 | BH8: Demurrage | BM8: 3 | BQ8: Outbound | BR8: 3 | BS8: 1.88 | BT8: =-BS8+BR8 -> 1.12 | BV8: Total | BW8: =SUM(BW5:BW7) -> 1.2 | CA8: =AR10 -> Forex from inventories | CB8: =AU10 -> -20.388072 | CD8: =CA8 -> Forex from inventories | CE8: =CB8+CH6 -> -28.388072 | CN8: Total | CO8: =SUM(CO5:CO7) -> -79
B9: CRC Auto | C9: =Cálculo!C28/1000 -> 1.2203924 | D9: =Cálculo!F28/1000 -> 1.8878106 | E9: =D9-C9 -> 0.66741819 | F9: =Cálculo!D94 -> 388.26831 | G9: =E9*F9/1000 -> 0.25913734 | H9: =Cálculo!P94/1000 -> 0.25913734 | I9: CRC Auto | J9: =Cálculo!D28 -> 882.99234 | K9: =Cálculo!G28 -> 937.18709 | L9: =K9-J9 -> 54.194756 | M9: =D9 -> 1.8878106 | N9: =L9*M9/1000 -> 0.10230943 | P9: Coke | Q9: =Cálculo!D131 -> 312.92945 | R9: =Cálculo!G131 -> 340.61823 | S9: =R9-Q9 -> 27.688782 | T9: =Cálculo!I131 -> 0.014076067 | U9: =-S9*T9*$U$23/1000 -> -2.7166629 | V9: =V8-V6 -> 0 | W9: ='[10]Bridges complementares'!E9 -> Others | X9: ='[10]Bridges complementares'!F9 -> -1 | Z9: =W9 -> Others | AA9: =X9 -> -1 | AR9: =Cálculo!B168 -> Slowmoving | AS9: =Cálculo!E168/1000 -> 0 | AT9: =Cálculo!H168/1000 -> -2.6041187 | AU9: =Cálculo!H168/1000 -> -2.6041187 | AW9: =[8]FYB26xFYMRF7!$P$25 -> Pension Plan (Actuarial calculation) | AX9: =[8]FYB26xFYMRF7!$Q$25 -> -5.0981563 | BH9: PCI | BM9: =U7 -> -47.243088 | BQ9: Total | BR9: =BR5+BR8 -> 28 | BS9: =BS5+BS8 -> 21.58 | BT9: =BT8+BT5 -> 6.42 | CA9: Total | CB9: =SUM(CB5:CB8) -> 50.184787 | CD9: Total | CE9: =SUM(CE5:CE8) -> 21.384787
B10: CRC Ind | C10: =Cálculo!C29/1000 -> 0.49226 | D10: =Cálculo!F29/1000 -> 4.847375 | E10: =D10-C10 -> 4.355115 | F10: =Cálculo!D95 -> -171.40909 | G10: =E10*F10/1000 -> -0.7465063 | H10: =Cálculo!P95/1000 -> -0.7465063 | I10: CRC Ind | J10: =Cálculo!D29 -> 323.31493 | K10: =Cálculo!G29 -> 603.52341 | L10: =K10-J10 -> 280.20848 | M10: =D10 -> 4.847375 | N10: =L10*M10/1000 -> 1.3582756 | P10: AMS fee | Q10: =Cálculo!D132 -> 72.724806 | R10: =Cálculo!G132 -> 75.803894 | U10: =Cálculo!J137/1000 -> 6.5643217 | W10: ='[10]Bridges complementares'!E10 -> AMV | X10: ='[10]Bridges complementares'!F10 -> 5.7962788 | Z10: =W10 -> AMV | AA10: =X10 -> 5.7962788 | AR10: Forex from inventories | AU10: ='[25]Forex MRF 2026'!$EV$30 -> -20.388072 | AW10: =[8]FYB26xFYMRF7!$P$26 -> Insurance | AX10: =[8]FYB26xFYMRF7!$Q$26 -> 0.6895298 | BH10: Coke price | BM10: =U9-BT7 -> -2.7166629 | CN10: For information only - Middle East war
B11: HDG Auto | C11: =Cálculo!C33/1000 -> 49.551853 | D11: =Cálculo!F33/1000 -> 41.148524 | E11: =D11-C11 -> -8.4033296 | F11: =Cálculo!D99 -> 445.45556 | G11: =E11*F11/1000 -> -3.7433099 | H11: =Cálculo!P99/1000 -> -3.7433099 | I11: HDG Auto | J11: =Cálculo!D33 -> 1018.0181 | K11: =Cálculo!G33 -> 1058.4157 | L11: =K11-J11 -> 40.397668 | M11: =D11 -> 41.148524 | N11: =L11*M11/1000 -> 1.6623044 | P11: Reds | U11: =U12+U13+U14 -> -54.073371 | W11: ='[10]Bridges complementares'!E11 -> 0 | X11: ='[10]Bridges complementares'!F11 -> 0 | Z11: Total | AA11: =SUM(AA6:AA10) -> -4.0925449 | AK11: =AK5-AL5 -> -0.22378556 | AR11: Stock variation | AU11: =Cálculo!C12-SUM(AU5:AU6)-AU10-AU9 -> 23.301765 | AW11: =[8]FYB26xFYMRF7!$P$27 -> Others | AX11: =[8]FYB26xFYMRF7!$Q$27 -> -1 | BH11: Total | BM11: =U6+U7+U9+U10 -> -91.531139
B12: HDG Ind | C12: =Cálculo!C34/1000 -> 1.01412 | D12: =Cálculo!F34/1000 -> 2.599121 | E12: =D12-C12 -> 1.585001 | F12: =Cálculo!D100 -> -268.88972 | G12: =E12*F12/1000 -> -0.42619048 | H12: =Cálculo!P100/1000 -> -0.42619048 | I12: HDG Ind | J12: =Cálculo!D34 -> 323.31493 | K12: =Cálculo!G34 -> 562.09665 | L12: =K12-J12 -> 238.78171 | M12: =D12 -> 2.599121 | N12: =L12*M12/1000 -> 0.62062257 | P12: Fines | Q12: =Cálculo!D132 -> 72.724806 | R12: =Cálculo!G132 -> 75.803894 | S12: =R12-Q12 -> 3.079088 | T12: =Cálculo!I132 -> 0.50546148 | U12: =-S12*T12*$U$23/1000 -> -10.848277 | W12: ='[10]Bridges complementares'!E12 -> 0 | X12: ='[10]Bridges complementares'!F12 -> 0 | AM12: =AM7+'Bridge combinada'!J15 -> -95.358056 | AR12: Total | AU12: =AU5+AU6+AU8 -> -4.4371962 | AW12: =[8]FYB26xFYMRF7!$P$28 -> Value Creation | AX12: =[8]FYB26xFYMRF7!$Q$28 -> -25.047168 | CN12: Impact | CO12: MUSD
B13: AlZn Ind | C13: =Cálculo!C38/1000 -> 0 | D13: =Cálculo!F38/1000 -> 0 | E13: =D13-C13 -> 0 | F13: =Cálculo!D104 -> -663.85931 | G13: =E13*F13/1000 -> 0 | H13: =Cálculo!P104/1000 -> 0 | I13: AlZn Ind | J13: =Cálculo!D38 -> 0 | K13: =Cálculo!G38 -> 0 | L13: =K13-J13 -> 0 | M13: =D13 -> 0 | N13: =L13*M13/1000 -> 0 | P13: Pellets | Q13: =Cálculo!D133 -> 121.43893 | R13: =Cálculo!G133 -> 128.95793 | S13: =R13-Q13 -> 7.5189958 | T13: =Cálculo!I133 -> 0.7869986 | U13: =-S13*T13*$U$23/1000 -> -41.246241 | W13: ='[10]Bridges complementares'!E13 -> 0 | X13: ='[10]Bridges complementares'!F13 -> 0 | AW13: =[8]FYB26xFYMRF7!$P$29 -> 2026 PSP Complement | AX13: =[8]FYB26xFYMRF7!$Q$29 -> -14.275973 | BH13: =BH4 -> Price $/t | BI13: =BI4 -> FY26'B | BJ13: =BJ4 -> FY26'F7 | BK13: =BK4 -> Var | BL13: =BL4 -> kt | BM13: =BM4 -> $m | BO13: =BM11-SUM(BM5:BM10) -> 0 | CN13: Slab sales | CO13: 9
B14: Export | C14: =SUM(C5:C13) -> 3269.91 | D14: =SUM(D5:D13) -> 3086.0096 | E14: =SUM(E5:E13) -> -183.90036 | G14: =SUM(G5:G13) -> -16.128529 | H14: =SUM(H5:H13) -> 4.125244 | I14: Export | N14: =SUM(N5:N13) -> 236.28757 | P14: Lumps | Q14: =Cálculo!D134 -> 82.183924 | R14: =Cálculo!G134 -> 83.470247 | S14: =R14-Q14 -> 1.286323 | T14: =Cálculo!I134 -> 0.2207054 | U14: =-S14*T14*$U$23/1000 -> -1.9788532 | AM14: =AL5-AK5 -> 0.22378556 | AW14: =[8]FYB26xFYMRF7!$P$30 -> 2025 PSP Complement | AX14: =[8]FYB26xFYMRF7!$Q$30 -> -8.7711955 | BH14: Iron ore MB 62% (1m lag) | BI14: ='[26]Premissa - Budget 2026'!$U$7 -> 96.416667 | BJ14: ='[27]Premissa - MRF'!$U$7 -> 102.62247 | BK14: =BJ14-BI14 -> 6.2058 | BL14: =SUM(Cálculo!I132:I134)*Cálculo!G144-BL16-BM25 -> 4802.8657 | BM14: =-BK14*BL14/1000 -> -29.805624 | BQ14: For information only - Value Plan | CN14: Index cost | CO14: -100
P15: Alloys | U15: =Cálculo!$J$135/1000 -> -12.014339 | AM15: =AM14*AJ5 -> 550.63799 | AW15: =[8]FYB26xFYMRF7!$P$31 -> Partner remuneration | AX15: =[8]FYB26xFYMRF7!$Q$31 -> -1 | BH15: Iron ore MB 65% (1m lag) | BI15: ='[26]Premissa - Budget 2026'!$U$6 -> 109.41667 | BJ15: ='[27]Premissa - MRF'!$U$6 -> 116.54488 | BK15: =BJ15-BI15 -> 7.1282083 | BL15: =BL16+BM25 -> 5744.3299 | BM15: =-BK15*BL15/1000 -> -40.94678 | CN15: Freight cost | CO15: 31
B16: Vol (kt) | C16: =C4 -> FY26'B | D16: =D4 -> FY26'F7 | E16: Var | F16: =F4 -> CM FY26'B | G16: MUSD | I16: NRP $/t | J16: =J4 -> FY26'B | K16: =K4 -> FY26'F7 | L16: Var | M16: =M4 -> Vol FY26'F7 | N16: MUSD | P16: Others | U16: =SUM(U17:U20) -> -19.853098 | W16: ='[10]Bridges complementares'!$E$14 -> Market driven | X16: ='[10]Bridges complementares'!$F$14 -> -8.7367984 | AM16: =AM15/AL5 -> 101.97 | AW16: =[8]FYB26xFYMRF7!$P$32 -> HVA Growth | AX16: =[8]FYB26xFYMRF7!$Q$32 -> -1 | BH16: Pellet premium | BI16: ='[26]Premissa - Budget 2026'!$U$9 -> 30 | BJ16: ='[27]Premissa - MRF'!$U$9+3 -> 36.5 | BK16: =BJ16-BI16 -> 6.5 | BL16: =Cálculo!I133*Cálculo!G144 -> 5485.605 | BM16: =-BK16*BL16/1000 -> -35.656433 | BQ16: Value plan | BR16: FY23B | BS16: FY23F | BT16: $m | CN16: Total | CO16: =SUM(CO13:CO15) -> -60
B17: Slab | C17: =Cálculo!C20/1000 -> 31 | D17: =Cálculo!F20/1000 -> 32.42416 | E17: =D17-C17 -> 1.42416 | F17: =Cálculo!D86 -> 0.72748999 | G17: =E17*F17/1000 -> 0.0010360621 | I17: Slab | J17: =Cálculo!D20*Cálculo!$E$152 -> 2435.9483 | K17: =Cálculo!G20*Cálculo!$H$152 -> 2403.9567 | L17: =K17-J17 -> -31.991604 | M17: =D17 -> 32.42416 | N17: =L17*M17/1000/$N$40 -> -0.19209276 | P17: Natural gas | U17: =Cálculo!J138/1000 -> 0.20690204 | W17: ='[10]Bridges complementares'!$E$15 -> Alloys | X17: ='[10]Bridges complementares'!$F$15 -> -6.5367984 | AW17: =[8]FYB26xFYMRF7!$P$33 -> Total | AX17: =AX12+AX8+AX5-1 -> -34.354236 | BH17: Rebate (pellet premium) | BI17: 0 | BJ17: -3 | BK17: =BJ17-BI17 -> -3 | BL17: =BL16 -> 5485.605 | BM17: =-BK17*BL17/1000 -> 16.456815 | BQ17: Usage & Mix | BR17: 28 | BS17: 11 | BT17: =BS17-BR17 -> -17
B18: Plates | C18: =Cálculo!C21/1000 -> 18 | D18: =Cálculo!F21/1000 -> 16.52916 | E18: =D18-C18 -> -1.47084 | F18: =Cálculo!D87 -> 269.02612 | G18: =E18*F18/1000 -> -0.39569438 | I18: Plates | J18: =Cálculo!D21*Cálculo!$E$152 -> 3701.1609 | K18: =Cálculo!G21*Cálculo!$H$152 -> 3627.0888 | L18: =K18-J18 -> -74.072135 | M18: =D18 -> 16.52916 | N18: =L18*M18/1000/$N$40 -> -0.22673151 | P18: Zinc | U18: =Cálculo!$J$136/1000 -> -11.03 | W18: ='[10]Bridges complementares'!$E$16 -> Coated lines | X18: ='[10]Bridges complementares'!$F$16 -> -2.2 | AM18: -60.00925 | AO18: =AM5-AM18 -> 164.09218 | BH18: Lump premium | BI18: ='[26]Premissa - Budget 2026'!$U$10 -> 8.2766667 | BJ18: ='[27]Premissa - MRF'!$U$10 -> 6.6041667 | BK18: =BJ18-BI18 -> -1.6725 | BL18: =Cálculo!I134*Cálculo!G144 -> 1538.3797 | BM18: =-BK18*BL18/1000 -> 2.57294 | BQ18: Volume | BR18: 4 | BS18: 16 | BT18: =BS18-BR18 -> 12
B19: HRC Auto | C19: =Cálculo!C23/1000 -> 85.81796 | D19: =Cálculo!F23/1000 -> 100.23684 | E19: =D19-C19 -> 14.41888 | F19: =Cálculo!D89 -> 244.22864 | G19: =E19*F19/1000 -> 3.5215036 | I19: HRC Auto | J19: =Cálculo!D23*Cálculo!$E$152 -> 3679.7808 | K19: =Cálculo!G23*Cálculo!$H$152 -> 3757.0515 | L19: =K19-J19 -> 77.270714 | M19: =D19 -> 100.23684 | N19: =L19*M19/1000/$N$40 -> 1.4343282 | P19: Fluxes | U19: =Cálculo!J139/1000 -> -7.03 | W19: ='[10]Bridges complementares'!$E$17 -> Total | X19: =X16+X5 -> -12.829343 | Z19: =U21+X19 -> -190.30129 | AM19: -21.124353 | AO19: =AM6-AM19 -> 60.442337 | BH19: Netback freight | BI19: ='[26]Premissa - Budget 2026'!$U$8 -> 15.957103 | BJ19: ='[27]Premissa - MRF'!$U$8 -> 19.879362 | BK19: =BJ19-BI19 -> 3.9222589 | BL19: =SUM(BL14:BL15) -> 10547.196 | BM19: =BK19*BL19/1000 -> 41.368831 | BQ19: Input price | BR19: 2 | BS19: 15 | BT19: =BS19-BR19 -> 13
B20: HRC Ind | C20: =Cálculo!C24/1000 -> 1438.6813 | D20: =Cálculo!F24/1000 -> 1441.7707 | E20: =D20-C20 -> 3.089416 | F20: =Cálculo!D90 -> 221.55976 | G20: =E20*F20/1000 -> 0.68449027 | I20: HRC Ind | J20: =Cálculo!D24*Cálculo!$E$152 -> 3557.3689 | K20: =Cálculo!G24*Cálculo!$H$152 -> 3591.5007 | L20: =K20-J20 -> 34.131787 | M20: =D20 -> 1441.7707 | N20: =L20*M20/1000/$N$40 -> 9.1130022 | P20: Energy | U20: =Cálculo!J140/1000 -> -2 | Z20: =X18+X8+X9+U10+U17+U18 -> -9.9480504 | AM20: 39.81089 | AO20: =AM7-AM20 -> -112.63895 | BH20: Forex (contract) | BM20: =([28]FY!$AF$11+[28]FY!$AI$11)/1000 -> -5.8272357 | BQ20: Sales mix | BR20: 3 | BS20: 3 | BT20: =BS20-BR20 -> 0
B21: HRC Down | C21: =Cálculo!C25/1000 -> 427.37381 | D21: =Cálculo!F25/1000 -> 446.35943 | E21: =D21-C21 -> 18.985624 | F21: =Cálculo!D91 -> 238.2919 | G21: =E21*F21/1000 -> 4.5241206 | I21: HRC Down | J21: =Cálculo!D25*Cálculo!$E$152 -> 4079.7224 | K21: =Cálculo!G25*Cálculo!$H$152 -> 4140.3062 | L21: =K21-J21 -> 60.583747 | M21: =D21 -> 446.35943 | N21: =L21*M21/1000/$N$40 -> 5.0078013 | P21: Total | U21: =SUM(U5,U11,U15,U16) -> -177.47195 | Z21: =Z19-Z20 -> -180.35324 | AM21: -41.322712 | AO21: =AM8-AM21 -> 111.89557 | BH21: Others (Vale contract specification, VIU, open balance) | BM21: =-(SUM(BM14:BM20)-BM22) -> -2.2358845 | BQ21: Selling price | BR21: 0 | BS21: 3 | BT21: =BS21-BR21 -> 3
B22: P&O Auto | C22: =Cálculo!C26/1000 -> 102.99919 | D22: =Cálculo!F26/1000 -> 90.523858 | E22: =D22-C22 -> -12.475332 | F22: =Cálculo!D92 -> 341.99386 | G22: =E22*F22/1000 -> -4.266487 | I22: P&O Auto | J22: =Cálculo!D26*Cálculo!$E$152 -> 4639.713 | K22: =Cálculo!G26*Cálculo!$H$152 -> 4733.5026 | L22: =K22-J22 -> 93.789581 | M22: =D22 -> 90.523858 | N22: =L22*M22/1000/$N$40 -> 1.5722583 | W22: TOTAL | X22: =U21+X19 -> -190.30129 | Z22: =U21+X19-X18-U18-U17-U10-X8-X9 -> -180.35324 | BH22: Total | BM22: =SUM(U12:U14) -> -54.073371 | BO22: =BM22-SUM(BM14:BM21) -> 0 | BQ22: Non steel | BR22: 0 | BS22: 1 | BT22: =BS22-BR22 -> 1
B23: P&O Ind | C23: =Cálculo!C27/1000 -> 0 | D23: =Cálculo!F27/1000 -> 45.424208 | E23: =D23-C23 -> 45.424208 | F23: =Cálculo!D93 -> 269.38858 | G23: =E23*F23/1000 -> 12.236763 | I23: P&O Ind | J23: =Cálculo!D27*Cálculo!$E$152 -> 3905.6445 | K23: =Cálculo!G27*Cálculo!$H$152 -> 3743.7877 | L23: =K23-J23 -> -161.85682 | M23: =D23 -> 45.424208 | N23: =L23*M23/1000/$N$40 -> -1.3615219 | P23: Crude Steel (kt) | U23: =Cálculo!G144 -> 6970.2857 | W23: VeGa | X23: =X17+X12+U17+U18 -> -17.359896 | Y23: 9 | BQ23: Total | BR23: 38 | BS23: 50 | BT23: =SUM(BT17:BT22) -> 12
B24: CRC Auto | C24: =Cálculo!C30/1000 -> 90.12747 | D24: =Cálculo!F30/1000 -> 95.622293 | E24: =D24-C24 -> 5.4948228 | F24: =Cálculo!D96 -> 427.2982 | G24: =E24*F24/1000 -> 2.3479279 | I24: CRC Auto | J24: =Cálculo!D30*Cálculo!$E$152 -> 4978.92 | K24: =Cálculo!G30*Cálculo!$H$152 -> 5088.197 | L24: =K24-J24 -> 109.27698 | M24: =D24 -> 95.622293 | N24: =L24*M24/1000/$N$40 -> 1.9350584 | P24: Check | Q24: = | U24: =Cálculo!C9 -> -177.47195 | W24: SUBTOTAL | X24: =X22-X23 -> -172.94139 | AU24: =#REF!+#REF!+#REF! -> #REF! | AW24: =Box!#REF!+Box!AU7+Box!#REF!+Box!#REF! -> #REF!
B25: CRC Ind | C25: =Cálculo!C31/1000 -> 265.32554 | D25: =Cálculo!F31/1000 -> 286.12232 | E25: =D25-C25 -> 20.796778 | F25: =Cálculo!D97 -> 293.49176 | G25: =E25*F25/1000 -> 6.1036832 | I25: CRC Ind | J25: =Cálculo!D31*Cálculo!$E$152 -> 4256.3653 | K25: =Cálculo!G31*Cálculo!$H$152 -> 4373.4123 | L25: =K25-J25 -> 117.04702 | M25: =D25 -> 286.12232 | N25: =L25*M25/1000/$N$40 -> 6.2018085 | U25: =U24-U21 -> 0 | W25: Minério foex | X25: -10 | BM25: ='[27]Iron ore - Calculo 2026'!$J$127+'[27]Iron ore - Calculo 2026'!$K$127 -> 258.72488
B26: CRC Down | C26: =Cálculo!C32/1000 -> 110.30197 | D26: =Cálculo!F32/1000 -> 117.39091 | E26: =D26-C26 -> 7.088941 | F26: =Cálculo!D98 -> 258.7764 | G26: =E26*F26/1000 -> 1.8344506 | I26: CRC Down | J26: =Cálculo!D32*Cálculo!$E$152 -> 4500.9023 | K26: =Cálculo!G32*Cálculo!$H$152 -> 4618.1222 | L26: =K26-J26 -> 117.21996 | M26: =D26 -> 117.39091 | N26: =L26*M26/1000/$N$40 -> 2.5482515 | W26: SUBTOTAL2 | X26: =X24+X25 -> -182.94139
B27: HDG Auto | C27: =Cálculo!C35/1000 -> 463.69403 | D27: =Cálculo!F35/1000 -> 463.78729 | E27: =D27-C27 -> 0.093261061 | F27: =Cálculo!D101 -> 472.53611 | G27: =E27*F27/1000 -> 0.044069219 | I27: HDG Auto | J27: =Cálculo!D35*Cálculo!$E$152 -> 5643.5325 | K27: =Cálculo!G35*Cálculo!$H$152 -> 5687.8782 | L27: =K27-J27 -> 44.345684 | M27: =D27 -> 463.78729 | N27: =L27*M27/1000/$N$40 -> 3.8086971 | W27: sv BD | X27: =-[29]FY25BxFY25A!$P$45/1000000 -> -30.880903 | AO27: =Box!#REF!+Box!AU7+Box!#REF!+Box!#REF!+Box!#REF!+Box!#REF! -> #REF!
B28: HDG Ind | C28: =Cálculo!C36/1000 -> 416.58471 | D28: =Cálculo!F36/1000 -> 438.61917 | E28: =D28-C28 -> 22.03446 | F28: =Cálculo!D102 -> 256.5783 | G28: =E28*F28/1000 -> 5.6535642 | I28: HDG Ind | J28: =Cálculo!D36*Cálculo!$E$152 -> 4583.428 | K28: =Cálculo!G36*Cálculo!$H$152 -> 4723.5641 | L28: =K28-J28 -> 140.13614 | M28: =D28 -> 438.61917 | N28: =L28*M28/1000/$N$40 -> 11.382666 | W28: Var. HRC | X28: 4
B29: HDG Down | C29: =Cálculo!C37/1000 -> 83.53933 | D29: =Cálculo!F37/1000 -> 76.159621 | E29: =D29-C29 -> -7.3797089 | F29: =Cálculo!D103 -> 208.09742 | G29: =E29*F29/1000 -> -1.5356984 | I29: HDG Down | J29: =Cálculo!D37*Cálculo!$E$152 -> 4753.6312 | K29: =Cálculo!G37*Cálculo!$H$152 -> 4920.7145 | L29: =K29-J29 -> 167.08325 | M29: =D29 -> 76.159621 | N29: =L29*M29/1000/$N$40 -> 2.356481 | R29: = | W29: TOTAL | X29: =X26+X27-X28 -> -217.8223
B30: AlZn Ind | C30: =Cálculo!C39/1000 -> 181.45709 | D30: =Cálculo!F39/1000 -> 136.27179 | E30: =D30-C30 -> -45.185301 | F30: =Cálculo!D105 -> 309.1623 | G30: =E30*F30/1000 -> -13.969592 | I30: AlZn Ind | J30: =Cálculo!D39*Cálculo!$E$152 -> 5254.3167 | K30: =Cálculo!G39*Cálculo!$H$152 -> 5319.2901 | L30: =K30-J30 -> 64.973401 | M30: =D30 -> 136.27179 | N30: =L30*M30/1000/$N$40 -> 1.6396373 | BH30: ∆ | BM30: =BM21-BM27-BM28 -> -2.2358845
B31: AlZn Down | C31: =Cálculo!C40/1000 -> 106.33588 | D31: =Cálculo!F40/1000 -> 88.523367 | E31: =D31-C31 -> -17.812513 | F31: =Cálculo!D106 -> 344.25133 | G31: =E31*F31/1000 -> -6.1319814 | I31: AlZn Down | J31: =Cálculo!D40*Cálculo!$E$152 -> 5875.7975 | K31: =Cálculo!G40*Cálculo!$H$152 -> 6130.6218 | L31: =K31-J31 -> 254.82436 | M31: =D31 -> 88.523367 | N31: =L31*M31/1000/$N$40 -> 4.1773908 | W31: EBITDA COST | X31: =-'[30]Máscara (Divulgação)'!$BD$20/1000 -> -29.259862
B32: Usibor Auto | C32: =Cálculo!C41/1000 -> 94.231595 | D32: =Cálculo!F41/1000 -> 99.323021 | E32: =D32-C32 -> 5.0914261 | F32: =Cálculo!D107 -> 718.52838 | G32: =E32*F32/1000 -> 3.6583342 | I32: Usibor Auto | J32: =Cálculo!D41*Cálculo!$E$152 -> 6973.4038 | K32: =Cálculo!G41*Cálculo!$H$152 -> 7149.6531 | L32: =K32-J32 -> 176.24927 | M32: =D32 -> 99.323021 | N32: =L32*M32/1000/$N$40 -> 3.2417797
B33: AlSi Ind | C33: =Cálculo!C42/1000 -> 7.73754 | D33: =Cálculo!F42/1000 -> 7.661225 | E33: =D33-C33 -> -0.076315 | F33: =Cálculo!D108 -> 275.87627 | G33: =E33*F33/1000 -> -0.021053497 | I33: AlSi Ind | J33: =Cálculo!D42*Cálculo!$E$152 -> 4583.0824 | K33: =Cálculo!G42*Cálculo!$H$152 -> 4243.7619 | L33: =K33-J33 -> -339.32045 | M33: =D33 -> 7.661225 | N33: =L33*M33/1000/$N$40 -> -0.48140931 | X33: =X29-X31 -> -188.56244
B34: Auto imp | C34: =Cálculo!C43/1000 -> 3.8163262 | D34: =Cálculo!F43/1000 -> 3.6272929 | E34: =D34-C34 -> -0.18903329 | F34: =Cálculo!D109 -> 1208.6234 | G34: =E34*F34/1000 -> -0.22847005 | I34: Auto imp | J34: =Cálculo!D43*Cálculo!$E$152 -> 10111.406 | K34: =Cálculo!G43*Cálculo!$H$152 -> 10097.65 | L34: =K34-J34 -> -13.756064 | M34: =D34 -> 3.6272929 | N34: =L34*M34/1000/$N$40 -> -0.0092402355
B35: =Cálculo!B45 -> Industry Imports | C35: =Cálculo!C45/1000 -> 35.39997 | D35: =Cálculo!F45/1000 -> 17.169268 | E35: =D35-C35 -> -18.230702 | F35: =Cálculo!D111 -> 284.85966 | G35: =E35*F35/1000 -> -5.1931916 | I35: =B35 -> Industry Imports | J35: =Cálculo!D45*Cálculo!$E$152 -> 5123.0825 | K35: =Cálculo!G45*Cálculo!$H$152 -> 5212.3443 | L35: =K35-J35 -> 89.261878 | M35: =D35 -> 17.169268 | N35: =L35*M35/1000/$N$40 -> 0.28380761
B36: =Cálculo!B46 -> Magnelis DM Downstream | C36: =Cálculo!C46/1000 -> 0 | D36: =Cálculo!F46/1000 -> 7.00288 | E36: =D36-C36 -> 7.00288 | F36: =Cálculo!D112 -> 343.65894 | G36: =E36*F36/1000 -> 2.4066023 | I36: =B36 -> Magnelis DM Downstream | J36: =Cálculo!D46*Cálculo!$E$152 -> 5440.5986 | K36: =Cálculo!G46*Cálculo!$H$152 -> 5215.1305 | L36: =K36-J36 -> -225.46804 | M36: =D36 -> 7.00288 | N36: =L36*M36/1000/$N$40 -> -0.29239363
B37: =Cálculo!B47 -> HRC Aperam baixo carbono | C37: =Cálculo!C47/1000 -> 0 | D37: =Cálculo!F47/1000 -> 0 | E37: =D37-C37 -> 0 | F37: =Cálculo!D113 -> 30 | G37: =E37*F37/1000 -> 0 | I37: =B37 -> HRC Aperam baixo carbono | J37: =Cálculo!D47*Cálculo!$E$152 -> 0 | K37: =Cálculo!G47*Cálculo!$H$152 -> 0 | L37: =K37-J37 -> 0 | M37: =D37 -> 0 | N37: =L37*M37/1000/$N$40 -> 0 | BQ37: TVC
B38: Revenue recognition | G38: =Cálculo!I166/1000 -> 0 | I38: Domestic | N38: =SUM(N17:N37) -> 52.139579 | BQ38: For information only - Trade defense
B39: Domestic | C39: =SUM(C17:C38) -> 3962.4237 | D39: =SUM(D17:D38) -> 4010.5488 | E39: =SUM(E17:E38) -> 48.125113 | G39: =SUM(G17:G38) -> 11.274377
I40: Forex | N40: =Cálculo!$E$152 -> 5.4 | BQ40: Trade defense | BR40: FY26B | BS40: FY26F | BT40: $m
BQ41: Volume & mix | BR41: 46.8 | BS41: =41-BS52 -> 38.5 | BT41: =BS41-BR41 -> -8.3
I42: Total | N42: =N14+N38 -> 288.42715 | BQ42: Price industry | BR42: 14.4 | BS42: =46-BS53 -> 44.9 | BT42: =BS42-BR42 -> 30.5
B43: Total | C43: =C14+C39 -> 7232.3337 | D43: =D14+D39 -> 7096.5585 | E43: =E14+E39 -> -135.77525 | G43: =G14+G39+G41 -> -4.8541517 | BQ43: Total | BR43: =SUM(BR41:BR42) -> 61.2 | BS43: =SUM(BS41:BS42) -> 83.4 | BT43: =BS43-BR43 -> 22.2
I44: Slabs and Plates | L44: =N44/M44*1000*$N$40 -> -46.200157 | M44: =M17+M18 -> 48.95332 | N44: =N17+N18 -> -0.41882427
B45: Slabs and Plates | C45: =C17+C18 -> 49 | D45: =D17+D18 -> 48.95332 | E45: =D45-C45 -> -0.04668 | F45: =G45/E45*1000 -> 8454.5484 | G45: =G17+G18 -> -0.39465832 | I45: Industry | L45: =N45/M45*1000*$N$40 -> 60.728573 | M45: =SUM(M20,M23,M25,M28,M30,M33) -> 2355.8694 | N45: =SUM(N20,N23,N25,N28,N30,N33) -> 26.494183
B46: Industry | C46: =SUM(C20,C23,C25,C28,C30,C33)+C35 -> 2345.1862 | D46: =SUM(D20,D23,D25,D28,D30,D33,D35) -> 2373.0387 | E46: =D46-C46 -> 27.852544 | F46: =G46/E46*1000 -> 470.13507 | G46: =SUM(G20,G23,G25,G28,G30,G33)+G37+G36 -> 13.094458 | I46: Downstream | L46: =N46/M46*1000*$N$40 -> 104.451 | M46: =SUM(M21,M26,M29,M31) -> 728.43333 | N46: =SUM(N21,N26,N29,N31) -> 14.089925
B47: Downstream | C47: =SUM(C21,C26,C29,C31) -> 727.55099 | D47: =SUM(D21,D26,D29,D31) -> 728.43333 | E47: =D47-C47 -> 0.8823435 | F47: =G47/E47*1000 -> -1483.6722 | G47: =SUM(G21,G26,G29,G31) -> -1.3091086 | I47: Auto | L47: =N47/M47*1000*$N$40 -> 75.84808 | M47: =SUM(M19,M22,M24,M27,M32,M34) -> 853.12059 | N47: =SUM(N19,N22,N24,N27,N32,N34) -> 11.982881
B48: Auto | C48: =SUM(C19,C22,C24,C27,C32,C34) -> 840.68657 | D48: =SUM(D19,D22,D24,D27,D32,D34) -> 853.12059 | E48: =D48-C48 -> 12.434025 | F48: =G48/E48*1000 -> 408.30527 | G48: =SUM(G19,G22,G24,G27,G32,G34) -> 5.0768778 | BQ48: Tekno
I49: Check | N49: =Cálculo!C5-N42 -> -1.8782022 | BQ49: For information only - Trade defense
B50: Check | G50: =Cálculo!C7+Cálculo!C6 -> -6.6803807
G51: =G50-G43 -> -1.826229 | BQ51: Trade defense | BR51: FY26B | BS51: FY26F | BT51: $m
B52: Total DM vol. | E52: =SUM(E19:E34) -> 59.399615 | G52: =SUM(G19:G34) -> 14.455625 | BQ52: Volume & mix | BR52: 1 | BS52: 2.5 | BT52: =BS52-BR52 -> 1.5
BQ53: Price industry | BR53: 0 | BS53: 1.1 | BT53: =BS53-BR53 -> 1.1
BQ54: Total | BR54: =SUM(BR52:BR53) -> 1 | BS54: =SUM(BS52:BS53) -> 3.6 | BT54: =BS54-BR54 -> 2.6
BQ57: Consolidado
BQ58: For information only - Trade defense
BQ60: Trade defense | BR60: FY26B | BS60: FY26F | BT60: $m
BQ61: Volume & mix | BR61: =BR41+BR52 -> 47.8 | BS61: =BS41+BS52 -> 41 | BT61: =BS61-BR61 -> -6.8
BQ62: Price industry | BR62: =BR42+BR53 -> 14.4 | BS62: =BS42+BS53 -> 46 | BT62: =BS62-BR62 -> 31.6
BQ63: Total | BR63: =SUM(BR61:BR62) -> 62.2 | BS63: =SUM(BS61:BS62) -> 87 | BT63: =BS63-BR63 -> 24.8

Sheet Box (resumo sem AMD)
B2: Volume & Mix | I2: Selling price | P2: Input price | W2: Usage | Z2: Fixed cost | AF2: Forex on costs | AN2: Others | AQ2: Non recurrent & Legal/compliance | AV2: Fixed cost | AY2: Vale negotiation | BD2: AMS consolidation | BG2: For information only - Flat raw material basket | BQ2: Calvert impact | BV2: Mandatory | CA2: Inflation | CD2: Footprint | CG2: Usage
B4: Vol (kt) | C4: =J4 -> FY26'B | D4: =K4 -> FY26'F7 | E4: Var | F4: ="CM "&C4 -> CM FY26'B | G4: MUSD | I4: NRP $/t | J4: =Cálculo!D15 -> FY26'B | K4: =Cálculo!G15 -> FY26'F7 | L4: Var | M4: ="Vol "&K4 -> Vol FY26'F7 | N4: MUSD
B5: Slab Calvert | C5: =Cálculo!C17/1000 -> 961 | D5: =Cálculo!F17/1000 -> 966.24787 | E5: =D5-C5 -> 5.24787 | F5: =Cálculo!D83 -> 84.272668 | G5: =E5*F5/1000 -> 0.44225201 | H5: =G5-Box!G5 -> 0 | I5: Slab Calvert | J5: =Cálculo!D17 -> 521.64672 | K5: =Cálculo!G17 -> 611.989 | L5: =K5-J5 -> 90.342283 | M5: =Box!M5 -> 966.24787 | N5: =L5*M5/1000 -> 87.293039 | O5: =Cálculo!M17 -> 87293.039 | DF5: =O5/1000 -> 87.293039
B6: Slabs Others Intragroup | C6: =Cálculo!C18/1000 -> 400 | D6: =Cálculo!F18/1000 -> 997.32708 | E6: =D6-C6 -> 597.32708 | F6: =Cálculo!D84 -> 28.199955 | G6: =E6*F6/1000 -> 16.844597 | I6: Slabs Others Intragroup | J6: =Cálculo!D18 -> 444.574 | K6: =Cálculo!G18 -> 516.61738 | L6: =K6-J6 -> 72.04338 | M6: =Box!M6 -> 997.32708 | N6: =L6*M6/1000 -> 71.850814 | O6: =Cálculo!M18 -> 71850.814 | DF6: =O6/1000 -> 71.850814
B7: Slabs 3rd Party | C7: =Cálculo!C19/1000 -> 1423.1644 | D7: =Cálculo!F19/1000 -> 874.38504 | E7: =D7-C7 -> -548.77934 | F7: =Cálculo!D85 -> 36.906952 | G7: =E7*F7/1000 -> -20.253773 | I7: Slabs 3rd Party | J7: =Cálculo!D19 -> 453.281 | K7: =Cálculo!G19 -> 520.32299 | L7: =K7-J7 -> 67.04199 | M7: =Box!M7 -> 874.38504 | N7: =L7*M7/1000 -> 58.620514
B8: HRC | C8: =Cálculo!C22/1000 -> 433.467 | D8: =Cálculo!F22/1000 -> 197.56682 | E8: =D8-C8 -> -235.90018 | F8: =Cálculo!D88 -> 36.052263 | G8: =E8*F8/1000 -> -8.5047354 | I8: HRC | J8: =Cálculo!D22 -> 482.26451 | K8: =Cálculo!G22 -> 557.07307 | L8: =K8-J8 -> 74.80856 | M8: =Box!M8 -> 197.56682 | N8: =L8*M8/1000 -> 14.779689 | DF8: =O8/1000 -> 0
B9: CRC Auto | C9: =Cálculo!C28/1000 -> 1.2203924 | D9: =Cálculo!F28/1000 -> 1.8878106 | E9: =D9-C9 -> 0.66741819 | F9: =Cálculo!D94 -> 388.26831 | G9: =E9*F9/1000 -> 0.25913734 | I9: CRC Auto | J9: =Cálculo!D28*Cálculo!$E$152 -> 4768.1586 | K9: =Cálculo!G28*Cálculo!$H$152 -> 4851.0814 | L9: =K9-J9 -> 82.922743 | M9: =D9 -> 1.8878106 | N9: =L9*M9/1000/$N$38 -> 0.028989339 | DF9: =O9/1000 -> 0
B10: CRC Ind | C10: =Cálculo!C29/1000 -> 0.49226 | D10: =Cálculo!F29/1000 -> 4.847375 | E10: =D10-C10 -> 4.355115 | F10: =Cálculo!D95 -> -171.40909 | G10: =E10*F10/1000 -> -0.7465063 | I10: CRC Ind | J10: =Cálculo!D29 -> 323.31493 | K10: =Cálculo!G29 -> 603.52341 | L10: =K10-J10 -> 280.20848 | M10: =D10 -> 4.847375 | N10: =L10*M10/1000 -> 1.3582756 | DF10: =O10/1000 -> 0
B11: HDG Auto | C11: =Cálculo!C33/1000 -> 49.551853 | D11: =Cálculo!F33/1000 -> 41.148524 | E11: =D11-C11 -> -8.4033296 | F11: =Cálculo!D99 -> 445.45556 | G11: =E11*F11/1000 -> -3.7433099 | I11: HDG Auto | J11: =Cálculo!D33*Cálculo!$E$152 -> 5497.2975 | K11: =Cálculo!G33*Cálculo!$H$152 -> 5478.5868 | L11: =K11-J11 -> -18.710747 | M11: =D11 -> 41.148524 | N11: =L11*M11/1000/$N$38 -> -0.14257771 | DF11: =O11/1000 -> 0
B12: HDG Ind | C12: =Cálculo!C34/1000 -> 1.01412 | D12: =Cálculo!F34/1000 -> 2.599121 | E12: =D12-C12 -> 1.585001 | F12: =Cálculo!D100 -> -268.88972 | G12: =E12*F12/1000 -> -0.42619048 | I12: HDG Ind | J12: =Cálculo!D34 -> 323.31493 | K12: =Cálculo!G34 -> 562.09665 | L12: =K12-J12 -> 238.78171 | M12: =D12 -> 2.599121 | N12: =L12*M12/1000 -> 0.62062257 | DF12: =O12/1000 -> 0 | DG12: ='Box (resumo sem AMD)'!C14+'Box (resumo sem AMD)'!C12+'Box (resumo sem AMD)'!C10 -> 1.50638
B13: =Cálculo!B44 -> Magnelis DM Industry | C13: =Cálculo!C44/1000 -> 0 | D13: =Cálculo!F44/1000 -> 10 | E13: =D13-C13 -> 10 | F13: =Cálculo!D110 -> -182.6229 | G13: =E13*F13/1000 -> -1.826229 | I13: HDG Ind | J13: =Cálculo!D44 -> 481.23641 | K13: =Cálculo!G44 -> 481.23641 | L13: =K13-J13 -> 0 | M13: =D13 -> 10 | N13: =L13*M13/1000 -> 0
B14: AlZn Ind | C14: =Cálculo!C38/1000 -> 0 | D14: =Cálculo!F38/1000 -> 0 | E14: =D14-C14 -> 0 | F14: =Cálculo!D104 -> -663.85931 | G14: =E14*F14/1000 -> 0 | I14: AlZn Ind | J14: =Cálculo!D38 -> 0 | K14: =Cálculo!G38 -> 0 | L14: =K14-J14 -> 0 | M14: =D14 -> 0 | N14: =L14*M14/1000 -> 0 | DF14: =O14/1000 -> 0
B15: Export | C15: =SUM(C5:C14) -> 3269.91 | D15: =SUM(D5:D14) -> 3096.0096 | E15: =SUM(E5:E14) -> -173.90036 | G15: =SUM(G5:G14) -> -17.954758 | H15: =G15-Box!G14 -> -1.826229 | I15: Export | N15: =SUM(N5:N14) -> 234.40936
B17: Vol (kt) | C17: =C4 -> FY26'B | D17: =D4 -> FY26'F7 | E17: Var | F17: =F4 -> CM FY26'B | G17: MUSD | I17: NRP $/t | J17: =J4 -> FY26'B | K17: =K4 -> FY26'F7 | L17: Var | M17: =M4 -> Vol FY26'F7 | N17: MUSD
B18: Slab | C18: =Cálculo!C20/1000 -> 31 | D18: =Cálculo!F20/1000 -> 32.42416 | E18: =D18-C18 -> 1.42416 | F18: =Cálculo!D86 -> 0.72748999 | G18: =E18*F18/1000 -> 0.0010360621 | I18: Slab | J18: =Cálculo!D20*Cálculo!$E$152 -> 2435.9483 | K18: =Cálculo!G20*Cálculo!$H$152 -> 2403.9567 | L18: =K18-J18 -> -31.991604 | M18: =D18 -> 32.42416 | N18: =L18*M18/1000/$N$38 -> -0.19209276 | O18: =Cálculo!M20 -> -192.09276 | DF18: =O18/1000 -> -0.19209276 | DG18: =N18-DF18 -> 0
B19: Plates | C19: =Cálculo!C21/1000 -> 18 | D19: =Cálculo!F21/1000 -> 16.52916 | E19: =D19-C19 -> -1.47084 | F19: =Cálculo!D87 -> 269.02612 | G19: =E19*F19/1000 -> -0.39569438 | I19: Plates | J19: =Cálculo!D21*Cálculo!$E$152 -> 3701.1609 | K19: =Cálculo!G21*Cálculo!$H$152 -> 3627.0888 | L19: =K19-J19 -> -74.072135 | M19: =D19 -> 16.52916 | N19: =L19*M19/1000/$N$38 -> -0.22673151 | O19: =+Cálculo!M21 -> -226.73151 | DF19: =O19/1000 -> -0.22673151 | DG19: =N19-DF19 -> 0
B20: HRC Auto | C20: =Cálculo!C23/1000 -> 85.81796 | D20: =Cálculo!F23/1000 -> 100.23684 | E20: =D20-C20 -> 14.41888 | F20: =Cálculo!D89 -> 244.22864 | G20: =E20*F20/1000 -> 3.5215036 | I20: HRC Auto | J20: =Cálculo!D23*Cálculo!$E$152 -> 3679.7808 | K20: =Cálculo!G23*Cálculo!$H$152 -> 3757.0515 | L20: =K20-J20 -> 77.270714 | M20: =D20 -> 100.23684 | N20: =L20*M20/1000/$N$38 -> 1.4343282 | O20: =Cálculo!M23 -> 1434.3282 | DF20: =O20/1000 -> 1.4343282 | DG20: =N20-DF20 -> 0
B21: HRC Industry | C21: =Cálculo!C24/1000+Cálculo!C25/1000 -> 1866.0551 | D21: =Cálculo!F24/1000+Cálculo!F25/1000 -> 1888.1302 | E21: =D21-C21 -> 22.07504 | F21: =((Cálculo!E24+Cálculo!E25)/(Cálculo!C24+Cálculo!C25))*1000-((Cálculo!E57+Cálculo!E58)/(Cálculo!C57+Cálculo!C58))*1000 -> 225.39184 | G21: =Box!G20+Box!G21 -> 5.2086109 | I21: HRC Industry | J21: =Cálculo!S24*Cálculo!$E$152 -> 3677.001 | K21: =Cálculo!S25*Cálculo!$H$152 -> 3721.2399 | L21: =K21-J21 -> 44.238826 | M21: =D21 -> 1888.1302 | N21: =Box!N20+Box!N21 -> 14.120804 | DF21: =O21/1000 -> 0 | DG21: =N21-DF21 -> 14.120804
B22: P&O Auto | C22: =Cálculo!C26/1000 -> 102.99919 | D22: =Cálculo!F26/1000 -> 90.523858 | E22: =D22-C22 -> -12.475332 | F22: =Cálculo!D92 -> 341.99386 | G22: =E22*F22/1000 -> -4.266487 | I22: P&O Auto | J22: =Cálculo!D26*Cálculo!$E$152 -> 4639.713 | K22: =Cálculo!G26*Cálculo!$H$152 -> 4733.5026 | L22: =K22-J22 -> 93.789581 | M22: =D22 -> 90.523858 | N22: =L22*M22/1000/$N$38 -> 1.5722583 | DF22: =O22/1000 -> 0 | DG22: =N22-DF22 -> 1.5722583
B23: P&O Ind | C23: =Cálculo!C27/1000 -> 0 | D23: =Cálculo!F27/1000 -> 45.424208 | E23: =D23-C23 -> 45.424208 | F23: =Cálculo!D93 -> 269.38858 | G23: =E23*F23/1000 -> 12.236763 | I23: P&O Ind | J23: =Cálculo!D27*Cálculo!$E$152 -> 3905.6445 | K23: =Cálculo!G27*Cálculo!$H$152 -> 3743.7877 | L23: =K23-J23 -> -161.85682 | M23: =D23 -> 45.424208 | N23: =L23*M23/1000/$N$38 -> -1.3615219 | DF23: =O23/1000 -> 0 | DG23: =N23-DF23 -> -1.3615219
B24: CRC Auto | C24: =Cálculo!C30/1000 -> 90.12747 | D24: =Cálculo!F30/1000 -> 95.622293 | E24: =D24-C24 -> 5.4948228 | F24: =Cálculo!D96 -> 427.2982 | G24: =E24*F24/1000 -> 2.3479279 | I24: CRC Auto | J24: =Cálculo!D30*Cálculo!$E$152 -> 4978.92 | K24: =Cálculo!G30*Cálculo!$H$152 -> 5088.197 | L24: =K24-J24 -> 109.27698 | M24: =D24 -> 95.622293 | N24: =L24*M24/1000/$N$38 -> 1.9350584 | DF24: =O24/1000 -> 0 | DG24: =N24-DF24 -> 1.9350584
B25: CRC Industry | C25: =Cálculo!C31/1000+Cálculo!C32/1000 -> 375.62751 | D25: =Cálculo!F31/1000+Cálculo!F32/1000 -> 403.51323 | E25: =D25-C25 -> 27.885719 | F25: =((Cálculo!E31+Cálculo!E32)/(Cálculo!C31+Cálculo!C32)*1000-((Cálculo!E64+Cálculo!E65)/(Cálculo!C64+Cálculo!C65))*1000) -> 283.29769 | G25: =Box!G25+Box!G26 -> 7.9381338 | I25: CRC Industry | J25: =Cálculo!S31*Cálculo!$E$152 -> 4328.1729 | K25: =Cálculo!S32*Cálculo!$H$152 -> 4444.6038 | L25: =K25-J25 -> 116.43094 | M25: =D25 -> 403.51323 | N25: =Box!N25+Box!N26 -> 8.7500599 | DF25: =O25/1000 -> 0 | DG25: =N25-DF25 -> 8.7500599
B26: HDG Auto | C26: =Cálculo!C35/1000 -> 463.69403 | D26: =Cálculo!F35/1000 -> 463.78729 | E26: =D26-C26 -> 0.093261061 | F26: =Cálculo!D101 -> 472.53611 | G26: =E26*F26/1000 -> 0.044069219 | I26: HDG Auto | J26: =Cálculo!D35*Cálculo!$E$152 -> 5643.5325 | K26: =Cálculo!G35*Cálculo!$H$152 -> 5687.8782 | L26: =K26-J26 -> 44.345684 | M26: =D26 -> 463.78729 | N26: =L26*M26/1000/$N$38 -> 3.8086971 | DF26: =O26/1000 -> 0 | DG26: =N26-DF26 -> 3.8086971
B27: HDG Industry | C27: =Cálculo!C36/1000+Cálculo!C37/1000 -> 500.12404 | D27: =Cálculo!F36/1000+Cálculo!F37/1000 -> 514.77879 | E27: =D27-C27 -> 14.654751 | F27: =((Cálculo!E36+Cálculo!E37)/(Cálculo!C36+Cálculo!C37))*1000-((Cálculo!E69+Cálculo!E70)/(Cálculo!C69+Cálculo!C70))*1000 -> 248.48018 | G27: =Box!G28+Box!G29 -> 4.1178658 | I27: HDG Industry | J27: =Cálculo!S36*Cálculo!$E$152 -> 4611.8582 | K27: =Cálculo!S37*Cálculo!$H$152 -> 4752.7318 | L27: =K27-J27 -> 140.87353 | M27: =D27 -> 514.77879 | N27: =Box!N28+Box!N29 -> 13.739147 | DF27: =O27/1000 -> 0 | DG27: =N27-DF27 -> 13.739147
B28: AlZn Industry | C28: =Cálculo!C39/1000+Cálculo!C40/1000 -> 287.79297 | D28: =Cálculo!F39/1000+Cálculo!F40/1000 -> 224.79516 | E28: =D28-C28 -> -62.997814 | F28: =((Cálculo!E39+Cálculo!E40)/(Cálculo!C39+Cálculo!C40))*1000-((Cálculo!E72+Cálculo!E73)/(Cálculo!C72+Cálculo!C73))*1000 -> 322.12726 | G28: =Box!G30+Box!G31 -> -20.101573 | I28: AlZn Industry | J28: =Cálculo!S39*Cálculo!$E$152 -> 5483.946 | K28: =Cálculo!S40*Cálculo!$H$152 -> 5638.789 | L28: =K28-J28 -> 154.84303 | M28: =D28 -> 224.79516 | N28: =Box!N31+Box!N30 -> 5.8170282 | DF28: =O28/1000 -> 0 | DG28: =N28-DF28 -> 5.8170282
B29: Usibor Auto | C29: =Cálculo!C41/1000 -> 94.231595 | D29: =Cálculo!F41/1000 -> 99.323021 | E29: =D29-C29 -> 5.0914261 | F29: =Cálculo!D107 -> 718.52838 | G29: =E29*F29/1000 -> 3.6583342 | I29: Usibor Auto | J29: =Cálculo!D41*Cálculo!$E$152 -> 6973.4038 | K29: =Cálculo!G41*Cálculo!$H$152 -> 7149.6531 | L29: =K29-J29 -> 176.24927 | M29: =D29 -> 99.323021 | N29: =L29*M29/1000/$N$38 -> 3.2417797 | DF29: =O29/1000 -> 0 | DG29: =N29-DF29 -> 3.2417797
B30: AlSi Ind | C30: =Cálculo!C42/1000 -> 7.73754 | D30: =Cálculo!F42/1000 -> 7.661225 | E30: =D30-C30 -> -0.076315 | F30: =Cálculo!D108 -> 275.87627 | G30: =E30*F30/1000 -> -0.021053497 | I30: AlSi Ind | J30: =Cálculo!D42*Cálculo!$E$152 -> 4583.0824 | K30: =Cálculo!G42*Cálculo!$H$152 -> 4243.7619 | L30: =K30-J30 -> -339.32045 | M30: =D30 -> 7.661225 | N30: =L30*M30/1000/$N$38 -> -0.48140931 | DF30: =O30/1000 -> 0 | DG30: =N30-DF30 -> -0.48140931
B31: Auto imp | C31: =Cálculo!C43/1000 -> 3.8163262 | D31: =Cálculo!F43/1000 -> 3.6272929 | E31: =D31-C31 -> -0.18903329 | F31: =Cálculo!D109 -> 1208.6234 | G31: =E31*F31/1000 -> -0.22847005 | I31: Auto imp | J31: =Cálculo!D43*Cálculo!$E$152 -> 10111.406 | K31: =Cálculo!G43*Cálculo!$H$152 -> 10097.65 | L31: =K31-J31 -> -13.756064 | M31: =D31 -> 3.6272929 | N31: =L31*M31/1000/$N$38 -> -0.0092402355 | DF31: =O31/1000 -> 0 | DG31: =N31-DF31 -> -0.0092402355
B32: =Box!B35 -> Industry Imports | C32: =Cálculo!C45/1000 -> 35.39997 | D32: =Cálculo!F45/1000 -> 17.169268 | E32: =D32-C32 -> -18.230702 | F32: =Cálculo!D111 -> 284.85966 | G32: =E32*F32/1000 -> -5.1931916 | I32: =B32 -> Industry Imports | J32: =Cálculo!D45*Cálculo!$E$152 -> 5123.0825 | K32: =Cálculo!G45*Cálculo!$H$152 -> 5212.3443 | L32: =K32-J32 -> 89.261878 | M32: =D32 -> 17.169268 | N32: =L32*M32/1000/$N$38 -> 0.28380761 | DF32: =O32/1000 -> 0 | DG32: =N32-DF32 -> 0.28380761
G33: =E33*F33/1000 -> 0 | I33: =B33 -> 0 | J33: =Cálculo!D46*Cálculo!$E$152 -> 5440.5986 | K33: =Cálculo!G46*Cálculo!$H$152 -> 5215.1305 | L33: =K33-J33 -> -225.46804 | M33: =D33 -> 0 | N33: =L33*M33/1000/$N$38 -> 0 | DF33: =O33/1000 -> 0 | DG33: =N33-DF33 -> 0
B34: HRC Aperam BC | C34: =Cálculo!C47/1000 -> 0 | D34: =Cálculo!F47/1000 -> 0 | E34: =D34-C34 -> 0 | F34: =Cálculo!D113 -> 30 | G34: =E34*F34/1000 -> 0 | I34: =B34 -> HRC Aperam BC | J34: =Cálculo!D47*Cálculo!$E$152 -> 0 | K34: =Cálculo!G47*Cálculo!$H$152 -> 0 | L34: =K34-J34 -> 0 | M34: =D34 -> 0 | N34: =L34*M34/1000/$N$38 -> 0 | DF34: =O34/1000 -> 0 | DG34: =N34-DF34 -> 0
B35: HRC Aperam | C35: =Cálculo!C46/1000 -> 0 | D35: =Cálculo!F46/1000 -> 7.00288 | E35: =D35-C35 -> 7.00288 | F35: =Cálculo!D112 -> 343.65894 | G35: =E35*F35/1000 -> 2.4066023 | I35: =B35 -> HRC Aperam | J35: =Cálculo!D46*Cálculo!$E$152 -> 5440.5986 | K35: =Cálculo!G46*Cálculo!$H$152 -> 5215.1305 | L35: =K35-J35 -> -225.46804 | M35: =D35 -> 7.00288 | N35: =L35*M35/1000/$N$38 -> -0.29239363 | DF35: =O35/1000 -> 0 | DG35: =N35-DF35 -> -0.29239363
B36: Revenue recognition | G36: =Cálculo!I166/1000 -> 0 | I36: Domestic | N36: =SUM(N18:N35) -> 52.139579
B37: Domestic | C37: =SUM(C18:C36) -> 3962.4237 | D37: =SUM(D18:D36) -> 4010.5488 | E37: =SUM(E18:E36) -> 48.125113 | G37: =SUM(G18:G36) -> 11.274377
I38: Forex | N38: =Cálculo!$E$152 -> 5.4
I40: Total | N40: =N15+N36 -> 286.54894
B41: Total | C41: =C15+C37 -> 7232.3337 | D41: =D15+D37 -> 7106.5585 | E41: =E15+E37+E39 -> -125.77525 | G41: =G15+G37+G39 -> -6.6803807
B43: DM Breakdown | C43: =SUM(C24:C42) -> 13053.309 | D43: =SUM(D24:D42) -> 12954.388 | E43: =E44+E45+E46 -> 48.125113 | G43: =G44+G45+G46+G47 -> 11.274377 | I43: Slabs & Plates | L43: =N43/M43*1000*$N$38 -> -46.200157 | M43: =M18+M19 -> 48.95332 | N43: =N18+N19 -> -0.41882427
B44: Slabs & Plates | C44: =C18+C19 -> 49 | D44: =D18+D19 -> 48.95332 | E44: =D44-C44 -> -0.04668 | F44: =G44/E44*1000 -> 8454.5484 | G44: =G18+G19 -> -0.39465832 | I44: Industry | L44: =N44/M44*1000*$N$38 -> 70.48724 | M44: =SUM(M21,M23,M25,M27,M28,M30)+M32+M34+M35 -> 3108.4749 | N44: =SUM(N21,N23,N25,N27,N28,N30)+N32+N33+N34+N35 -> 40.575522 | O44: =N36+N15 -> 286.54894
B45: Industry | C45: =SUM(C21,C23,C25,C27,C28,C30,C35)+C32+C34 -> 3072.7372 | D45: =SUM(D21,D23,D25,D27,D28,D30,D32,D35)+D34 -> 3108.4749 | E45: =D45-C45 -> 35.737768 | F45: =G45/E45*1000 -> 184.45913 | G45: =SUM(G21,G23,G25,G27,G28,G30,G32,G35)+G34+G33 -> 6.5921577 | I45: Auto | L45: =N45/M45*1000*$N$38 -> 75.84808 | M45: =SUM(M20,M22,M24,M26,M29,M31) -> 853.12059 | N45: =SUM(N20,N22,N24,N26,N29,N31) -> 11.982881
B46: Auto | C46: =SUM(C20,C22,C24,C26,C29,C31) -> 840.68657 | D46: =SUM(D20,D22,D24,D26,D29,D31) -> 853.12059 | E46: =D46-C46 -> 12.434025 | F46: =G46/E46*1000 -> 408.30527 | G46: =SUM(G20,G22,G24,G26,G29,G31) -> 5.0768778
B47: =B36 -> Revenue recognition | G47: =G36 -> 0
I48: Check | N48: =Cálculo!C5-N40 -> 0
B49: Check | G49: =Cálculo!C6+Cálculo!C7-G41 -> 8.8817842e-15
B51: Total DM vol. | E51: =SUM(E20:E31) -> 59.399615 | G51: =SUM(G20:G31) -> 14.455625
G54: =Cálculo!C7+Cálculo!C6 -> -6.6803807
B60: Volume & Mix
B62: =B17 -> Vol (kt) | C62: =C17 -> FY26'B | D62: =D17 -> FY26'F7 | E62: =E17 -> Var | F62: =F17 -> CM FY26'B | G62: =G17 -> MUSD
B63: Auto | E63: =SUM(E20,E22,E24,E26,E29,E31,E9,E11) -> 4.6981132 | F63: =G63/E63*1000 -> 339.00955 | G63: =SUM(G20,G22,G24,G26,G29,G31,G9,G11) -> 1.5927053
B64: Total | C64: =C37 -> 3962.4237 | D64: =D37 -> 4010.5488 | G64: =SUM(G63:G63) -> 1.5927053

Sheet Box (resumo SAIDA)
B2: Volume & Mix | I2: Selling price
B4: Vol (kt) | C4: =J4 -> FY26'B | D4: =K4 -> FY26'F7 | E4: Var | F4: ="CM "&C4 -> CM FY26'B | G4: MUSD | I4: NRP $/t | J4: =Cálculo!D15 -> FY26'B | K4: =Cálculo!G15 -> FY26'F7 | L4: Var | M4: ="Vol "&K4 -> Vol FY26'F7 | N4: MUSD | W4: =G5+G6+N5+N6 -> 176.4307
B5: Slab Calvert | C5: =Cálculo!C17/1000 -> 961 | D5: =Cálculo!F17/1000 -> 966.24787 | E5: =D5-C5 -> 5.24787 | F5: =G5*1000/E5 -> 84.272668 | G5: =Cálculo!K83/1000 -> 0.44225201 | H5: =G5-Box!G5 -> -3.4972025e-15 | I5: Slab Calvert | J5: =Cálculo!D17 -> 521.64672 | K5: =Cálculo!G17 -> 611.989 | L5: =K5-J5 -> 90.342283 | M5: =Box!M5 -> 966.24787 | N5: =L5*M5/1000 -> 87.293039 | O5: -47.380538 | P5: =N5-O5 -> 134.67358 | W5: ='[31]Resumo- Analise movimentação'!$C$5+'[31]Resumo- Analise movimentação'!$C$4 -> -78.963691
B6: =Box!B6 -> Slabs Others Intragroup | C6: =Cálculo!C18/1000 -> 400 | D6: =Cálculo!F18/1000 -> 997.32708 | E6: =D6-C6 -> 597.32708 | F6: =G6*1000/E6 -> 28.199955 | G6: =Cálculo!K84/1000 -> 16.844597 | I6: =Box!B6 -> Slabs Others Intragroup | J6: =Cálculo!D18 -> 444.574 | K6: =Cálculo!G18 -> 516.61738 | L6: =K6-J6 -> 72.04338 | M6: =Box!M6 -> 997.32708 | N6: =L6*M6/1000 -> 71.850814 | O6: -71.046172 | P6: =N6-O6 -> 142.89699 | W6: =W4-W5 -> 255.39439
B7: =Box!B7 -> Slabs 3rd Party | C7: =Cálculo!C19/1000 -> 1423.1644 | D7: =Cálculo!F19/1000 -> 874.38504 | E7: =D7-C7 -> -548.77934 | F7: =Cálculo!D85 -> 36.906952 | G7: =E7*F7/1000 -> -20.253773 | I7: =Box!B7 -> Slabs 3rd Party | J7: =Cálculo!D19 -> 453.281 | K7: =Cálculo!G19 -> 520.32299 | L7: =K7-J7 -> 67.04199 | M7: =Box!M7 -> 874.38504 | N7: =L7*M7/1000 -> 58.620514
B8: LFR industry | C8: ='Box (resumo sem AMD)'!C8+'Box (resumo sem AMD)'!C14+'Box (resumo sem AMD)'!C12+'Box (resumo sem AMD)'!C10+'Box (resumo sem AMD)'!C13 -> 434.97338 | D8: ='Box (resumo sem AMD)'!D8+'Box (resumo sem AMD)'!D14+'Box (resumo sem AMD)'!D12+'Box (resumo sem AMD)'!D10+'Box (resumo sem AMD)'!D13 -> 215.01332 | E8: =D8-C8 -> -219.96006 | F8: =G8*1000/E8 -> 52.298862 | G8: ='Box (resumo sem AMD)'!G8+'Box (resumo sem AMD)'!G14+'Box (resumo sem AMD)'!G12+'Box (resumo sem AMD)'!G10+'Box (resumo sem AMD)'!G13 -> -11.503661 | I8: LFR industry | L8: =N8/M8*1000 -> 77.942091 | M8: ='Box (resumo sem AMD)'!M8+'Box (resumo sem AMD)'!D14+'Box (resumo sem AMD)'!D12+'Box (resumo sem AMD)'!D10+'Box (resumo sem AMD)'!D13 -> 215.01332 | N8: ='Box (resumo sem AMD)'!N8+'Box (resumo sem AMD)'!N14+'Box (resumo sem AMD)'!N12+'Box (resumo sem AMD)'!N10+'Box (resumo sem AMD)'!N13 -> 16.758587 | O8: -10.125036 | P8: =N8-O8 -> 26.883623
B9: Export | C9: =SUM(C5:C8) -> 3219.1378 | D9: =SUM(D5:D8) -> 3052.9733 | E9: =SUM(E5:E8) -> -166.16445 | G9: =SUM(G5:G8) -> -14.470585 | I9: Export | N9: =SUM(N5:N8) -> 234.52295 | O9: -130.62831 | P9: =N9-O9 -> 365.15126
P10: =N10-O10 -> 0
B11: Vol (kt) | C11: =C4 -> FY26'B | D11: =D4 -> FY26'F7 | E11: Var | F11: =F4 -> CM FY26'B | G11: MUSD | I11: NRP R$/t | J11: =J4 -> FY26'B | K11: =K4 -> FY26'F7 | L11: Var | M11: =M4 -> Vol FY26'F7 | N11: MUSD | O11: MUSD | P11: =N11-O11 -> #VALUE! | T11: =#REF!*#REF! -> #REF! | U11: =T11/'Box (resumo sem AMD)'!$N$38 -> #REF!
B12: ='Box (resumo sem AMD)'!B44 -> Slabs & Plates | C12: ='Box (resumo sem AMD)'!C44 -> 49 | D12: ='Box (resumo sem AMD)'!D44 -> 48.95332 | E12: ='Box (resumo sem AMD)'!E44 -> -0.04668 | F12: ='Box (resumo sem AMD)'!F44 -> 8454.5484 | G12: ='Box (resumo sem AMD)'!G44 -> -0.39465832 | I12: ='Box (resumo sem AMD)'!I43 -> Slabs & Plates | J12: ='Box (resumo sem AMD)'!J43 -> 0 | K12: ='Box (resumo sem AMD)'!K43 -> 0 | L12: ='Box (resumo sem AMD)'!L43 -> -46.200157 | M12: ='Box (resumo sem AMD)'!M43 -> 48.95332 | N12: ='Box (resumo sem AMD)'!N43 -> -0.41882427
B13: ='Box (resumo sem AMD)'!B45 -> Industry | C13: ='Box (resumo sem AMD)'!C45 -> 3072.7372 | D13: ='Box (resumo sem AMD)'!D45 -> 3108.4749 | E13: ='Box (resumo sem AMD)'!E45 -> 35.737768 | F13: ='Box (resumo sem AMD)'!F45 -> 184.45913 | G13: ='Box (resumo sem AMD)'!G45 -> 6.5921577 | I13: ='Box (resumo sem AMD)'!I44 -> Industry | J13: ='Box (resumo sem AMD)'!J44 -> 0 | K13: ='Box (resumo sem AMD)'!K44 -> 0 | L13: ='Box (resumo sem AMD)'!L44 -> 70.48724 | M13: ='Box (resumo sem AMD)'!M44 -> 3108.4749 | N13: ='Box (resumo sem AMD)'!N44 -> 40.575522 | O13: 61.548129 | P13: =N13-O13 -> -20.972607 | T13: =L14*M14 -> 64094.182 | U13: =T13/'Box (resumo sem AMD)'!$N$38 -> 11869.293
B14: ='Box (resumo sem AMD)'!B46 -> Auto | C14: ='Box (resumo sem AMD)'!C46+C21 -> 891.45882 | D14: ='Box (resumo sem AMD)'!D46+D21 -> 896.15693 | E14: ='Box (resumo sem AMD)'!E46+'Box (resumo sem AMD)'!E11+'Box (resumo sem AMD)'!E9 -> 4.6981132 | F14: =G14/E14*1000 -> 339.00955 | G14: ='Box (resumo sem AMD)'!G46+G21 -> 1.5927053 | I14: ='Box (resumo sem AMD)'!I45 -> Auto | J14: ='Box (resumo sem AMD)'!J45 -> 0 | K14: ='Box (resumo sem AMD)'!K45 -> 0 | L14: =N14/M14*1000*'Box (resumo sem AMD)'!N38 -> 71.521159 | M14: ='Box (resumo sem AMD)'!M45+M23 -> 896.15693 | N14: ='Box (resumo sem AMD)'!N45+N23 -> 11.869293 | O14: -10.773846 | P14: =N14-O14 -> 22.643139
B15: ='Box (resumo sem AMD)'!B47 -> Revenue recognition | C15: ='Box (resumo sem AMD)'!C47 -> 0 | D15: ='Box (resumo sem AMD)'!D47 -> 0 | G15: ='Box (resumo sem AMD)'!G47 -> 0 | I15: Domestic | N15: =SUM(N12:N14) -> 52.02599 | O15: 51.269788 | P15: =N15-O15 -> 0.75620233
P16: =N16-O16 -> 0
B17: Domestic | C17: =SUM(C13:C16) -> 3964.196 | D17: =SUM(D13:D16) -> 4004.6319 | E17: =SUM(E13:E15) -> 40.435881 | G17: =SUM(G12:G16) -> 7.7902047 | I17: Total | N17: =N9+N15 -> 286.54894 | O17: -79.358523 | P17: =N17-O17 -> 365.90747 | Z17: =('Box (resumo SAIDA)'!F13-'Box (resumo SAIDA)'!F8)*'Box (resumo SAIDA)'!E17/1000 -> 5.344017
B19: Total | E19: =E17+E9 -> -125.72857 | G19: =G17+G9 -> -6.6803807
M20: =M5+M6+#REF!+#REF!+M13+M14+M8 -> #REF! | N20: =Cálculo!C5 -> 286.54894
B21: Auto ME | C21: ='Box (resumo sem AMD)'!C9+'Box (resumo sem AMD)'!C11 -> 50.772246 | D21: ='Box (resumo sem AMD)'!D9+'Box (resumo sem AMD)'!D11 -> 43.036334 | E21: =D21-C21 -> -7.7359114 | F21: =G21*1000/E21 -> 450.3894 | G21: ='Box (resumo sem AMD)'!G11+'Box (resumo sem AMD)'!G9 -> -3.4841725 | L21: =#REF!*#REF! -> #REF! | M21: =M20-Cálculo!F48/1000 -> #REF! | N21: =N17-Cálculo!C5 -> 0
I22: Incluir no NRP
G23: =Cálculo!C6+Cálculo!C7 -> -6.6803807 | I23: Auto ME | L23: =N23/M23*1000 -> -2.6393598 | M23: ='Box (resumo sem AMD)'!M11+'Box (resumo sem AMD)'!M9 -> 43.036334 | N23: ='Box (resumo sem AMD)'!N11+'Box (resumo sem AMD)'!N9 -> -0.11358837 | P23: For information only - Selling price (Base & extra)
F24: =('Box (resumo SAIDA)'!F13-'Box (resumo SAIDA)'!F8)*E17/1000 -> 5.344017 | G24: =G19-G23 -> -1.7763568e-14
E25: =Cálculo!F48-Cálculo!C48 -> -125775.25 | P25: $/t | Q25: Var | R25: =M4 -> Vol FY26'F7 | S25: MUSD | T25: $/t | U25: Var | V25: =R25 -> Vol FY26'F7 | W25: MUSD
B26: =('Box (resumo SAIDA)'!F13-'Box (resumo SAIDA)'!F8)*'Box (resumo SAIDA)'!E17/1000 -> 5.344017 | C26: =C9+C17 -> 7183.3337 | D26: =D9+D17 -> 7057.6052 | F26: =Cálculo!C6+Cálculo!C7 -> -6.6803807 | P26: Base | T26: Extra
D27: =Cálculo!F114-Cálculo!C114 -> -125775.25 | F27: =F26-G19 -> 1.7763568e-14 | P27: Calvert | Q27: ='[32]Analise Calvert - Base'!$G$19-'[32]Analise Calvert - Base'!$D$19+0.6 -> 3.5542493 | R27: ='[32]Analise Calvert - Base'!$F$19/1000 -> 1091.657 | S27: =Q27*R27/1000 -> 3.8800213 | T27: Calvert | U27: ='[32]Analise Calvert - Extra'!$G$19-'[32]Analise Calvert - Extra'!$D$19 -> -1.238592 | V27: ='[32]Analise Calvert - Base'!$F$19/1000 -> 1091.657 | W27: =U27*V27/1000 -> -1.3521177 | X27: =S27+W27 -> 2.5279036 | Y27: =N5 -> 87.293039
B28: =G13+G8 -> -4.9115034 | C28: =Cálculo!C48 -> 7232333.7 | D28: =Cálculo!F48 -> 7106558.5 | F28: =G16/45 -> 0 | P28: Others | Q28: ='[32]Analise SLAB Others Base'!$G$45-'[32]Analise SLAB Others Base'!$D$45+0.4 -> 16.516414 | R28: ='[32]Analise SLAB Others Base'!$F$45/1000 -> 1655.1978 | S28: =Q28*R28/1000-0.3 -> 27.037931 | T28: Others | U28: ='[32]Analise SLAB Others Extra'!$G$45-'[32]Analise SLAB Others Extra'!$D$45+0.4 -> 4.7758742 | V28: ='[32]Analise SLAB Others Base'!$F$45/1000 -> 1655.1978 | W28: =U28*V28/1000 -> 7.9050163 | X28: =S28+W28 -> 34.942948 | Y28: =N6 -> 71.850814
B29: =B28-B26 -> -10.25552 | P29: Total base | S29: =S28+S27 -> 30.917953 | T29: Total extra | W29: =W27+W28-0.1 -> 6.4528986
F30: =('Box (resumo SAIDA)'!F13-'Box (resumo SAIDA)'!F8)*'Box (resumo SAIDA)'!E17/1000 -> 5.344017
C31: =SUMPRODUCT(F13:F13,D13:D13)/SUM(D13:D13) -> 184.45913 | P31: Total | W31: =W29+S29 -> 37.370851
C32: =C31-F8 -> 132.16027
C33: =C32*E17 -> 5344.017 | F33: =225*63 -> 14175 | W33: =N5+N6 -> 159.14385
W34: =W33-W31 -> 121.773
L37: =('Box (resumo SAIDA)'!F13-'Box (resumo SAIDA)'!F8)*'Box (resumo SAIDA)'!E17/1000 -> 5.344017
B53: For information only | F53: tvc
B55: US tariffs impact | C55: Vol (kt) | D55: MC ($/t) | E55: MUSD
B56: Volume & Mix | E56: ='[33]Saida box receita FY'!$N$29 -> -6.2499621
B57: Selling Price | E57: ='[33]Saida box receita FY'!$N$30+[34]MRF02!$AN$37-10.9-0.6 -> -61.006643
B58: Alloys market driven | E58: -3
B59: Total | E59: =SUM(E56:E58) -> -70.256605
B63: For information only | F63: AMP
B65: US tariffs impact | C65: Vol (kt) | D65: MC ($/t) | E65: MUSD
B66: Volume & Mix | E66: -22
B67: Selling Price | E67: -46
B68: Alloys market driven | E68: 10
B69: Total | E69: =SUM(E66:E68) -> -58
B71: For information only | F71: consolidado
B73: US tariffs impact | C73: Vol (kt) | D73: MC ($/t) | E73: MUSD
B74: Volume & Mix | E74: =E56+E66 -> -28.249962
B75: Selling Price | E75: =E57+E67 -> -107.00664
B76: Alloys market driven | E76: =E58+E68 -> 7
B77: Total | E77: =SUM(E74:E76) -> -128.25661

Sheet Check BPM
C4: QT7000REF Steel Sales (in MT) | D4: ASP Average Selling Price | E4: EBITDAREF EBITDA | F4: GAP Legal to Managerial | G4: EBITDAMREF EBITDA Managerial | H4: VOLEF Volume Effect | I4: MIXIMPACT Mix Impact | J4: SELPRICE Selling Price Impact | K4: INPUTPRICEIM Input Price Impact | L4: TSTOCKEF Stock effect | M4: USAGEMIX Usage & Mix Variance | N4: T600FEBTOT Fixed Costs Variance | O4: NSEBITDATOT Non Steel EBITDA Variance | P4: UNITEMVAR Unusual Items Variance | Q4: FOREXBRTOT Forex Impact | R4: OTHER Other (Bridge) | S4: OTHER-CONV Other Converted (EUR entitie for Bridge) | T4: FOREX-EUR Forex (EUR entitie for Bridge) Impact | U4: EBITDAMCUR EBITDA Managerial | V4: Gap Legal to Managerial | W4: EBITDACUR EBITDA | X4: QT7000CUR Steel Sales (in MT) | Y4: ASP Average Selling Price
C5: Reference Period | D5: Reference Period | E5: Reference Period | F5: Reference Period | G5: Reference Period | U5: Current/Projected period | V5: Current/Projected period | W5: Current/Projected period | X5: Current/Projected period | Y5: Current/Projected period
A7: SCENARIO DESCRIPTION
A10: Act Q3'21 vs Act Q2'21 / Qn A vs Qn-1 A
A11: Fcst Q4’21 vs Act Q3’21 / Qn+1 F vs Qn A
A12: Act Q3'21 vs Act Q3'20 / Qn Y A vs Qn Y-1 A
A13: FY F 21 vs FY B 21 / FY F vs FY B | H13: -23 | I13: 16 | J13: 287 | K13: -177 | L13: 0 | M13: -12 | N13: -34 | P13: -10 | Q13: 70 | R13: -9.03156 | U13: 1151.3449 | V13: -4.982228 | W13: 1285.775 | X13: 6436.0818 | Y13: 996.87798
A14: FY F 21 vs FY A 20 / FYn F vs FYn-1 A
H17: =H13-Cálculo!C6 -> 0.1262211 | I17: =I13-Cálculo!C7 -> -0.44584038 | J17: =J13-Cálculo!C5 -> 0.45105631 | K17: =K13-Cálculo!C9 -> 0.47194678 | L17: =L13-Cálculo!C12 -> 4.4371962 | M17: =M13-Cálculo!C10 -> 0.82934337 | N17: =N13-Cálculo!C8 -> 0.29055852 | P17: =P13-Cálculo!C11 -> -4.2359796 | Q17: =Q13-Cálculo!C4 -> -0.57285861

Sheet BPM
E2: Comment for exceptional delta
A5: ACCOUNT DESCRIPTION | B5: CODE
A7: Volume Effect MUSD | B7: VOLEF | D7: =Cálculo!C6 -> -23.126221
A8: Mix Impact | B8: MIXIMPACT | D8: =Cálculo!C7 -> 16.44584
A9: SellingPrice | B9: SELPRICE | D9: =Cálculo!C5 -> 286.54894
A10: Fixed Cost Absorbtion / Release (inventory change) | B10: TSTOCKEF1 | D10: =Cálculo!C12 -> -4.4371962
A11: Fixed Cost per Ton changes / Weighted avg FC impact | B11: TSTOCKEF2
A12: Weighted Average Variable Cost Impact | B12: TSTOCKEF3
A13: Idle Capacity | B13: TSTOCKEF4
A14: Other (physical inventory & aging reserve) | B14: TSTOCKEF5
A15: Input price variance - Coking coal | B15: INP-PRICIM1 | D15: =Box!U6 -> -48.13571
A16: Input price variance - PCI coal | B16: INP-PRICIM2 | D16: =Box!U7 -> -47.243088
A17: Input price variance - Coke | B17: INP-PRICIM3 | D17: =Box!U9 -> -2.7166629
A18: Input price variance - Iron ore | B18: INP-PRICIM4 | D18: =SUM(Box!U12:U14) -> -54.073371
A19: Input price variance - Scrap | B19: INP-PRICIM5
A20: Input price variance - Ferro alloys | B20: INP-PRICIM6 | D20: =Box!U15 -> -12.014339
A21: Input price variance - Base metals | B21: INP-PRICIM7
A22: Input price variance - Fluxes | B22: INP-PRICIM8 | D22: =Box!U19 -> -7.03
A23: Input price variance - Electricity | B23: INP-PRICIM9
A24: Input price variance - Gas | B24: INP-PRICIM10 | D24: =Box!U17 -> 0.20690204
A25: Input price variance - Other | B25: INP-PRICIM11 | D25: =Box!U18+Box!U20+Box!U10 -> -6.4656783
A26: RM Mix - RM Mix - Iron Ores | B26: USAGEMIX1 | D26: ='[10]Bridges complementares'!C5 -> 0
A27: RM Mix - Coals/Coke | B27: USAGEMIX2 | D27: ='[10]Bridges complementares'!C6 -> -3.3995496
A28: RM Mix - Scrap / Hot Metal / DRI | B28: USAGEMIX3 | D28: ='[10]Bridges complementares'!C7 -> -3
A29: RM Mix - Ferro Alloys / Stoppages / Refractories / Other | B29: USAGEMIX4 | D29: ='[10]Bridges complementares'!C8 -> -6.4297938
A30: Usage - Metallic & Charge (yields) | B30: USAGEMIX5 | D30: ='[10]Bridges complementares'!C9 -> 0
A31: Usage - Coke (BF) | B31: USAGEMIX6 | D31: ='[10]Bridges complementares'!C10 -> 0
A32: Usage - Energy | B32: USAGEMIX7 | D32: ='[10]Bridges complementares'!C11 -> 0
A33: By-product credits | B33: USAGEMIX8 | D33: ='[10]Bridges complementares'!C12 -> 0
A34: Other variable costs / Purchased slab penalty | B34: USAGEMIX9 | D34: ='[10]Bridges complementares'!C13 -> 0
A35: Other variable costs / Purchased slab penalty
A36: FC - Manpower costs - COGS | B36: T600FEB1 | D36: =Cálculo!J189 -> -27.684098
A37: FC - Manpower costs - SG&A | B37: T600FEB2 | D37: =Cálculo!J190 -> -3.6834087
A38: FC - Non-manpower costs - SG&A | B38: T600FEB3 | D38: =Cálculo!J191+Cálculo!J192 -> -2.2638715
A39: FC - R&M spares | B39: T600FEB4 | D39: =Cálculo!J193 -> -1.8627139
A40: FC - Contractors & Services (prod & R&M) | B40: T600FEB5 | D40: =Cálculo!J194 -> 3.5177748
A41: FC - Structure costs | B41: T600FEB6 | D41: =Cálculo!J195+Cálculo!J196 -> -2.2942719
A42: FC - Other | B42: T600FEB7 | G42: Ref | H42: Cur | I42: Var | J42: Check
A43: Unusual Item 1 | B43: UNITEM1 | I43: =H43-G43 -> 0 | J43: =I43-D43 -> 0
A44: Unusual Item 2 | B44: UNITEM2 | D44: =Cálculo!I155/1000+Cálculo!I164/1000 -> -5.7640204 | E44: Logistic / VAT | G44: =-Cálculo!L159-3 -> -117.03548 | H44: =-Cálculo!M159 -> -122.4933 | I44: =H44-G44 -> -5.4578207 | J44: =I44-D44 -> 0.30619963
A45: Unusual Item 3 | B45: UNITEM3
A46: Unusual Item 4 | B46: UNITEM4
A47: Unusual Item 5 | B47: UNITEM5 | D47: =Cálculo!I175/1000 -> -4.896564 | E47: =Cálculo!B175 -> Invest-ES | G47: =Cálculo!E175/1000 -> 134.78471 | H47: =Cálculo!H175/1000 -> 129.88814 | I47: =H47-G47 -> -4.896564 | J47: =I47-D47 -> 9.7699626e-15
A48: Unusual Item 6 | B48: UNITEM6
A49: Unusual Item 7 | B49: UNITEM7
A50: Unusual Item 8 | B50: UNITEM8
A51: Unusual Item 9 | B51: UNITEM9
A52: Unusual Item 10 | B52: UNITEM10
A53: Unusual Item - Other | B53: UNITEMOTH
A54: NS-EBITDA - Liquid steel sales to Long | B54: NSEBITDA1
A55: NS-EBITDA - Coke sales | B55: NSEBITDA2
A56: NS-EBITDA - Coal sales | B56: NSEBITDA3
A57: NS-EBITDA - Scrap sales | B57: NSEBITDA4
A58: NS-EBITDA - Iron ore & Pellet sales | B58: NSEBITDA5
A59: NS-EBITDA - Iron ore fines sales | B59: NSEBITDA6
... A64: NS-EBITDA - Other | B64: NSEBITDA11
A65: Forex on Revenue | B65: FOREXREV | D65: =Box!AM5+Box!AM6 -> 143.40091
A66: Forex on Costs | B66: FOREXCOST | D66: =Box!AM7 -> -72.828056
A67: Forex on Other | B67: FOREXOTH
A68: VC Management gains A | B68: VCMGTGA
A69: FC Management gains A | B69: FCMGTGA
A70: Other MG A | B70: OTHMGTGA
A71: VC Management gains B | B71: VCMGTGB
A72: FC Management gains B | B72: FCMGTGB
A73: Other MG B | B73: OTHMGTGB
A76: Variance value between periods in mUSD/m€
A78: Absolute value for the periods in mUSD/m€
A80: Comment for exceptional delta
A83: Checks
A84: Stock variation | D84: =Cálculo!C12-SUM(D10:D14) -> 0
A85: Input price | D85: =Cálculo!C9-SUM(D15:D25) -> 0
A86: Usage | D86: =Cálculo!C10-SUM(D26:D34) -> 0
A87: Fixed cost | D87: =Cálculo!C8-SUM(D36:D42) -> -0.019968984
A88: Others (Unusual) | D88: =Cálculo!C11-SUM(D43:D53) -> 4.896564
A89: Non Steel
A90: Forex | D90: =Cálculo!C4-SUM(D65:D67) -> -6.9633188e-13
D92: =Cálculo!C13-Cálculo!C3 -> 115.64836
D93: =SUM(D7:D67) -> 110.77176
D94: =D92-D93 -> 4.876595

Sheet Analise mes minério
C1: Bridge | D1: Var. | E1: KD | G1: IP
B2: Budget vs MRF1 | C2: =[18]Box!$U$11 -> -32.207643 | D2: =C2 -> -32.207643 | E2: =F19 -> -32.404121 | F2: =C2-E2 -> 0.19647807
B3: Budget vs MRF2 | C3: =[19]Box!$U$11 -> -24.749472 | D3: =C3-C2 -> 7.4581713 | E3: =I18 -> 6.3784712 | F3: =D3-E3 -> 1.0797001
B4: Budget vs MRF3 | C4: =[21]Box!$U$11 -> -20.353894 | D4: =C4-C3 -> 4.3955778 | E4: =L19 -> 3.6635359 | F4: =D4-E4 -> 0.73204189
B5: Budget vs MRF4 | C5: =[22]Box!$U$11 -> 36.732446 | D5: =C5-C4 -> 57.08634 | E5: =O20 -> 59.494899 | F5: =D5-E5 -> -2.4085592
B6: Budget vs MRF5 | C6: =[23]Box!$U$11 -> 33.876311 | D6: =C6-C5 -> -2.8561355 | E6: =R18 -> -11.161322 | F6: =D6-E6 -> 8.3051861
B7: Budget vs MRF6 | C7: =Box!$U$11 -> -54.073371 | D7: =C7-C6 -> -87.949681 | E7: =U21 -> 2.2260463 | F7: =D7-E7 -> -90.175728
D8: =SUM(D2:D7) -> -54.073371 | E8: =SUM(E2:E7) -> 28.19751 | F8: =D8-E8 -> -82.270881
E10: MRF1 | H10: MRF2 | K10: mrf3 | N10: mrf4 | Q10: mrf5
E11: Input Price | H11: Input Price | K11: Input Price | N11: Input Price | Q11: Input Price | T11: Input Price
E13: =A13 -> 0 | F13: =F15+F16+F17 -> -23.830202 | H13: Impact | I13: MUSD | K13: Impact | L13: MUSD | N13: =K13 -> Impact | O13: MUSD | Q13: Impact | R13: MUSD | T13: Impact | U13: MUSD
E14: Coal | F14: -23.830202 | H14: Coal | I14: -12.315596 | K14: Coal | L14: -3 | N14: Coal | O14: 7.2991734 | Q14: Coal | R14: 0 | T14: Coal | U14: 1.6357735
E15: International ref. | F15: -12.762719 | H15: Internacional reference | I15: -14.315596 | K15: Mix | L15: -5 | N15: International ref. | O15: 12 | Q15: International ref. | R15: 0 | T15: Price (may) | U15: 3
E16: Starting balance | F16: -13.216352 | H16: Mix/Others | I16: 2 | K16: Q2 PCI ratio | L16: 4 | N16: Q3 PCI ratio | O16: 5.3 | Q16: Mix | R16: 0 | T16: AMS contract updates | U16: 6
E17: Mix / others | F17: 2.148869 | H17: Purchased Coke | I17: -0.49931138 | K17: Demurrage | L17: -2 | N17: Freight | O17: -2 | Q17: Purchased Coke | R17: 0 | T17: (Price) PCI index | U17: -1.2956606
E18: Purchased Coke | F18: -5.9951706 | H18: Iron ore | I18: 6.3784712 | K18: Purchased Coke | L18: 0 | N18: Purchased Coke | O18: 2.5347094 | Q18: Iron ore | R18: -11.161322 | T18: Demurrage | U18: -3.0685658
E19: Iron ore | F19: -32.404121 | H19: Internacional reference | I19: 5.8423735 | K19: Iron ore | L19: 3.6635359 | N19: Mix | O19: -8 | Q19: International ref. | R19: -11.161322 | T19: Mix | U19: -3
E20: International ref. | F20: -17.602787 | H20: VIU premium (Si, Al & P) | I20: 2 | K20: International ref. | L20: 11.963352 | N20: Iron ore | O20: 59.494899 | Q20: Scrap | R20: 0 | T20: Purchased Coke | U20: 0.38990434
E21: Netback freight | F21: -5.5778136 | H21: % Fe | I21: -1.4639022 | K21: Pellet premium in Q2 | L21: -12.301144 | N21: International ref. | O21: 49.727698 | Q21: Alloys | R21: 0.13 | T21: Iron ore | U21: 2.2260463
E22: Pellet premium | F22: -9.2235212 | H22: Alloys | I22: -0.06 | K22: VIU Vale contract | L22: 4.4431404 | N22: Netback freight | O22: 17.634238 | Q22: Zinc (Vega) | R22: -1.47 | T22: International ref. | U22: -6.2737641
E23: Alloys | F23: -0.29 | H23: Zinc (Vega) | I23: 0.63 | K23: Alloys | L23: -0.27 | N23: Pellet premium | O23: -6.2029299 | Q23: Fluxes | R23: 0 | T23: Pellet premium | U23: 3.1816105
E24: Zinc (Vega) | F24: 0.86 | H24: Fluxes | I24: 0 | K24: Zinc (Vega) | L24: 0.79 | N24: VIU Vale contract | O24: -1.4641068 | Q24: Total | R24: -12.401322 | T24: Vale contract specification H2 | U24: 5.3182
E25: Fluxes | F25: 2 | H25: Total | I25: -5.8664365 | K25: Fluxes | L25: 3 | N25: Scrap | O25: 1.0073149 | T25: Scrap | U25: 0
E26: Total | F26: -59.659494 | K26: Total | L26: 4.1835359 | N26: Alloys | O26: 0.62 | T26: Alloys | U26: -2.35
N27: Zinc (Vega) | O27: 2.95 | T27: Zinc (Vega) | U27: 1.05
N28: Fluxes | O28: 0 | T28: Fluxes | U28: 1.32
N29: Total | O29: 73.906097 | T29: Total | U29: 4.2717242

Sheet jvS
K1: =M17+M19 -> #VALUE!
B3: FC LATAM EBITDA including share of JVs | D3: $m | E3: Budget | F3: MRF9
D4: FC Latam | E4: ='Bridge combinada'!B6+'Bridge combinada'!B7 -> 732.30404 | F4: =SUM('Bridge combinada'!B21:K21) -> 1003.0402
D5: AM Tuper (May-Dec) | E5: =SUM(G31:N31) -> 24.714286 | F5: =SUM(G32:N32) -> 20.090888 | H5: =SUM(F4:F5)/SUM(E4:E5) -> 1.3515275
D6: Share of JV's² | E6: ='[35]MPR - Key figures mensal USD'!Z35 -> 16.145083 | F6: ='[35]MPR - Key figures mensal USD'!AA35 -> 18.269014 | H6: Link FFA
D7: Total | E7: =SUM(E4:E6) -> 773.16341 | F7: =SUM(F4:F6) -> 1041.4001 | H7: =F7/E7 -> 1.346934
B9: FC LATAM EBITDA including share of JVs | D9: $m | E9: Budget | F9: =F3 -> MRF9
D10: FC Latam | E10: =E4 -> 732.30404 | F10: =F4 -> 1003.0402
D11: Share of JV's/subs | E11: =SUM(E5:E6) -> 40.859369 | F11: =SUM(F5:F6) -> 38.359902
D12: Total | E12: =SUM(E10:E11) -> 773.16341 | F12: =SUM(F10:F11) -> 1041.4001
B14: Share of JV's:
B15: Unicon, MAG, Gonvarri e Perfilor de jan a dez
B16: Tuper de jan a abr (40%)
F18: 1. Consolidado | G18: JAN | H18: FEV | I18: MAR | J18: ABR | K18: MAI | L18: JUN | M18: JUL | N18: AGO | O18: SET | P18: OUT | Q18: NOV | R18: DEZ
F19: MR$ | G19: Jan.25 | H19: Feb.25 | I19: Mar.25 | J19: Apr.25 | K19: May.25 | L19: Jun.25 | M19: Jul.25 | N19: Aug.25 | O19: Sep.25 | P19: Oct.25 | Q19: Nov.25 | R19: Dec.25 | S19: Total 2025
F20: MRF9 | G20: 18.9 | H20: 18.8 | I20: 18.8 | J20: 16.5 | K20: 13.5 | L20: 15.5 | M20: 19.1 | N20: 16 | O20: 15 | P20: 15.6 | Q20: 13 | R20: 14.5 | S20: =SUM(G20:R20) -> 195.2 | T20: =S20/5.66 -> 34.487633 | U20: =SUM(G20:J20) -> 73 | V20: =S20-U20 -> 122.2 | W20: =V20/5.66 -> 21.590106
F21: Budget | G21: 13.3 | H21: 12 | I21: 17.5 | J21: 15.8 | K21: 16.8 | L21: 21.4 | M21: 15 | N21: 16.1 | O21: 20.7 | P21: 16.4 | Q21: 17.8 | R21: 14.2 | S21: 197 | T21: =S21/5.66 -> 34.805654 | U21: =SUM(G21:J21) -> 58.6 | V21: =S21-U21 -> 138.4 | W21: =V21/5.6 -> 24.714286
F22: Desvio | G22: 5.6 | H22: 6.8 | I22: 1.3 | J22: 0.7 | K22: -3.3 | L22: -5.9 | M22: 4 | N22: 3.1 | O22: -4.2 | P22: -0.8 | Q22: -1.9 | R22: -2.7 | S22: 2.5
F26: R$ | G26: Mai | H26: Jun | I26: Jul | J26: Ago | K26: Set | L26: Out | M26: Nov | N26: Dez
F27: Budget | G27: =K21 -> 16.8 | H27: =L21 -> 21.4 | I27: =M21 -> 15 | J27: =N21 -> 16.1 | K27: =O21 -> 20.7 | L27: =P21 -> 16.4 | M27: =Q21 -> 17.8 | N27: =R21 -> 14.2
F28: =F20 -> MRF9 | G28: =K20 -> 13.5 | H28: =L20 -> 15.5 | I28: =M20 -> 19.1 | J28: =N20 -> 16 | K28: =O20 -> 15 | L28: =P20 -> 15.6 | M28: =Q20 -> 13 | N28: =R20 -> 14.5
F30: $ | G30: Mai | H30: Jun | I30: Jul | J30: Ago | K30: Set | L30: Out | M30: Nov | N30: Dez
F31: Budget | G31: =G27/5.6 -> 3 | H31: =H27/5.6 -> 3.8214286 | I31: =I27/5.6 -> 2.6785714 | J31: =J27/5.6 -> 2.875 | K31: =K27/5.6 -> 3.6964286 | L31: =L27/5.6 -> 2.9285714 | M31: =M27/5.6 -> 3.1785714 | N31: =N27/5.6 -> 2.5357143
F32: =F28 -> MRF9 | G32: =G31/'[36]2025 - US$ EUA '!$F$57 -> 0.5293446 | H32: =H28/'[36]2025 - US$ EUA '!$G$57 -> 2.7942755 | I32: =I28/'[36]2025 - US$ EUA '!$H$57 -> 3.4548304 | J32: =J28/'[36]2025 - US$ EUA '!$I$57 -> 2.9374378 | K32: =K28/'[36]2025 - US$ EUA '!$J$57 -> 2.6785714 | L32: =L28/'[36]2025 - US$ EUA '!$K$57 -> 2.7857143 | M32: =M28/'[36]2025 - US$ EUA '!$L$57 -> 2.3214286 | N32: =N28/'[36]2025 - US$ EUA '!$M$57 -> 2.5892857
F36: Actual | G36: Jan | H36: Fev | I36: Mar | J36: Abr | K36: Total
F37: EBITDA BRL | G37: 18,87 | H37: 18,83 | I37: 18,78 | J37: 16,45 | K37: 72.94
F38: Forex | G38: 6,02 | H38: 5,77 | I38: 5,75 | J38: 5,78 | K38: 5.83
F39: EBITDA USD | G39: 3,13 | H39: 3,27 | I39: 3,27 | J39: 2,85 | K39: 12.51
F40: Share | G40: 0.4 | H40: 0.4 | I40: 0.4 | J40: 0.4 | K40: 0.4
F41: EBITDA USD / share | G41: 1.25 | H41: 1.31 | I41: 1.31 | J41: 1.14 | K41: =SUM(G41:J41) -> 5.01
J42: =SUM(G41:J41) -> 5.01
F44: Budget | G44: Jan | H44: Fev | I44: Mar | J44: Abr | K44: Mai | L44: Jun | M44: Jul | N44: Ago | O44: Set | P44: Out | Q44: Nov | R44: Dez | S44: FY25
F45: EBITDA BRL | G45: 13,31 | H45: 12,02 | I45: 17,53 | J45: 15,76 | K45: 16,82 | L45: 24,32 | M45: 17,45 | N45: 18,54 | O45: 23,49 | P45: 18,90 | Q45: 20,64 | R45: 16,40 | S45: 215.17
F46: Forex | G46: 5,60 | H46: 5,60 | I46: 5,60 | J46: 5,60 | K46: 5,60 | L46: 5,60 | M46: 5,60 | N46: 5,60 | O46: 5,60 | P46: 5,60 | Q46: 5,60 | R46: 5,60 | S46: 5.6
F47: EBITDA USD | G47: 2,38 | H47: 2,15 | I47: 3,13 | J47: 2,81 | K47: 3,00 | L47: 4,34 | M47: 3,12 | N47: 3,31 | O47: 4,19 | P47: 3,37 | Q47: 3,69 | R47: 2,93 | S47: 38.42
F48: Share | G48: 0.4 | H48: 0.4 | I48: 0.4 | J48: 0.4 | K48: 0.4 | L48: 0.4 | M48: 0.4 | N48: 0.4 | O48: 0.4 | P48: 0.4 | Q48: 0.4 | R48: 0.4 | S48: 0.4
F49: EBITDA USD / share | G49: 0.95 | H49: 0.86 | I49: 1.25 | J49: 1.13 | K49: 1.2 | L49: 1.74 | M49: 1.25 | N49: 1.32 | O49: 1.68 | P49: 1.35 | Q49: 1.47 | R49: 1.17 | S49: 15.37
J50: =SUM(G49:J49) -> 4.19

Sheet Bridge
W11: 1111.04
U17: =A29 -> FY26 Budget | V17: =A30 -> Vol & Mix | W17: =A32 -> Selling price | X17: =A33 -> Input price | Y17: Usage Market driven | Z17: Usage Performance | AA17: =A35 -> Fixed costs | AB17: Logistic | AC17: =A36 -> Exchange rate | AD17: SV/Others | AE17: =A40 -> FY26 MRF7
U19: =B29 -> 632.04404 | V19: =B30 -> -6.6803807 | W19: =B32 -> 286.54894 | X19: =B33 -> -177.47195 | Y19: =Box!AD8 -> -8.7367984 | Z19: =Box!AA11 -> -4.0925449 | AA19: =B35 -> -34.290559 | AB19: =Cálculo!I155/1000 -> -5.7640204 | AC19: =B36 -> 70.572859 | AD19: =Cálculo!C12 -> -4.4371962 | AE19: e | AH19: =V32 -> 0 | AI19: =W32 -> 0 | AJ19: =X32 -> 0 | AK19: =Y32 -> 0 | AL19: =AA32 -> 0 | AM19: =AC32 -> 0 | AN19: =#REF! -> #REF! | AO19: =#REF! -> #REF!
V22: =Cálculo!C6+Cálculo!C7 -> -6.6803807 | W22: =Cálculo!C5 -> 286.54894 | X22: =Cálculo!C9 -> -177.47195 | Y22: =Cálculo!C10 -> -12.829343
AE24: =SUM(U19:AD19) -> 747.6924
AE25: =Cálculo!C13 -> 747.6924
AE26: =AE25-AE24 -> 0
B28: Amount | C28: Cumulated | D28: Ext. points | E28: Blank neg | F28: Red neg | G28: Green neg | H28: Blank pos | I28: Red pos | J28: Green pos
A29: FY26 Budget | B29: =Cálculo!C3 -> 632.04404 | C29: =+SUM(B29) -> 632.04404 | D29: =+B29 -> 632.04404
A30: Vol & Mix | B30: =Cálculo!C6+Cálculo!C7 -> -6.6803807 | C30: =+SUM(B29:B30) -> 625.36366 | E30: =IF(AND(C30<0,C29<0),MAX(C29:C30),0) -> 0 | F30: =IF(AND(C30<0,B30<0),MAX(B30,C30),0) -> 0 | G30: =IF(AND(C29<0,B30>0),MAX(-B30,C29),0) -> 0 | H30: =IF(AND(C30>0,C29>0),MIN(C29:C30),0) -> 625.36366 | J30: =IF(AND(C30>0,B30>0),MIN(B30,C30),0) -> 0
A31: Mix | C31: =+SUM(B29:B31) -> 625.36366 | E31: =IF(AND(C31<0,C30<0),MAX(C30:C31),0) -> 0 | F31: =IF(AND(C31<0,B31<0),MAX(B31,C31),0) -> 0 | G31: =IF(AND(C30<0,B31>0),MAX(-B31,C30),0) -> 0 | H31: =IF(AND(C31>0,C30>0),MIN(C30:C31),0) -> 625.36366 | I31: =IF(AND(C30>0,B31<0),MIN(-B31,C30),0) -> 0 | J31: =IF(AND(C31>0,B31>0),MIN(B31,C31),0) -> 0
A32: Selling price | B32: =Cálculo!C5 -> 286.54894 | C32: =+SUM(B29:B32) -> 911.91261 | E32: =IF(AND(C32<0,C31<0),MAX(C31:C32),0) -> 0 | F32: =IF(AND(C32<0,B32<0),MAX(B32,C32),0) -> 0 | G32: =IF(AND(C31<0,B32>0),MAX(-B32,C31),0) -> 0 | H32: =IF(AND(C32>0,C31>0),MIN(C31:C32),0) -> 625.36366 | J32: =IF(AND(C32>0,B32>0),MIN(B32,C32),0) -> 286.54894
A33: Input price | B33: =Cálculo!C9 -> -177.47195 | C33: =+SUM(B29:B33) -> 734.44066 | E33: =IF(AND(C33<0,C32<0),MAX(C32:C33),0) -> 0 | F33: =IF(AND(C33<0,B33<0),MAX(B33,C33),0) -> 0 | G33: =IF(AND(C32<0,B33>0),MAX(-B33,C32),0) -> 0 | H33: =IF(AND(C33>0,C32>0),MIN(C32:C33),0) -> 734.44066 | I33: =IF(AND(C32>0,B33<0),MIN(-B33,C32),0) -> 177.47195
A34: Usage | B34: =Cálculo!C10 -> -12.829343 | C34: =+SUM(B29:B34) -> 721.61132 | E34: =IF(AND(C34<0,C33<0),MAX(C33:C34),0) -> 0 | F34: =IF(AND(C34<0,B34<0),MAX(B34,C34),0) -> 0 | G34: =IF(AND(C33<0,B34>0),MAX(-B34,C33),0) -> 0 | H34: =IF(AND(C34>0,C33>0),MIN(C33:C34),0) -> 721.61132 | J34: =IF(AND(C34>0,B34>0),MIN(B34,C34),0) -> 0
A35: Fixed costs | B35: =Cálculo!C8 -> -34.290559 | C35: =+SUM(B29:B35) -> 687.32076 | E35: =IF(AND(C35<0,C34<0),MAX(C34:C35),0) -> 0 | F35: =IF(AND(C35<0,B35<0),MAX(B35,C35),0) -> 0 | G35: =IF(AND(C34<0,B35>0),MAX(-B35,C34),0) -> 0 | H35: =IF(AND(C35>0,C34>0),MIN(C34:C35),0) -> 687.32076 | I35: =IF(AND(C34>0,B35<0),MIN(-B35,C34),0) -> 34.290559 | AA35: sd
A36: Exchange rate | B36: =Cálculo!$C$4 -> 70.572859 | C36: =+SUM(B29:B36) -> 757.89362 | E36: =IF(AND(C36<0,C35<0),MAX(C35:C36),0) -> 0 | F36: =IF(AND(C36<0,B36<0),MAX(B36,C36),0) -> 0 | G36: =IF(AND(C35<0,B36>0),MAX(-B36,C35),0) -> 0 | H36: =IF(AND(C36>0,C35>0),MIN(C35:C36),0) -> 687.32076 | I36: =IF(AND(C35>0,B36<0),MIN(-B36,C35),0) -> 0
A37: Vale impact | C37: =+SUM(B29:B37) -> 757.89362 | E37: =IF(AND(C37<0,C36<0),MAX(C36:C37),0) -> 0 | F37: =IF(AND(C37<0,B37<0),MAX(B37,C37),0) -> 0 | G37: =IF(AND(C36<0,B37>0),MAX(-B37,C36),0) -> 0 | H37: =IF(AND(C37>0,C36>0),MIN(C36:C37),0) -> 757.89362 | I37: =IF(AND(C36>0,B37<0),MIN(-B37,C36),0) -> 0
A38: Non recurrent | C38: =+SUM(B29:B38) -> 757.89362 | E38: =IF(AND(C38<0,C36<0),MAX(C36:C38),0) -> 0 | F38: =IF(AND(C38<0,B38<0),MAX(B38,C38),0) -> 0 | G38: =IF(AND(C36<0,B38>0),MAX(-B38,C36),0) -> 0 | H38: =IF(AND(C38>0,C36>0),MIN(C36:C38),0) -> 757.89362 | J38: =IF(AND(C38>0,B38>0),MIN(B38,C38),0) -> 0
A39: SV & Others | B39: =Cálculo!C11+Cálculo!C12-Bridge!B37-Bridge!B38 -> -10.201217 | C39: =+SUM(B29:B39) -> 747.6924 | E39: =IF(AND(C39<0,C38<0),MAX(C38:C39),0) -> 0 | F39: =IF(AND(C39<0,B39<0),MAX(B39,C39),0) -> 0 | G39: =IF(AND(C38<0,B39>0),MAX(-B39,C38),0) -> 0 | H39: =IF(AND(C39>0,C38>0),MIN(C38:C39),0) -> 747.6924 | I39: =IF(AND(C38>0,B39<0),MIN(-B39,C38),0) -> 10.201217 | J39: =IF(AND(C39>0,B39>0),MIN(B39,C39),0) -> 0
A40: FY26 MRF7 | B40: =SUM(B29:B39) -> 747.6924 | C40: =+SUM(B29:B40) -> 1495.3848 | D40: =+B40 -> 747.6924
A41: Check | B41: =Cálculo!C13-B40 -> 0

Sheet Box combinado
B3: Volume & Mix | E3: Selling price | H3: Input price | K3: Usage - Market driven | N3: Usage - Performance | Q3: Fixed costs | T3: Logistic | W3: Exchange rate | Z3: Others
B5: Consolidated | C5: MUSD | E5: Consolidated | F5: MUSD | H5: Consolidated | I5: MUSD | K5: Consolidated | L5: MUSD | N5: Consolidated | O5: MUSD | Q5: Consolidated | R5: MUSD | T5: Consolidated | U5: MUSD | W5: Consolidated | X5: MUSD | Z5: Consolidated | AA5: MUSD
B6: TVC | C6: =Bridge!V19 -> -6.6803807 | E6: TVC | F6: =Bridge!W19 -> 286.54894 | H6: TVC | I6: =Bridge!X19 -> -177.47195 | K6: TVC | L6: =Bridge!Y19 -> -8.7367984 | N6: TVC | O6: =Bridge!Z19 -> -4.0925449 | Q6: TVC | R6: =Bridge!AA19 -> -34.290559 | T6: TVC | U6: =Bridge!AB19 -> -5.7640204 | W6: TVC | X6: =Bridge!AC19 -> 70.572859 | Z6: TVC | AA6: =Bridge!AD19+'Bridge combinada'!K23 -> -4.2108092
B7: AM Pecém | C7: ='Bridge combinada'!C15 -> 23.3 | E7: AM Pecém | F7: ='Bridge combinada'!D15 -> 209.35 | H7: AM Pecém | I7: ='Bridge combinada'!E15 -> -57.55 | K7: AM Pecém | L7: ='Bridge combinada'!F15 -> -56.15 | N7: AM Pecém | O7: ='Bridge combinada'!G15 -> 9.92 | Q7: AM Pecém | R7: ='Bridge combinada'!H15 -> -7.6 | T7: AM Pecém | U7: ='Bridge combinada'!I15 -> -0.6 | W7: AM Pecém | X7: ='Bridge combinada'!J15 -> -22.53 | Z7: AM Pecém | AA7: ='Bridge combinada'!K15 -> -9.5
B8: AM Tuper | C8: ='Bridge combinada'!C16 -> 0.7 | E8: AM Tuper | F8: ='Bridge combinada'!D16 -> 11.2 | H8: AM Tuper | I8: ='Bridge combinada'!E16 -> -10.9 | K8: AM Tuper | L8: ='Bridge combinada'!F16 -> 0 | N8: AM Tuper | O8: ='Bridge combinada'!G16 -> 0 | Q8: AM Tuper | R8: ='Bridge combinada'!H16 -> -0.5 | T8: AM Tuper | U8: ='Bridge combinada'!I16 -> 0 | W8: AM Tuper | X8: ='Bridge combinada'!J16 -> 2.2 | Z8: AM Tuper | AA8: ='Bridge combinada'!K16 -> 10.1
B9: AM Tekno | C9: ='Bridge combinada'!C17 -> 0.71980764 | E9: AM Tekno | F9: ='Bridge combinada'!D17 -> 0.72162239 | H9: AM Tekno | I9: ='Bridge combinada'!E17 -> 0.01658585 | K9: AM Tekno | L9: ='Bridge combinada'!F17 -> 0 | N9: AM Tekno | O9: ='Bridge combinada'!G17 -> 0.24651878 | Q9: AM Tekno | R9: ='Bridge combinada'!H17 -> 0.50828804 | T9: AM Tekno | U9: ='Bridge combinada'!I17 -> 0 | W9: AM Tekno | X9: ='Bridge combinada'!J17 -> 0.281026 | Z9: AM Tekno | AA9: ='Bridge combinada'!K17 -> -0.069616127
B10: Total | C10: =SUM(C6:C9) -> 18.039427 | E10: Total | F10: =SUM(F6:F9) -> 507.82057 | H10: Total | I10: =SUM(I6:I9) -> -245.90536 | K10: Total | L10: =SUM(L6:L9) -> -64.886798 | N10: Total | O10: =SUM(O6:O9) -> 6.0739738 | Q10: Total | R10: =SUM(R6:R9) -> -41.88227 | T10: Total | U10: =SUM(U6:U9) -> -6.3640204 | W10: Total | X10: =SUM(X6:X9) -> 50.523885 | Z10: Total | AA10: =SUM(AA6:AA9) -> -3.6804253

Sheet Bridge combinada
B2: =B6-Bridge!U19 -> 0 | C2: =C6-Bridge!V19 -> 0 | D2: =D6-Bridge!W19 -> 0 | E2: =E6-Bridge!X19 -> 0 | F2: =F6-Bridge!Y19 -> 0 | G2: =G6-Bridge!Z19 -> 0 | H2: =H6-Bridge!AA19 -> 0 | I2: =I6-Bridge!AB19 -> 0 | ... K2: =K6-Bridge!AD19 -> 0.226387 | L2: =L6-Bridge!#REF! -> #REF!
B4: =Bridge!U17 -> FY26 Budget | C4: =Bridge!V17 -> Vol & Mix | D4: =Bridge!W17 -> Selling price | E4: =Bridge!X17 -> Input price | F4: Usage Market driven | G4: Usage Operational Performance | H4: =Bridge!AA17 -> Fixed costs | I4: =Bridge!AB17 -> Logistic | J4: =Bridge!AC17 -> Exchange rate | K4: SV/Others | L4: =Bridge!AE17 -> FY26 MRF7 | M4: =L6+L7 -> 936.81879 | U4: 669.3
U5: 292.1
A6: TVC | B6: =B13 -> 632.04404 | C6: =C13 -> -6.6803807 | D6: =D13 -> 286.54894 | E6: =E13 -> -177.47195 | F6: =F13 -> -8.7367984 | G6: =G13 -> -4.0925449 | H6: =H13 -> -34.290559 | I6: =I13 -> -5.7640204 | J6: =J13 -> 70.572859 | K6: =K13+K23 -> -4.2108092 | L6: =SUM(B6:K6) -> 747.91879 | M6: =L6-Cálculo!C13 -> 0.226387 | O6: 582
A7: AMP | B7: 100.26 | C7: 23.3 | D7: 209.35 | E7: -57.55 | F7: -56.15 | G7: 9.92 | H7: -7.6 | I7: -0.6 | J7: -22.53 | K7: -9.5 | L7: =SUM(B7:K7) -> 188.9 | O7: 366 | P7: =L6+L7 -> 936.81879 | S7: =L6+L7 -> 936.81879
A8: TUPER | B8: 38.4 | C8: 0.7 | D8: 11.2 | E8: -10.9 | H8: -0.5 | J8: 2.2 | K8: 10.1 | L8: =SUM(B8:K8) -> 51.2 | O8: =O6+O7 -> 948
A9: TEKNO | B9: 12.597163 | C9: 0.71980764 | D9: 0.72162239 | E9: 0.01658585 | G9: 0.24651878 | H9: 0.50828804 | J9: 0.281026 | K9: -0.069616127 | L9: =SUM(B9:K9) -> 15.021395
L10: =SUM(L6:L9) -> 1003.0402
C11: =B7+C7+D7+E7+F7+G7+H7+I7+J7+K7 -> 188.9
A13: Tubarão | B13: =Bridge!U19 -> 632.04404 | C13: =Bridge!V19 -> -6.6803807 | D13: =Bridge!W19 -> 286.54894 | E13: =Bridge!X19 -> -177.47195 | F13: =Bridge!Y19 -> -8.7367984 | G13: =Bridge!Z19 -> -4.0925449 | H13: =Bridge!AA19 -> -34.290559 | I13: =Bridge!AB19 -> -5.7640204 | ... K13: =Bridge!AD19 -> -4.4371962 | L13: =SUM(B13:K13) -> 747.6924 | M13: =L6+L7 -> 936.81879 | N13: =L13-Bridge!AE24 -> 0
S14: =292+669 -> 961
A15: Pecém | B15: =B7 -> 100.26 | C15: =C7 -> 23.3 | D15: =D7 -> 209.35 | E15: =E7 -> -57.55 | F15: =F7 -> -56.15 | G15: =G7 -> 9.92 | H15: =H7 -> -7.6 | I15: =I7 -> -0.6 | ... L15: =L7 -> 188.9 | M15: =L10+L11 -> 1003.0402
A16: TUPER | B16: =B8 -> 38.4 | C16: =C8 -> 0.7 | D16: =D8 -> 11.2 | E16: =E8 -> -10.9 | F16: =F8 -> 0 | G16: =G8 -> 0 | H16: =H8 -> -0.5 | I16: =I8 -> 0 | ... L16: =L8 -> 51.2
A17: TEKNO | B17: =B9 -> 12.597163 | C17: =C9 -> 0.71980764 | D17: =D9 -> 0.72162239 | E17: =E9 -> 0.01658585 | F17: =F9 -> 0 | G17: =G9 -> 0.24651878 | H17: =H9 -> 0.50828804 | I17: =I9 -> 0 | ... L17: =L9 -> 15.021395
A18: Consolidado | M18: =179-160 -> 19
B19: =B4 -> FY26 Budget | C19: =C4 -> Vol & Mix | D19: =D4 -> Selling price | E19: =E4 -> Input price | F19: =F4 -> Usage Market driven | G19: =G4 -> Usage Operational Performance | H19: =H4 -> Fixed costs | I19: =I4 -> Logistic | ... L19: =L4 -> FY26 MRF7
O20: =
B21: =B6+B7+B8+B9 -> 783.30121 | C21: =C6+C7+C8+C9 -> 18.039427 | D21: =D6+D7+D8+D9 -> 507.82057 | E21: =E6+E7+E8+E9 -> -245.90536 | F21: =F6+F7+F8+F9 -> -64.886798 | G21: =G6+G7+G8+G9 -> 6.0739738 | H21: =H6+H7+H8+H9 -> -41.88227 | I21: =I6+I7+I8+I9 -> -6.3640204 | ... K21: =K6+K7+K8+K9 -> -3.6804253 | L21: e
L22: =SUM(B21:K21) -> 1003.0402
B23: Tubarão | F23: Pecem | J23: Eliminação | K23: ='[37]EBITDA (consolidada) NEW'!$O$18 -> 0.226387 | L23: =K23+L6 -> 748.14517 | O23: 292.19537
A24: Tubarão | B24: Budget | C24: MRF02 | E24: Pecém | F24: Budget | H24: MRF01
A25: SLAB export | B25: ='[38]Template - LEAN vs MRF anterior'!$AS$50+'[38]Template - LEAN vs MRF anterior'!$AS$51 -> 73.236045 | C25: ='[38]Template - LEAN vs MRF anterior'!$AU$50+'[38]Template - LEAN vs MRF anterior'!$AU$51 -> 82.716084 | E25: =A25 -> SLAB export | F25: =[39]MPR!$T$54+[39]MPR!$T$55 -> 201.00593 | H25: =[39]MPR!$U$54+[39]MPR!$U$55 -> 221.25159 | J25: =[40]MPR!$U$56 -> 176.55393
A26: Slab DM | B26: ='[38]Template - LEAN vs MRF anterior'!$AS$66 -> -1.6936683 | C26: ='[38]Template - LEAN vs MRF anterior'!$AU$66 -> -0.10691912 | E26: Slab DM | F26: =[39]MPR!$T$57 -> 170.07479 | H26: =[39]MPR!$U$57 -> 125.64035
A27: HRC Export | B27: ='[38]Template - LEAN vs MRF anterior'!$AS$52 -> -2.1378559 | C27: ='[38]Template - LEAN vs MRF anterior'!$AU$52 -> -19.002082 | D27: =SUM(C25:C30) -> 523.72739 | M27: 707
A28: DM | B28: ='[38]Template - LEAN vs MRF anterior'!$AS$83-B26 -> 249.87944 | C28: ='[38]Template - LEAN vs MRF anterior'!$AU$83-C26 -> 201.5901 | M28: 238
A29: Auto | B29: ='[38]Template - LEAN vs MRF anterior'!$AS$65+'[38]Template - LEAN vs MRF anterior'!$AS$56+'[38]Template - LEAN vs MRF anterior'!$AS$54 -> 273.19747 | C29: ='[38]Template - LEAN vs MRF anterior'!$AU$65+'[38]Template - LEAN vs MRF anterior'!$AU$56+'[38]Template - LEAN vs MRF anterior'!$AU$54 -> 270.86482
A30: Legal and non-steel and others | B30: ='[38]Template - LEAN vs MRF anterior'!$AS$92 -> -14.585889 | C30: ='[38]Template - LEAN vs MRF anterior'!$AU$92+'[38]Template - LEAN vs MRF anterior'!$AU$55 -> -12.334614 | F30: =[39]MPR!$T$60 -> 0.78270063 | H30: =[39]MPR!$U$60 -> 12.952659
B31: =SUM(B25:B30) -> 577.89554 | C31: =SUM(C25:C30) -> 523.72739 | F31: =SUM(F25:F30) -> 371.86342 | H31: =SUM(H25:H30) -> 359.8446
C32: ='[38]Template - LEAN vs MRF anterior'!$AU$96 -> 523.64876
A34: Tubarão
B35: =B4 -> FY26 Budget | C35: =C4 -> Vol & Mix | D35: =D4 -> Selling price | E35: =E4 -> Input price | F35: =F4 -> Usage Market driven | G35: =G4 -> Usage Operational Performance | H35: =H4 -> Fixed costs | I35: =I4 -> Logistic | ... L35: =L4 -> FY26 MRF7
A37: SLAB export | B37: =B25 -> 73.236045 | C37: =C6+C7 -> 16.619619 | D37: =D6+D7 -> 495.89894 | E37: =E6+E7 -> -235.02195 | F37: =F6+F7 -> -64.886798 | G37: =G6+G7 -> 5.8274551 | H37: =H6+H7 -> -41.890559 | I37: =I6+I7 -> -6.3640204 | J37: =J6+J7 -> 48.042859 | K37: =K6+K7 -> -13.710809 | L37: =C25 -> 82.716084
A38: Slab DM | B38: =B26 -> -1.6936683 | L38: =C26 -> -0.10691912
A39: HRC Export | B39: =B27 -> -2.1378559 | L39: =C27 -> -19.002082
A40: DM | B40: =B28 -> 249.87944 | L40: =C28 -> 201.5901
A41: Auto | B41: =B29 -> 273.19747 | L41: =C29 -> 270.86482
A42: Legal and non-steel | B42: =B30 -> -14.585889 | L42: =C30 -> -12.334614
B45: =B35 -> FY26 Budget | C45: =C35 -> Vol & Mix | D45: =D35 -> Selling price | E45: =E35 -> Input price | F45: =F35 -> Usage Market driven | G45: =G35 -> Usage Operational Performance | H45: =H35 -> Fixed costs | I45: =I35 -> Logistic | ... L45: =L35 -> FY26 MRF7
A47: SLAB export | B47: =B25+F25 -> 274.24198 | C47: =C6+C7 -> 16.619619 | D47: =D6+D7 -> 495.89894 | E47: =E6+E7 -> -235.02195 | F47: =F6+F7 -> -64.886798 | G47: =G6+G7 -> 5.8274551 | H47: =H6+H7 -> -41.890559 | I47: =I6+I7 -> -6.3640204 | J47: =J6+J7 -> 48.042859 | K47: =K6+K7 -> -13.710809 | L47: =C25+H25 -> 303.96767
A48: Slab DM | B48: =B26+F26 -> 168.38112 | L48: =C26+H26 -> 125.53343
A49: HRC Export | B49: =B27+F27 -> -2.1378559 | L49: =C27+H27 -> -19.002082
A50: DM | B50: =B28+F28 -> 249.87944 | L50: =C28+H28 -> 201.5901
A51: Auto | B51: =B29+F29 -> 273.19747 | L51: =C29+H29 -> 270.86482
A52: Legal and non-steel | B52: =B30+F30 -> -13.803188 | L52: =C30+H30 -> 0.61804477
B56: =SUM(B47:B55) -> 949.75896
L57: =SUM(L47:L56) -> 883.57199
B61: =B45 -> FY26 Budget | C61: =C45 -> Vol & Mix | D61: =D45 -> Selling price | E61: =E45 -> Input price | F61: =F45 -> Usage Market driven | H61: =H45 -> Fixed costs | I61: =I45 -> Logistic | J61: =J45 -> Exchange rate | K61: =K45 -> SV/Others | L61: =L45 -> FY26 MRF7
A63: SLAB export | B63: =B47 -> 274.24198 | L63: =L47 -> 303.96767 | M63: =L63-B63 -> 29.725693
A64: Slab DM | B64: =B48 -> 168.38112 | L64: =L48 -> 125.53343 | M64: =L64-B64 -> -42.847685
A65: HRC Export | B65: =B49 -> -2.1378559 | L65: =L49 -> -19.002082 | M65: =L65-B65 -> -16.864226
A66: DM | B66: =B50 -> 249.87944 | L66: =L50 -> 201.5901 | M66: =L66-B66 -> -48.289336
A67: Auto | B67: =B51 -> 273.19747 | L67: =L51 -> 270.86482 | M67: =L67-B67 -> -2.33265
A68: Legal and non-steel | B68: =B52 -> -13.803188 | L68: =L52 -> 0.61804477 | M68: =L68-B68 -> 14.421233

Sheet Bridge Consolidade modelo n (2)
A3: Consolidado
B4: ='[41]Bridge combinada'!B17 -> FY25 Budget | C4: US tariff impact | D4: Mix DM | E4: Price DM | F4: Forex Industry | G4: Forex others (Auto/cost/Inventories) | H4: Input price | I4: Cost reduction | J4: Invest-ES | K4: Extemporaneous effects | N4: Others | O4: ='Bridge combinada'!L4 -> FY26 MRF7
B6: ='[41]Bridge combinada'!B19 -> 926.76655 | C6: =-'[42]Summary Dec16th'!$S$5 -> -251.43221 | D6: =('[43]Box (resumo SAIDA)'!$F$13-'[43]Box (resumo SAIDA)'!$F$7)*'[43]Box (resumo SAIDA)'!$E$13/1000-3 -> -12.209934 | E6: ='Box (resumo SAIDA)'!N15 -> 52.02599 | F6: =Box!AM5 -> 104.08293 | G6: =Box!AM6+Box!AM7+T26+T27+T28 -> -70.898143 | I6: =I29+I33+I45 -> 80.4 | J6: =Box!AU5 -> -4.896564 | K6: =Box!#REF!+Box!AU7+Box!#REF!+Box!#REF!+Box!#REF!+Box!#REF!+T30 -> #REF! | N6: =P7-SUM(B6:M6) -> #REF! | O6: e | P6: =SUM(B6:N6) -> #REF!
G7: Incluir de Pecem e forex nos estoques | P7: =SUM('Bridge combinada'!B21:K21) -> 1003.0402
P8: Bridge | Q8: Diferença
A9: ='Bridge combinada'!C4 -> Vol & Mix | C9: =C6 -> -251.43221 | D9: =D6 -> -12.209934 | E9: =E6 -> 52.02599 | O9: =SUM(C9:N9) -> -211.61615 | P9: ='Bridge combinada'!C21+'Bridge combinada'!D21 -> 525.85999 | Q9: =O9-P9 -> -737.47614
A10: ='Bridge combinada'!D4 -> Selling price
A11: ='Bridge combinada'!E4 -> Input price | I11: =I33 -> 9 | O11: =SUM(C11:N11) -> 9 | P11: ='Bridge combinada'!E21 -> -245.90536 | Q11: =O11-P11 -> 254.90536
A12: ='Bridge combinada'!F4 -> Usage Market driven | O12: =SUM(C12:N12) -> 0 | P12: ='Bridge combinada'!E21 -> -245.90536 | Q12: =O12-P12 -> 245.90536
A13: ='Bridge combinada'!G4 -> Usage Operational Performance | I13: =I37+I41 -> 36 | O13: =SUM(C13:N13) -> 36 | P13: ='Bridge combinada'!F21 -> -64.886798 | Q13: =O13-P13 -> 100.8868
A14: ='Bridge combinada'!H4 -> Fixed costs | I14: =I21 -> 33.7 | O14: =SUM(C14:N14) -> 33.7 | P14: ='Bridge combinada'!H21 -> -41.88227 | Q14: =O14-P14 -> 75.58227
A15: ='Bridge combinada'!I4 -> Logistic | I15: =I25 -> 1.7 | O15: =SUM(C15:N15) -> 1.7 | P15: ='Bridge combinada'!I21 -> -6.3640204 | Q15: =O15-P15 -> 8.0640204
A16: ='Bridge combinada'!J4 -> Exchange rate | F16: =F6 -> 104.08293 | G16: =Box!AM6+Box!AM7+'Box combinado'!X7 -> -56.040071 | O16: =SUM(C16:N16) -> 48.042859 | P16: ='Bridge combinada'!J21 -> 50.523885 | Q16: =O16-P16 -> -2.481026
A17: ='Bridge combinada'!K4 -> SV/Others | G17: =T26+T27 -> -36.388072 | K17: =K6 -> #REF! | L17: =Box!#REF! -> #REF! | N17: =Box!AU8-11-G17 -> 25.697646 | O17: =SUM(C17:N17) -> #REF! | P17: ='Bridge combinada'!K21 -> -3.6804253 | Q17: =O17-P17 -> #REF!
B18: =SUM(B9:B17) -> 0 | C18: =SUM(C9:C17) -> -251.43221 | D18: =SUM(D9:D17) -> -12.209934 | E18: =SUM(E9:E17) -> 52.02599 | F18: =SUM(F9:F17) -> 104.08293 | G18: =SUM(G9:G17) -> -92.428143 | I18: =SUM(I9:I17) -> 80.4 | K18: =SUM(K9:K17) -> #REF! | L18: =SUM(L9:L17) -> #REF! | N18: =SUM(N9:N17) -> 25.697646
C19: =C6-C18 -> 0 | D19: =D6-D18 -> 0 | E19: =E6-E18 -> 0 | F19: =F6-F18 -> 0 | G19: =G6-G18 -> 21.53 | I19: =I6-I18 -> 0 | K19: =K6-K18 -> #REF! | L19: =L6-L18 -> #REF! | N19: =N6-N18 -> #REF!
I20: =190-110 -> 80 | J20: AJUSTADO 2 COM REVISAO DE PAULA
G21: Fixed cost | I21: =I22+I23 -> 33.7
G22: TVC | I22: =27-15 -> 12
G23: Pecém | I23: =35-13.3 -> 21.7 | K23: =164-110 -> 54
S24: IP | T24: ='Bridge combinada'!E6+'Bridge combinada'!E7-I33 -> -244.02195
G25: Logistic | I25: =I26+I27 -> 1.7 | S25: Forex nos estoques
G26: TVC | I26: 1.7 | S26: TVC | T26: =Box!AU10 -> -20.388072
G27: Pecém | I27: 0 | S27: Pecém | T27: -16
S28: Forex Pecém | T28: -1
G29: TOTAL FC | I29: =I25+I21 -> 35.4 | S29: Reintegra Pecem | T29: 10
G30: Check | I30: =62-28+2 -> 36 | S30: Legal contingency pecem | T30: -2
I31: =I29-I30 -> -0.6
G33: Procurement | I33: =I34+I35 -> 9
G34: TVC | I34: =29.7-18-I26 -> 10 | J34: REBATE VALE
G35: Pecém | I35: -1
G37: Gap & Sinergy | I37: =SUM(I38:I39) -> 7
G38: TVC | I38: =49-49 -> 0 | S38: =43-21 -> 22
G39: Pecém | I39: =21-14 -> 7
A41: Pecém | G41: Usage | I41: =I42+I43 -> 29
G42: TVC | I42: 18
A43: =4+2 -> 6 | G43: Pecém | I43: 11
G45: Total CV | I45: =I46+I47 -> 36
G46: Usage | I46: =I41 -> 29
G47: GAP | I47: =I37 -> 7
I48: =SUM(I22:I23,I26:I27,I34:I35,I38:I39,I42:I43) -> 80.4
A50: Tubarão
B51: ='[41]Bridge combinada'!B64 -> 249.87944 | C51: US tariff impact | D51: Mix DM | E51: Price DM | F51: Forex Industry | G51: Forex others (Auto/cost/Inventories) | H51: Input price | I51: Cost reduction | J51: Invest-ES | K51: Extemporaneous effects | L51: Tuper acquisition | M51: Value creation | N51: SV/Others | O51: ='Bridge combinada'!L53 -> 0
S52: ='Bridge Consolidade modelo n (2)'!N53+AH6+S6+2 -> 280.59237
B53: ='Bridge combinada'!B13 -> 632.04404 | C53: ='[44]Resumo- Analise movimentaçã Com'!$C$7 -> -131.27924 | D53: =D6 -> -12.209934 | E53: =E6 -> 52.02599 | F53: =Box!AM5 -> 104.08293 | G53: =Box!AM6+Box!AM7+T26 -> -53.898143 | H53: =Box!U21-Box!U16 -> -157.61885 | I53: =I22+I26+I34+I38+I42-1 -> 40.7 | J53: =Box!AU5 -> -4.896564 | K53: =Box!AU6 -> 0.14979323 | N53: =N54-SUM(B53:M53) -> 278.59237 | O53: e | U53: Diferença Comercial
N54: =Cálculo!C13 -> 747.6924 | U54: Placas | V54: ='Box (resumo SAIDA)'!G6+'Box (resumo SAIDA)'!G5+'Box (resumo SAIDA)'!N5+'Box (resumo SAIDA)'!N6 -> 176.4307
P55: Bridge | Q55: Diferença | V55: =C56 -> -130.6967
A56: =A9 -> Vol & Mix | C56: =SUM('[44]Resumo- Analise movimentaçã Com'!$C$4:$C$5) -> -130.6967 | D56: =D53 -> -12.209934 | E56: =E53 -> 52.02599 | N56: =-28+2 -> -26 | O56: =SUM(C56:N57) -> -116.88064 | P56: ='Bridge combinada'!C13+'Bridge combinada'!D13 -> 279.86856 | Q56: =O56-P56 -> -396.74921 | V56: =V54-V55 -> 307.1274
A57: =A10 -> Selling price | U57: MRF1 | V57: ='[31]Resumo- Analise movimentação'!$C$12+'[31]Resumo- Analise movimentação'!$C$15 -> -12
A58: =A11 -> Input price | H58: =H53 -> -157.61885 | I58: =Box!U16 -> -19.853098 | O58: =SUM(C58:N58) -> -177.47195 | P58: ='Bridge combinada'!E13 -> -177.47195 | Q58: =O58-P58 -> 0 | V58: =V56-V57 -> 319.1274
A59: =A12 -> Usage Market driven | C59: ='[44]Resumo- Analise movimentaçã Com'!$C$6 -> -0.58253923 | N59: =Box!AD6 -> -6.5367984 | O59: =SUM(C59:N59) -> -7.1193377 | P59: ='Bridge combinada'!F13 -> -8.7367984 | Q59: =O59-P59 -> 1.6174608 | U59: Ajuste Produção | V59: =-9-0.5 -> -9.5
A60: =A13 -> Usage Operational Performance | I60: =I42+I38 -> 18 | N60: =Box!AA11-I60 -> -22.092545 | O60: =SUM(C60:N60) -> -4.0925449 | P60: ='Bridge combinada'!G13 -> -4.0925449 | Q60: =O60-P60 -> 0 | V60: =V58-V59 -> 328.6274
A61: =A14 -> Fixed costs | I61: =I22 -> 12 | N61: =Box!AX17-I61 -> -46.354236 | O61: =SUM(C61:N61) -> -34.354236 | P61: ='Bridge combinada'!H13 -> -34.290559 | Q61: =O61-P61 -> -0.063677001 | U61: Preço HRC | V61: ='Box (resumo SAIDA)'!N8 -> 16.758587
A62: =A15 -> Logistic | I62: =I26 -> 1.7 | N62: =Box!AP7-I62 -> -7.7 | O62: =SUM(C62:N62) -> -6 | P62: ='Bridge combinada'!I13 -> -5.7640204 | Q62: =O62-P62 -> -0.23597964 | V62: ='Box (resumo SAIDA)'!B29 -> -10.25552
A63: =A16 -> Exchange rate | F63: =Box!AM5 -> 104.08293 | G63: =Box!AM6+Box!AM7 -> -33.510071 | O63: =SUM(C63:N63) -> 70.572859 | P63: ='Bridge combinada'!J13 -> 70.572859 | Q63: =O63-P63 -> 6.9633188e-13 | V63: ='Box (resumo SAIDA)'!#REF! -> #REF!
A64: =A17 -> SV/Others | G64: =T26 -> -20.388072 | J64: =Box!AU5 -> -4.896564 | K64: =Box!AU6 -> 0.14979323 | N64: =Box!AU11 -> 23.301765 | O64: =SUM(C64:N64) -> -1.8330775 | P64: ='Bridge combinada'!K6 -> -4.2108092 | Q64: =O64-P64 -> 2.3777317 | U64: Ajuste RMB | V64: 4
B65: =SUM(B56:B64) -> 0 | C65: =SUM(C56:C64) -> -131.27924 | D65: =SUM(D56:D64) -> -12.209934 | E65: =SUM(E56:E64) -> 52.02599 | F65: =SUM(F56:F64) -> 104.08293 | G65: =SUM(G56:G64) -> -53.898143 | H65: =SUM(H56:H64) -> -157.61885 | I65: =SUM(I56:I64) -> 11.846902 | ... N65: =SUM(N56:N64) -> -85.381814 | P65: =SUM(P58:P64) -> -163.99382 | Q65: =B53+SUM(P56:P64) -> 747.91879
C66: =C53-C65 -> 0 | D66: =D53-D65 -> 0 | E66: =E53-E65 -> 0 | F66: =F53-F65 -> 0 | G66: =G53-G65 -> 0 | H66: =H53-H65 -> 0 | I66: =I53-I65 -> 28.853098 | J66: =J53-J65 -> 0 | ... N66: =N53-N65 -> 363.97419 | P66: =SUM(P56:P64) -> 115.87474 | Q66: =Q65-Cálculo!C13 -> 0.226387
P67: =SUM('Bridge combinada'!C6:K6) -> 115.87474 | V67: =V57+V59+V61+V62+V63+V64 -> #REF!
P68: =P66-P67 -> 0 | V68: =V67-N56 -> #REF!
J70: =N65+H65+2 -> -241.00066
A72: Pecém
B73: ='[41]Bridge combinada'!B86 -> 0 | C73: US tariff impact | D73: Mix DM | E73: Price DM | F73: Forex Industry | G73: Forex others (Auto/cost/Inventories) | H73: Input price | I73: Cost reduction | J73: Invest-ES | K73: Extemporaneous effects | L73: Tuper acquisition | M73: Value creation | N73: SV/Others | O73: ='Bridge combinada'!L75 -> 0
B75: ='Bridge combinada'!B7 -> 100.26 | C75: ='[44]Resumo- Analise movimentaçã Com'!$I$7 -> -156.8 | D75: 0 | E75: 0 | F75: 0 | G75: =T28+T27 -> -17 | H75: ='Bridge combinada'!E7-I35 -> -56.55 | I75: =I43+I39+I35+I27+I23 -> 38.7 | J75: 0 | K75: =T30 -> -2 | L75: 0 | M75: -1 | N75: =N76-SUM(B75:M75) -> 283.29 | O75: e
I76: 31 | J76: 2 | N76: ='Bridge combinada'!L7 -> 188.9
I77: =I76-I75 -> -7.7 | J77: -3 | P77: Bridge | Q77: Diferença
A78: =A56 -> Vol & Mix | C78: =SUM('[44]Resumo- Analise movimentaçã Com'!$I$4:$I$5) -> -140.3 | N78: 0 | O78: =SUM(C78:N78) -> -140.3 | P78: ='Bridge combinada'!C7+'Bridge combinada'!D7 -> 232.65 | Q78: =O78-P78 -> -372.95 | S78: Preços MRF1 | T78: =19-12 -> 7
A79: =A57 -> Selling price | S79: Volume | T79: -6
A80: =A58 -> Input price | H80: ='Bridge combinada'!E7-I80 -> -56.55 | I80: =I35 -> -1 | O80: =SUM(C80:N80) -> -57.55 | P80: ='Bridge combinada'!E7 -> -57.55 | Q80: =O80-P80 -> 0
A81: =A59 -> Usage Market driven | C81: -11 | O81: =SUM(C81:N81) -> -11 | P81: ='Bridge combinada'!F7 -> -56.15 | Q81: =O81-P81 -> 45.15
A82: =A60 -> Usage Operational Performance | I82: =I43+I39 -> 18 | N82: ='Bridge combinada'!G15-I82 -> -8.08 | O82: =SUM(C82:N82) -> 9.92 | P82: ='Bridge combinada'!G7 -> 9.92 | Q82: =O82-P82 -> 0
A83: =A61 -> Fixed costs | I83: =I23 -> 21.7 | N83: ='Bridge combinada'!H15-I83 -> -29.3 | O83: =SUM(C83:N83) -> -7.6 | P83: ='Bridge combinada'!H7 -> -7.6 | Q83: =O83-P83 -> 0
A84: =A62 -> Logistic | O84: =SUM(C84:N84) -> 0 | P84: ='Bridge combinada'!I7 -> -0.6 | Q84: =O84-P84 -> 0.6
A85: =A63 -> Exchange rate | G85: ='Bridge combinada'!J7 -> -22.53 | O85: =SUM(C85:N85) -> -22.53 | P85: ='Bridge combinada'!J7 -> -22.53 | Q85: =O85-P85 -> 0
A86: =A64 -> SV/Others | G86: =T27 -> -16 | N86: ='Bridge combinada'!K7-G86 -> 6.5 | O86: =SUM(C86:N86) -> -9.5 | P86: ='Bridge combinada'!K7 -> -9.5 | Q86: =O86-P86 -> 0
B87: =SUM(B78:B86) -> 0 | C87: =SUM(C78:C86) -> -151.3 | D87: =SUM(D78:D86) -> 0 | E87: =SUM(E78:E86) -> 0 | F87: =SUM(F78:F86) -> 0 | G87: =SUM(G78:G86) -> -38.53 | H87: =SUM(H78:H86) -> -56.55 | I87: =SUM(I78:I86) -> 38.7 | ... L87: =SUM(L78:L86) -> 0 | N87: =SUM(N78:N86) -> -30.88 | P87: =SUM(P78:P86) -> 88.64 | Q87: =B75+SUM(P78:P86) -> 188.9
C88: =C75-C87 -> -5.5 | D88: =D75-D87 -> 0 | E88: =E75-E87 -> 0 | F88: =F75-F87 -> 0 | G88: =G75-G87 -> 21.53 | H88: =H75-H87 -> 0 | I88: =I75-I87 -> 0 | J88: =J75-J87 -> 0 | ... L88: =L75-L87 -> 0 | N88: =N75-N87 -> 314.17 | P88: =SUM('Bridge combinada'!C7:K7) -> 88.64 | Q88: =Q87-Cálculo!C36 -> -416395.81
P89: =SUM('Bridge combinada'!C30:K30) -> 1.4007454

Sheet Bridge combinada (2)
B4: =Bridge!U17 -> FY26 Budget | C4: =Bridge!V17 -> Vol & Mix | D4: =Bridge!W17 -> Selling price | E4: =Bridge!X17 -> Input price | F4: =Bridge!Y17 -> Usage Market driven | G4: =Bridge!AA17 -> Fixed costs | H4: =Bridge!AB17 -> Logistic | I4: =Bridge!AC17 -> Exchange rate | J4: =Bridge!#REF! -> #REF! | K4: =Bridge!AD17 -> SV/Others | L4: =Bridge!AE17 -> FY26 MRF7
B6: =B11 -> 632.04404 | C6: =C11 -> -6.6803807 | D6: =D11 -> 286.54894 | E6: =E11 -> -177.47195 | F6: =F11 -> -8.7367984 | G6: =G11 -> -34.290559 | H6: =H11 -> -5.7640204 | I6: =I11 -> 70.572859 | ... K6: =K11 -> -4.4371962 | L6: =SUM(B6:K6) -> #REF!
B7: =B13 -> 245 | C7: =C13 -> 0 | D7: =D13 -> 0 | E7: =E13 -> 0 | F7: =F13 -> 0 | G7: =G13 -> 0 | H7: =H13 -> 0 | I7: =I13 -> 0 | ... K7: =K13 -> 172 | L7: =SUM(B7:K7) -> 417
A11: Tubarão | B11: =Bridge!U19 -> 632.04404 | C11: =Bridge!V19 -> -6.6803807 | D11: =Bridge!W19 -> 286.54894 | E11: =Bridge!X19 -> -177.47195 | F11: =Bridge!Y19 -> -8.7367984 | G11: =Bridge!AA19 -> -34.290559 | H11: =Bridge!AB19 -> -5.7640204 | I11: =Bridge!AC19 -> 70.572859 | J11: =Bridge!#REF! -> #REF! | K11: =Bridge!AD19 -> -4.4371962 | L11: =SUM(B11:K11) -> #REF!
A13: Pecém | B13: 245 | K13: 172 | L13: =SUM(B13:K13) -> 417
L14: 417
L15: =L14-B13 -> 172
A22: Tubarão | B22: Budget
A24: SLAB export | B24: ='[38]Template - LEAN vs MRF anterior'!$AO$50+'[38]Template - LEAN vs MRF anterior'!$AO$51 -> 13.440802 | C24: =L24 -> 12.542049 | L24: ='[38]Template - LEAN vs MRF anterior'!$AQ$50+'[38]Template - LEAN vs MRF anterior'!$AQ$51 -> 12.542049
A25: Slab DM | B25: ='[38]Template - LEAN vs MRF anterior'!$AO$66 -> 0.37359881 | C25: ='[38]Template - LEAN vs MRF anterior'!$AQ$66 -> -0.25064842
A26: HRC Export | B26: ='[38]Template - LEAN vs MRF anterior'!$AO$52 -> -5.3790523 | C26: =L26 -> -5.8421381 | L26: ='[38]Template - LEAN vs MRF anterior'!$AQ$52 -> -5.8421381
A27: DM | B27: ='[38]Template - LEAN vs MRF anterior'!$AO$83-B25 -> 59.108871 | C27: =L27-C25 -> 40.366197 | L27: ='[38]Template - LEAN vs MRF anterior'!$AQ$83 -> 40.115549
A28: Auto | B28: ='[38]Template - LEAN vs MRF anterior'!$AO$65+'[38]Template - LEAN vs MRF anterior'!$AO$56+'[38]Template - LEAN vs MRF anterior'!$AO$54 -> 67.194562 | C28: =L28 -> 68.785577 | L28: ='[38]Template - LEAN vs MRF anterior'!$AQ$65+'[38]Template - LEAN vs MRF anterior'!$AQ$56+'[38]Template - LEAN vs MRF anterior'!$AQ$54 -> 68.785577
A29: Legal and non-steel | B29: ='[38]Template - LEAN vs MRF anterior'!$AO$92 -> -0.67864418 | C29: =L29 -> -1.7551497 | L29: ='[38]Template - LEAN vs MRF anterior'!$AQ$92 -> -1.7551497
B30: =SUM(B24:B29) -> 134.06014 | C30: =L30 -> 113.84589 | L30: =SUM(L24:L29) -> 113.84589
B34: =B4 -> FY26 Budget | C34: =C4 -> Vol & Mix | D34: =D4 -> Selling price | E34: =E4 -> Input price | F34: =F4 -> Usage Market driven | G34: =G4 -> Fixed costs | H34: =H4 -> Logistic | I34: =I4 -> Exchange rate | ... L34: =L4 -> FY26 MRF7
B36: =B6+B7 -> 877.04404 | C36: =C6+C7 -> -6.6803807 | D36: =D6+D7 -> 286.54894 | E36: =E6+E7 -> -177.47195 | F36: =F6+F7 -> -8.7367984 | G36: =G6+G7 -> -34.290559 | H36: =H6+H7 -> -5.7640204 | I36: =I6+I7 -> 70.572859 | ... K36: =K6+K7 -> 167.5628 | L36: =SUM(B36:K36) -> #REF!

Sheet Box combinado (modleo novo)
K1: =
B3: ='Bridge Consolidade modelo n (2)'!C4 -> US tariff impact | E3: ='Bridge Consolidade modelo n (2)'!D4 -> Mix DM | H3: ='Bridge Consolidade modelo n (2)'!E4 -> Price DM | K3: ='Bridge Consolidade modelo n (2)'!F4 -> Forex Industry | N3: Forex others | R3: ='Bridge Consolidade modelo n (2)'!H4 -> Input price | U3: ='Bridge Consolidade modelo n (2)'!I4 -> Cost reduction | X3: ='Bridge Consolidade modelo n (2)'!J4 -> Invest-ES | AA3: ='Bridge Consolidade modelo n (2)'!K4 -> Extemporaneous effects | AD3: ='Bridge Consolidade modelo n (2)'!L4 -> 0 | AG3: ='Bridge Consolidade modelo n (2)'!M4 -> 0 | AJ3: ='Bridge Consolidade modelo n (2)'!N4 -> Others
B5: Combined | C5: MUSD | E5: Combined | F5: MUSD | H5: Combined | I5: MUSD | K5: Combined | L5: MUSD | N5: Combined | O5: MUSD | R5: Combined | S5: MUSD | U5: Combined | V5: MUSD | X5: Combined | Y5: MUSD | AA5: Combined | AB5: MUSD | AD5: Combined | AE5: MUSD | AG5: Combined | AH5: MUSD | AJ5: Combined | AK5: MUSD
B6: FC LATAM | C6: =-'[42]Summary Dec16th'!$S$29 -> -95.203045 | E6: FC LATAM | F6: ='Bridge Consolidade modelo n (2)'!D53 -> -12.209934 | H6: FC LATAM | I6: ='Bridge Consolidade modelo n (2)'!E53 -> 52.02599 | K6: FC LATAM | L6: ='Bridge Consolidade modelo n (2)'!F53 -> 104.08293 | N6: FC LATAM | O6: ='Bridge Consolidade modelo n (2)'!G53 -> -53.898143 | R6: FC LATAM | S6: ='Bridge Consolidade modelo n (2)'!H53 -> -157.61885 | U6: FC LATAM | V6: =[45]Planilha1!$G$17 -> 41.7 | X6: FC LATAM | Y6: ='Bridge Consolidade modelo n (2)'!J53 -> -4.896564 | AA6: FC LATAM | AB6: =Box!#REF!+Box!AU7+Box!#REF!+Box!#REF!+Box!#REF!+Box!#REF! -> #REF! | AD6: FC LATAM | AE6: ='Bridge Consolidade modelo n (2)'!L53 -> 0 | AG6: FC LATAM | AH6: ='Bridge Consolidade modelo n (2)'!M53 -> 0 | AJ6: FC LATAM | AK6: ='Bridge combinada'!L6-'Bridge combinada'!B6-SUM(C6,F6,I6,L6,O6,V6,Y6,AB6)+1 -> #REF! | AM6: ='Bridge combinada'!B6 -> 632.04404 | AN6: =F6+I6+L6+O6+V6+Y6+AB6+AM6+C6+AK6 -> #REF! | AO6: =AP6-AN6 -> #REF! | AP6: ='Bridge combinada'!L6+1 -> 748.91879
B7: AM Pecém | C7: =-'[42]Summary Dec16th'!$S$53 -> -156.22916 | E7: AM Pecém | F7: ='Bridge Consolidade modelo n (2)'!D75 -> 0 | H7: AM Pecém | I7: ='Bridge Consolidade modelo n (2)'!E75 -> 0 | K7: AM Pecém | L7: ='Bridge Consolidade modelo n (2)'!F75 -> 0 | N7: AM Pecém | O7: ='Bridge Consolidade modelo n (2)'!G75 -> -17 | R7: AM Pecém | S7: ='Bridge Consolidade modelo n (2)'!H75 -> -56.55 | U7: AM Pecém | V7: =[45]Planilha1!$G$18 -> 38.7 | X7: AM Pecém | Y7: ='Bridge Consolidade modelo n (2)'!J75 -> 0 | AA7: AM Pecém | AB7: ='Bridge Consolidade modelo n (2)'!T30 -> -2 | AD7: AM Pecém | AE7: ='Bridge Consolidade modelo n (2)'!L75 -> 0 | AG7: AM Pecém | AH7: ='Bridge Consolidade modelo n (2)'!M75 -> -1 | AJ7: AM Pecém | AK7: ='Bridge combinada'!L7-'Bridge combinada'!B7-SUM(C7,F7,I7,L7,O7,V7,Y7,AB7) -> 225.16916 | AM7: ='Bridge combinada'!B7 -> 100.26 | AN7: =F7+I7+L7+O7+V7+Y7+AB7+AM7+C7+AK7 -> 188.9 | AO7: =AP7-AN7 -> 0 | AP7: ='Bridge combinada'!L7 -> 188.9
B8: Total | C8: =C6+C7 -> -251.43221 | E8: Total | F8: =F6+F7 -> -12.209934 | H8: Total | I8: =I6+I7 -> 52.02599 | K8: Total | L8: =L6+L7 -> 104.08293 | N8: Total | O8: =O6+O7 -> -70.898143 | R8: Total | S8: =S6+S7 -> -214.16885 | U8: Total | V8: =V6+V7 -> 80.4 | X8: Total | Y8: =Y6+Y7 -> -4.896564 | AA8: Total | AB8: =AB6+AB7 -> #REF! | AD8: Total | AE8: =AE6+AE7 -> 0 | AG8: Total | AH8: =AH6+AH7 -> -1 | AJ8: Total | AK8: =AK6+AK7+0.3 -> #REF!
S17: =

Sheet Invest-ES
D3: Jan | E3: Fev | F3: Mar | G3: Abr | H3: Mai | I3: Jun | J3: Jul | K3: Ago | L3: Set | M3: Out | N3: Nov | O3: Dez | P3: 2026
B4: Invest | C4: USD | D4: 10830382 | E4: 11069998 | F4: 11551259 | G4: 11041345 | H4: 11167776 | I4: 11280219 | J4: 11395984 | K4: 12433932 | L4: 11020623 | M4: 12274792 | N4: 12233213 | O4: 8485185.2 | P4: 1.3478471e+08 | Q4: Budget
B5: Invest | C5: USD | D5: 11241751 | E5: 11907969 | F5: 11474361 | G5: 10961687 | H5: 12161513 | I5: 11429835 | J5: 11508923 | K5: 12054489 | L5: 11423262 | M5: 11383292 | N5: 11257534 | O5: 7367240.4 | P5: 1.3417186e+08 | Q5: MRF1
B6: Invest | C6: USD | D6: 11646875 | E6: 10128422 | F6: 11789618 | G6: 13314066 | H6: 12983219 | I6: 11860108 | J6: 11916512 | K6: 12684950 | L6: 11516886 | M6: 12291288 | N6: 11363566 | O6: 2880006.2 | P6: 1.3417186e+08 | Q6: MRF2
B7: Invest | C7: USD | D7: =D6 -> 11646875 | E7: =([46]Análise!$G$27+[46]Análise!$G$28)*1000000 -> 10443842 | F7: 11773783 | G7: 12812922 | H7: 12815114 | I7: 12034402 | J7: 12716588 | K7: 12608486 | L7: 11735483 | M7: 12494652 | N7: 12591731 | O7: 965661.32 | P7: =SUM(D7:O7) -> 1.3463954e+08 | Q7: MRF3
B8: Invest | C8: USD | D8: =D7 -> 11646875 | E8: =E7 -> 10443842 | F8: =([47]Análise!$G$27+[47]Análise!$G$28)*1000000 -> 11384596 | G8: 12675236 | H8: 13850723 | I8: 12530993 | J8: 12325263 | K8: 13723009 | L8: 12368118 | M8: 13311752 | N8: 9963171.8 | O8: 0 | P8: =SUM(D8:O8) -> 1.3422358e+08 | Q8: MRF4
B9: Invest | C9: USD | D9: =D8 -> 11646875 | E9: =E8 -> 10443842 | F9: =F8 -> 11384596 | G9: =([48]Análise!$G$27+[48]Análise!$G$28)*1000000 -> 11824559 | H9: ='[49]AMB_ICMS ES'!H187 -> 12629419 | I9: ='[49]AMB_ICMS ES'!I187 -> 14742585 | J9: ='[49]AMB_ICMS ES'!J187 -> 12324342 | K9: ='[49]AMB_ICMS ES'!K187 -> 14002044 | L9: ='[49]AMB_ICMS ES'!L187 -> 12869043 | M9: ='[49]AMB_ICMS ES'!M187 -> 13627622 | N9: ='[49]AMB_ICMS ES'!N187 -> 8737401.5 | O9: 552379.71 | P9: =SUM(D9:O9) -> 1.3478471e+08 | Q9: MRF5 | R9: =P9-P4 -> 0
B10: Invest | C10: USD | D10: =D9 -> 11646875 | E10: =E9 -> 10443842 | F10: =F9 -> 11384596 | G10: =G9 -> 11824559 | H10: =([50]Análise!$G$27+[50]Análise!$G$28)*1000000 -> 13968621 | I10: 11358156 | J10: 12325979 | K10: 15083263 | L10: 13273870 | M10: 13833511 | N10: 12971807 | P10: =SUM(D10:O10) -> 1.3811508e+08 | Q10: MRF6
B11: Invest | C11: USD | D11: =D10 -> 11646875 | E11: =E10 -> 10443842 | F11: =F10 -> 11384596 | G11: =G10 -> 11824559 | H11: =H10 -> 13968621 | I11: =([51]Análise!$G$27+[51]Análise!$G$28)*1000000 -> 12490587 | J11: ='[52]AMB_ICMS ES'!J199 -> -5942732.8 | K11: ='[52]AMB_ICMS ES'!K199 -> 14311341 | L11: ='[52]AMB_ICMS ES'!L199 -> 11707336 | M11: ='[52]AMB_ICMS ES'!M199 -> 14078424 | N11: ='[52]AMB_ICMS ES'!N199 -> 13470829 | O11: ='[52]AMB_ICMS ES'!O199 -> 10503867 | P11: =SUM(D11:O11) -> 1.2988814e+08 | Q11: MRF7
H21: =H9*5.25 -> 66304449 | I21: =I9*5.25 -> 77398574 | J21: =J9*5.25 -> 64702797 | K21: =K9*5.25 -> 73510731 | L21: =L9*5.25 -> 67562478 | M21: =M9*5.25 -> 71545014 | N21: =N9*5.25 -> 45871358 | O21: =O9*5.25 -> 2899993.5
D23: Q1 | E23: Q2 | F23: Q3 | G23: Q4 | H23: FY
C24: Budget | D24: =SUM(D4:F4)/1000000 -> 33.451639 | E24: =SUM(G4:I4)/1000000 -> 33.48934 | F24: =SUM(J4:L4)/1000000 -> 34.850539 | G24: =SUM(M4:O4)/1000000 -> 32.99319 | H24: =SUM(D24:G24) -> 134.78471
C25: MRF6 | D25: =SUM(D10:F10)/1000000 -> 33.475313 | E25: =SUM(G10:I10)/1000000 -> 37.151336 | F25: =SUM(J10:L10)/1000000 -> 40.683112 | G25: =SUM(M10:O10)/1000000 -> 26.805318 | H25: =SUM(D25:G25) -> 138.11508
C26: Dif. | D26: =D25-D24 -> 0.023674628 | E26: =E25-E24 -> 3.6619954 | F26: =F25-F24 -> 5.8325729 | G26: =G25-G24 -> -6.1878722 | H26: =SUM(D26:G26) -> 3.3303708

Sheet Bridge Book

Sheet Wanick
D3: vrs.$461
C4: 2020 MRF10 | D4: =Cálculo!$C$3 -> 632.04404 | F4: Source:
B5: Corporate Assumptions
C6: . Selling price reference | D6: =Footprint!$I$27 -> #REF!
C7: . Input price reference | D7: =Footprint!$I$34 -> -158.74421
D8: =D6+D7 -> #REF!
C9: Expected EBITDA | D9: =D4+D8 -> #REF!
B10: Footprint related
C11: . Volume | D11: =Footprint!$I$6 -> -413.839 | F11: $100/t
C12: . Usage Mkt/Footprint | D12: =Footprint!$I$12 -> -4.0925449
C13: . FC Mkt/Footprint | D13: =Box!#REF! -> #REF! | F13: Menores gastos em 2020 em função dos reflexos da Covid-19 (redução da produção, jornada, viagens, manutenções, acesso à planta, Covid...)
C14: . Reliability/Multiannual | D14: =Box!#REF!+Box!#REF! -> #REF!
C15: . Costs on sales | D15: =Footprint!$E$13 -> 1.006202 | F15: Logística variavel
C16: . Stock variation | D16: =Box!#REF!-1-1.7 -> #REF! | F16: Logistica
C17: =Box!#REF! -> #REF! | D17: =Box!#REF! -> #REF!
D18: =SUM(D11:D17) -> #REF!
C19: Footprint adjusted | D19: =D9+D18 -> #REF!
B20: Management actions
C21: . Calvert | D21: =Footprint!$I$5+Footprint!$I$29 -> #REF!
C22: . Vol & Mix - domestic | D22: =Footprint!$I$7+Footprint!$I$8 -> #REF!
C23: . Pricing | D23: =Footprint!$I$28 -> #REF!
C24: . RM negotiations | D24: ='Box Book'!G102 -> #REF! | F24: Other RM prices
C25: . Performance usage | D25: =Box!X17 -> -6.5367984
C26: . Fixed costs | D26: =Box!#REF! -> #REF! | F26: Sust reduction
C27: . Vale impacts | D27: =Box!#REF!+Box!#REF!+Box!#REF!+1 -> #REF! | F27: Incluir Vale impact
D28: =SUM(D21:D27) -> #REF!
C29: Business adjusted | D29: =D19+D28 -> #REF!
B30: Non-controllable/non-recurrent
C31: . FX effect | D31: =Cálculo!$C$4 -> 70.572859
C32: . Inflation | D32: =Footprint!$I$19+Footprint!$I$35 -> #VALUE! | F32: Fixed + Variable
C33: . Non controllable FC | D33: =Box!#REF! -> #REF! | F33: Corporate costs, environmental
C34: . Non recurrent | D34: =Box!#REF!+Box!#REF!+Box!#REF! -> #REF! | F34: VSS, AMC
C35: . Legal, compliance | D35: =Box!#REF! -> #REF! | F35: Legal contingencies
D36: =SUM(D31:D35) -> #VALUE!
C37: FY 2021 BUDGET | D37: =D29+D36 -> #REF!
C38: Outros a conciliar | D38: =D39-D37 -> #REF!
C39: FY 2021 BUDGET | D39: =Cálculo!$C$13 -> 747.6924

Sheet Box Book
D1: Trazer inflação
D2: Trazer costs on sales | L2: Origem ligado vazamento | AG2: -0.11 | AH2: =-12% -> -0.12
B3: Selling price reference | J3: Exports | L3: Origem não ligado ate 2023 vale a laminação | X3: North america slab market | AF3: Domestic
J4: Export price reference | K4: =SUM(G6:G7) -> #REF! | AI4: FY21 | AM4: FY20
B5: Price $/t | C5: FY20 | D5: FY21 | E5: Var | F5: kt | G5: MUSD | J5: Spread LATAM | K5: =R5 -> -0.92597757 | M5: Spread LATAM | N5: 43 | O5: 40 | P5: =O5-N5 -> -3 | Q5: =R25/1000 -> 308.65919 | R5: =P5*Q5/1000 -> -0.92597757 | X5: Slab BR FOB | Y5: =AVERAGE('Slab BR FOB'!B4:M4) -> 404.59237 | Z5: =AVERAGE('Slab BR FOB'!N4:Y4) -> 440.29453 | AA5: =Z5-Y5 -> 35.702158 | AB5: =AA5-M31 -> -6.0373659 | AF5: HRC reference | AG5: =E8*AG20/1000 -> #REF! | AI5: =D8 -> #REF! | AM5: =C8 -> 447.22366 | AR5: Commercial | AS5: =G9+G54+Box!#REF! -> #REF! | AT5: =Cálculo!P8/1000+Cálculo!C6+Cálculo!C7+Cálculo!F5 -> 364.64896 | AU5: =AS5-AT5 -> #REF! | AV5: ok | AW5: =SUM(Cálculo!V5:V7) -> -64.50351
B6: HRC China - Exports | C6: =G14 -> 459.24469 | D6: =G19 -> #REF! | E6: =D6-C6 -> #REF! | F6: =K16 -> 2211.6246 | G6: =E6*F6/1000 -> #REF! | J6: BQ worst mix (higher Asia) | K6: =-U28 -> -26.073294 | X6: Slab America MRF10 | Y6: $/t | Z6: Kt | AA6: $m | AF6: Tax (Imposto Imp.) | AG6: =E8*0.12*AG22/1000 -> #REF! | AI6: 32.5 | AJ6: Frete | AM6: 27 | AR6: Input price | AS6: =G72+G84+G102 -> #REF! | AT6: =Cálculo!C9 -> -177.47195 | AU6: =AS6-AT6 -> #REF!
B7: Spread Slab SEA | C7: =G26 -> -54.002848 | D7: =G31 -> #REF! | E7: =D7-C7 -> #REF! | F7: =G32 -> #REF! | G7: =E7*F7/1000 -> #REF! | J7: Mix calvert | K7: =U42 -> -25.228834 | X7: ='[53]Preço NRP'!D40 -> AM Dofasco 1 | Y7: 462.26447 | Z7: 201.01988 | AA7: =Y7*Z7 -> 92924.349 | AI7: =SUM(AI5:AI6) -> #REF! | AL7: =AI9*AM19/100 -> #REF! | AM7: =SUM(AM5:AM6) -> 474.22366
B8: HRC CIS - Domestic | C8: =G38 -> 447.22366 | D8: =G43 -> #REF! | E8: =D8-C8 -> #REF! | F8: =AG20 -> 3986.3767 | G8: =E8*F8/1000 -> #REF! | J8: Calvert price | M8: Spread China SEA | N8: =(-4+17-12-2)/4 -> -0.25 | O8: 10 | P8: =O8-N8 -> 10.25 | X8: ='[53]Preço NRP'!D41 -> AM Dofasco 2 | Y8: 449.98784 | Z8: 100.04775 | AA8: =Y8*Z8 -> 45020.271 | AC8: =SUM(Z7:Z8) -> 301.06763 | AF8: Premium | AG8: =AI9*AM19/100*AG22/1000*0.6 -> #REF! | AH8: a | AI8: =80+28-22 -> 86 | AJ8: Impostos e taxas | AL8: =AL7*AG22 -> #REF! | AM8: =AI8 -> 86
B9: Total | G9: =SUM(G6:G8) -> #REF! | J9: Slab Dofasco Extra | K9: =AC34 -> -1.2153561 | M9: Spread SEA BQ Placa | N9: =-(59+58+43+57)/4 -> -54.25 | O9: =-(60+55+55+55)/4 -> -56.25 | P9: =N9-O9 -> 2 | X9: ='[53]Preço NRP'!$D$46 -> CSI | Y9: 427.00215 | Z9: 101.72101 | AA9: =Y9*Z9 -> 43435.09 | AC9: =Z16 -> 109 | AF9: Aumento Auto | AG9: =AI33 -> #REF! | AI9: =SUM(AI7:AI8) -> #REF! | AM9: =SUM(AM7:AM8) -> 560.22366
J10: Lower slab NA | K10: =O16 -> -18.57443 | X10: ='[53]Preço NRP'!$D$49 -> NLMK USA | Y10: 460 | Z10: 50 | AA10: =Y10*Z10 -> 23000 | AC10: =AC9-AC8 -> -192.06763 | AH10: =E8*1.12*1.0567 -> #REF!
B11: For information only - HRC reference - Exports | J11: Total | K11: =SUM(K4:K10) -> #REF! | X11: $/t | Y11: =AA11/Z11 -> 451.37994 | Z11: =SUM(Z7:Z10) -> 452.78864 | AA11: =SUM(AA7:AA10) -> 204379.71 | AC11: =Y16-P33 -> 86 | AI11: =AI9*$AM$18/100 -> #REF!
I12: =SUM(H47:H47) -> 0 | J12: Bridge | K12: =Cálculo!P6/1000+Cálculo!I172/1000 -> 177.66705 | AC12: =AC10*AC11/1000+2 -> -14.517816 | AF12: Higher spreads | AG12: =AI42 -> 51.633547 | AI12: =AI9*AM17/100 -> #REF! | AM12: =AM9*AM18/100 -> 24.276358 | AN12: =AI12-AM12 -> #REF!
B13: =B6 -> HRC China - Exports | C13: Q120 | D13: Q220 | E13: Q320 | F13: Q420 | G13: FY20 | J13: Difference | K13: =K12-K11 -> #REF! | M13: =N33 -> 0.32615609 | N13: =S33 -> 0.55816435 | O13: =M13-N13 -> -0.23200826 | P13: {=K33-(M34:M35)/SUM(L34:L35)} -> -85.780463 | Q13: =O13*P13*Q36/1000 -> 18.647964 | AF13: Total | AG13: =SUM(AG5:AG12) -> #REF! | AI13: =AI12-AI11 -> #REF!
A14: Ajustar China | B14: Price $/t (1 quarter lag) | C14: ='[54]HRC Prices'!V52 -> 450.55385 | D14: ='[54]HRC Prices'!W52 -> 466.0625 | E14: ='[54]HRC Prices'!X52 -> 417.11864 | F14: ='[54]HRC Prices'!Y52 -> 489.22727 | G14: =G16/G15*1000 -> 459.24469 | J14: $/t | K14: =K13/K16*1000 -> #REF! | P14: 294.05725
B15: Vol. Kt | C15: ='[3]Shipments & Prices'!Q111 -> 684.06751 | D15: ='[3]Shipments & Prices'!R111 -> 880.72259 | E15: ='[3]Shipments & Prices'!S111 -> 709.80898 | F15: ='[3]Shipments & Prices'!T111 -> 995.31054 | G15: =SUM(C15:F15) -> 3269.9096 | X15: Slab America Budget | Y15: $/t | Z15: Kt | AA15: $m | AB15: $/t ∆ | AF15: Bridge | AG15: =Cálculo!P7/1000+Cálculo!F5 -> 193.66229
B16: Sales $m | C16: =C15*C14/1000 -> 308.20925 | D16: =D15*D14/1000 -> 410.47177 | E16: =E15*E14/1000 -> 296.07456 | F16: =F15*F14/1000 -> 486.93306 | G16: =SUM(C16:F16) -> 1501.6886 | J16: Export (kt) | K16: =SUM(Cálculo!F17:F18,Cálculo!F22,Cálculo!F28:F29,Cálculo!F33:F34,Cálculo!F38)/1000 -> 2211.6246 | M16: =Q34-L34 -> -288.78864 | N16: =P34-P33 -> 71.243902 | O16: =M16*N16/1000+2 -> -18.57443 | X16: =X7 -> AM Dofasco 1 | Y16: 466 | Z16: 109 | AA16: =Y16*Z16 -> 50794 | AB16: =Y16-Y7 -> 3.7355253 | AC16: =AB16-AA5 -> -31.966632 | AH16: Premio DM | AI16: Q1 | AJ16: Q2 | AK16: Q3 | AL16: Q4 | AM16: Avr.
J17: Preço Ex-W | K17: =#REF! -> #REF! | X17: =X8 -> AM Dofasco 2 | Y17: 0 | Z17: 0 | AA17: =Y17*Z17 -> 0 | AF17: Difference | AG17: =AG15-AG13 -> #REF! | AH17: FY21 | AI17: 10 | AJ17: 10 | AK17: 10 | AL17: 10 | AM17: =AVERAGE(AI17:AL17) -> 10
B18: =B13 -> HRC China - Exports | C18: Q121 | D18: Q221 | E18: Q321 | F18: Q421 | G18: FY21 | J18: Check | K18: =K16-K17 -> #REF! | O18: 2milhoes ajustados por conta das ligas | X18: =X9 -> CSI | Y18: 422 | Z18: 55 | AA18: =Y18*Z18 -> 23210 | AB18: =Y18-Y9 -> -5.0021545 | AC18: =AB18-AA5 -> -40.704312 | AF18: $/t | AG18: =AG17/AG20*1000 -> #REF! | AH18: FY20 | AI18: =AVERAGE(2,1,-1) -> 0.66666667 | AJ18: =AVERAGE(8,4,2) -> 4.6666667 | AK18: =AVERAGE(8,1,-3) -> 2 | AL18: 10 | AM18: =AVERAGE(AI18:AL18) -> 4.3333333
A19: Ajustar China | B19: Price $/t (1 quarter lag) | C19: ='[54]HRC Prices'!Z52 -> 496.65136 | D19: ='[54]HRC Prices'!AA52 -> 489.695 | E19: ='[54]HRC Prices'!AB52 -> 474.3 | F19: ='[54]HRC Prices'!AC52 -> 460.85 | G19: =G21/G20*1000 -> #REF! | X19: =X10 -> NLMK USA | Y19: 0 | Z19: 0 | AA19: =Y19*Z19 -> 0 | AM19: =AM17-AM18 -> 5.6666667 | AN19: a
B20: Vol. Kt | C20: =#REF! -> #REF! | D20: =#REF! -> #REF! | E20: =#REF! -> #REF! | F20: =#REF! -> #REF! | G20: =SUM(C20:F20) -> #REF! | X20: $/t | Y20: =AA20/Z20 -> 451.2439 | Z20: =SUM(Z16:Z19) -> 164 | AA20: =SUM(AA16:AA19) -> 74004 | AB20: =Y20-Y11 -> -0.13604026 | AC20: =AB20-AA5 -> -35.838198 | AF20: Domestic (kt) | AG20: =SUM(Cálculo!F20:F21,Cálculo!F23:F27,Cálculo!F30:F32,Cálculo!F35:F37,Cálculo!F39:F43)/1000 -> 3986.3767
B21: =B16 -> Sales $m | C21: =C20*C19/1000 -> #REF! | D21: =D20*D19/1000 -> #REF! | E21: =E20*E19/1000 -> #REF! | F21: =F20*F19/1000 -> #REF! | G21: =SUM(C21:F21) -> #REF! | J21: MRF10 plano de vendas | O21: Budget plano de vendas | AI21: HRC Industry | AJ21: =E8 -> #REF! | AK21: =AI13*0.65 -> #REF!
AF22: Industry (kt) | AG22: =SUM(Cálculo!F20:F21,Cálculo!F24:F25,Cálculo!F27,Cálculo!F31:F32,Cálculo!F36:F37,Cálculo!F39:F40,Cálculo!F42)/1000 -> 3133.2561
B23: For information only - Spread reference - Slab | J23: HRC CIS reference | K23: =AVERAGE(C14:F14) -> 455.74057 | L23: =AVERAGE(C19:F19) -> 480.37409 | M23: =L23-K23 -> 24.633525 | X23: Extra price MRF10 | Y23: =Y15 -> $/t | Z23: =Z15 -> Kt | AA23: =AA15 -> $m | AF23: Auto (kt) | AG23: =SUM(Cálculo!F23,Cálculo!F26,Cálculo!F30,Cálculo!F35,Cálculo!F41,Cálculo!F43)/1000 -> 853.12059
J24: HRC MRF10 | K24: $/t | L24: Kt | M24: $m | N24: % Mix | O24: HRC Budget | P24: $/t | Q24: Kt | R24: $m | S24: % Mix | T24: $/t ∆ | U24: Mix $m | X24: Dofasco 1 | Y24: 21.150056 | Z24: 201.01988 | AA24: =Y24*Z24 -> 4251.5817
B25: Spread SEA - Slab | C25: Q120 | D25: Q220 | E25: Q320 | F25: Q420 | G25: FY20 | J25: BQ Latam | K25: 478.21458 | L25: 393.00168 | M25: =K25*L25 -> 187939.13 | N25: =L25/L27 -> 0.78323664 | O25: BQ Latam | P25: 477.8006 | Q25: 646 | R25: =P25*Q25 -> 308659.19 | S25: =Q25/Q27 -> 0.52189368 | T25: =P25-K25 -> -0.41397429 | U25: =T25*Q25/1000 -> -0.26742739 | X25: Dofasco 2 | Y25: 10.951049 | Z25: 100.04775 | AA25: =Y25*Z25 -> 1095.6278
B26: Price $/t (1 quarter lag) | C26: =-4-59 -> -63 | D26: =17-58 -> -41 | E26: =-12-43 -> -55 | F26: =-2-57 -> -59 | G26: =G28/G27*1000 -> -54.002848 | J26: BQ Asia | K26: 397.61465 | L26: 108.76453 | M26: =K26*L26 -> 43246.371 | N26: =L26/L27 -> 0.21676336 | O26: BQ Asia | P26: 445.69971 | Q26: 591.8 | R26: =P26*Q26 -> 263765.09 | S26: =Q26/Q27 -> 0.47810632 | T26: =P26-K26 -> 48.085055 | U26: =T26*Q26/1000 -> 28.456735 | X26: Total extra price | Y26: =AA26/Z26 -> 17.760825 | Z26: =SUM(Z24:Z25) -> 301.06763 | AA26: =SUM(AA24:AA25) -> 5347.2096 | AF26: Auto | AG26: Price var | AH26: Kt | AI26: Impact $m | AK26: FY20 | AL26: FY21 | AM26: ∆ R$/t | AN26: ∆ %
B27: Vol. Kt | C27: ='[3]Shipments & Prices'!Q22 -> 579 | D27: ='[3]Shipments & Prices'!R22 -> 771.605 | E27: ='[3]Shipments & Prices'!S22 -> 585 | F27: ='[3]Shipments & Prices'!T22 -> 848.559 | G27: =SUM(C27:F27) -> 2784.164 | J27: Total | K27: =M27/L27 -> 460.74347 | L27: =SUM(L25:L26) -> 501.76621 | M27: =SUM(M25:M26) -> 231185.5 | O27: =J27 -> Total | P27: =R27/Q27 -> 462.45296 | Q27: =SUM(Q25:Q26) -> 1237.8 | R27: =SUM(R25:R26) -> 572424.28 | T27: =P27-K27 -> 1.7094955 | U27: =T27*Q27/1000 -> 2.1160136 | AF27: HRC | AG27: =Cálculo!O23-$E$8 -> #REF! | AH27: =Cálculo!F23/1000 -> 100.23684 | AI27: =AG27*AH27/1000 -> #REF! | AK27: =Cálculo!D23*Cálculo!$E$152 -> 3679.7808 | AL27: =Cálculo!G23*Cálculo!$H$152 -> 3757.0515 | AM27: =AL27-AK27 -> 77.270714 | AN27: =AM27/AK27 -> 0.020998727
B28: Sales $m | C28: =C27*C26/1000 -> -36.477 | D28: =D27*D26/1000 -> -31.635805 | E28: =E27*E26/1000 -> -32.175 | F28: =F27*F26/1000 -> -50.064981 | G28: =SUM(C28:F28) -> -150.35279 | M28: =M27/L27 -> 460.74347 | Q28: =Q27-L27 -> 736.03379 | R28: =R27/Q27 -> 462.45296 | T28: =R28-M28 -> 1.7094955 | U28: =U25+U26-U27 -> 26.073294 | V28: Mix HRC | X28: Calvert | Y28: 47.17 | Z28: 365.2513 | AA28: =Y28*Z28 -> 17228.904 | AF28: P&O | AG28: =Cálculo!O26-$E$8 -> #REF! | AH28: =Cálculo!F26/1000 -> 90.523858 | AI28: =AG28*AH28/1000 -> #REF! | AK28: =Cálculo!D26*Cálculo!$E$152 -> 4639.713 | AL28: =Cálculo!G26*Cálculo!$H$152 -> 4733.5026 | AM28: =AL28-AK28 -> 93.789581 | AN28: =AM28/AK28 -> 0.020214522
J29: Diferença preço versus referencia | M29: =M28-C6 -> 1.4987746 | O29: Diferença preço versus referencia | R29: =R28-D6 -> #REF! | T29: =R29-M29 -> #REF! | U29: =T29*Q27/1000 -> #REF! | X29: Calvert USIBOR | Y29: 120.92942 | Z29: 193.32147 | AA29: =Y29*Z29 -> 23378.253 | AF29: CRC Auto | AG29: =Cálculo!O30-$E$8 -> #REF! | AH29: =Cálculo!F30/1000 -> 95.622293 | AI29: =AG29*AH29/1000 -> #REF! | AK29: =Cálculo!D30*Cálculo!$E$152 -> 4978.92 | AL29: =Cálculo!G30*Cálculo!$H$152 -> 5088.197 | AM29: =AL29-AK29 -> 109.27698 | AN29: =AM29/AK29 -> 0.021947928
B30: Spread SEA - Slab | C30: Q121 | D30: Q221 | E30: Q321 | F30: Q421 | G30: FY21 | X30: Total extra price | Y30: =AA30/Z30 -> 72.69806 | Z30: =SUM(Z28:Z29) -> 558.57277 | AA30: =SUM(AA28:AA29) -> 40607.156 | AF30: HDG Auto | AG30: =Cálculo!O35-$E$8 -> #REF! | AH30: =Cálculo!F35/1000 -> 463.78729 | AI30: =AG30*AH30/1000 -> #REF! | AK30: =Cálculo!D35*Cálculo!$E$152 -> 5643.5325 | AL30: =Cálculo!G35*Cálculo!$H$152 -> 5687.8782 | AM30: =AL30-AK30 -> 44.345684 | AN30: =AM30/AK30 -> 0.0078577883
B31: Price $/t (1 quarter lag) | C31: =10-60 -> -50 | D31: =10-55 -> -45 | E31: =10-55 -> -45 | F31: =10-55 -> -45 | G31: =G33/G32*1000 -> #REF! | J31: Slab CIS reference | K31: =AVERAGE('[54]Semis steel prices and spreads'!$V$10:$Y$10) -> 387.43029 | L31: =AVERAGE('[54]Semis steel prices and spreads'!$Z$10:$AC$10) -> 429.16981 | M31: =L31-K31 -> 41.739523 | AF31: Usibor Auto | AG31: =Cálculo!O41-$E$8 -> #REF! | AH31: =Cálculo!F41/1000 -> 99.323021 | AI31: =AG31*AH31/1000 -> #REF! | AK31: =Cálculo!D41*Cálculo!$E$152 -> 6973.4038 | AL31: =Cálculo!G41*Cálculo!$H$152 -> 7149.6531 | AM31: =AL31-AK31 -> 176.24927 | AN31: =AM31/AK31 -> 0.025274497
B32: Vol. Kt | C32: =#REF! -> #REF! | D32: =#REF! -> #REF! | E32: =#REF! -> #REF! | F32: =#REF! -> #REF! | G32: =SUM(C32:F32) -> #REF! | J32: Slabs w/o Calvert MRF10 | K32: $/t | L32: Kt | M32: $m | N32: % Mix | O32: Slabs w/o Calvert Budget | P32: $/t | Q32: Kt | R32: $m | S32: % Mix | T32: $/t ∆ | U32: Mix $m | AF32: Auto imports | AG32: =Cálculo!O43-$E$8 -> #REF! | AH32: =Cálculo!F43/1000 -> 3.6272929 | AI32: =AG32*AH32/1000 -> #REF! | AK32: =Cálculo!D43*Cálculo!$E$152 -> 10111.406 | AL32: =Cálculo!G43*Cálculo!$H$152 -> 10097.65 | AM32: =AL32-AK32 -> -13.756064 | AN32: =AM32/AK32 -> -0.0013604501
B33: =B28 -> Sales $m | C33: =C32*C31/1000 -> #REF! | D33: =D32*D31/1000 -> #REF! | E33: =E32*E31/1000 -> #REF! | F33: =F32*F31/1000 -> #REF! | G33: =SUM(C33:F33) -> #REF! | J33: Slab Asia | K33: 328.96065 | L33: 238.52114 | M33: =K33*L33 -> 78464.07 | N33: =L33/$L$36 -> 0.32615609 | O33: Slab Asia | P33: 380 | Q33: 523 | R33: =P33*Q33 -> 198740 | S33: =Q33/$Q$36 -> 0.55816435 | T33: =P33-K33 -> 51.039347 | U33: =T33*Q33/1000 -> 26.693578 | X33: Extra price Budget | Y33: =Y23 -> $/t | Z33: =Z23 -> Kt | AA33: =AA23 -> $m | AB33: $/t ∆ | AF33: Total | AI33: =SUM(AI27:AI32) -> #REF!
J34: Slab America | K34: =Y11 -> 451.37994 | L34: =Z11 -> 452.78864 | M34: =AA11 -> 204379.71 | N34: =L34/$L$36 -> 0.61914753 | O34: Slab America | P34: =Y20 -> 451.2439 | Q34: =Z20 -> 164 | R34: =AA20 -> 74004 | S34: =Q34/$Q$36 -> 0.17502668 | T34: =P34-K34 -> -0.13604026 | U34: =T34*Q34/1000 -> -0.022310603 | X34: Dofasco 1 | Y34: 10 | Z34: 109 | AA34: =Y34*Z34 -> 1090 | AB34: =Y34-Y24 -> -11.150056 | AC34: =AB34*Z34/1000 -> -1.2153561
B35: For information only - HRC reference - Domestic | J35: Slab Europe | K35: 430 | L35: 40 | M35: =K35*L35 -> 17200 | N35: =L35/$L$36 -> 0.054696383 | O35: Slab Europe | P35: 398.7088 | Q35: 250 | R35: =P35*Q35 -> 99677.2 | S35: =Q35/$Q$36 -> 0.26680896 | T35: =P35-K35 -> -31.2912 | U35: =T35*Q35/1000 -> -7.8228 | X35: Dofasco 2 | Y35: 0 | Z35: 0 | AA35: =Y35*Z35 -> 0 | AB35: =Y35-Y25 -> -10.951049
J36: Total | K36: =M36/L36 -> 410.28274 | L36: =SUM(L33:L35) -> 731.30978 | M36: =SUM(M33:M35) -> 300043.78 | N36: =L36/$L$36 -> 1 | O36: =J36 -> Total | P36: =R36/Q36 -> 397.46126 | Q36: =SUM(Q33:Q35) -> 937 | R36: =SUM(R33:R35) -> 372421.2 | S36: =Q36/$Q$36 -> 1 | T36: =P36-K36 -> -12.821481 | U36: =T36*Q36/1000 -> -12.013728 | X36: Total extra price | Y36: =AA36/Z36 -> 10 | Z36: =SUM(Z34:Z35) -> 109 | AA36: =SUM(AA34:AA35) -> 1090 | AF36: Industry | AG36: Price var | AH36: Kt | AI36: Impact $m | AK36: FY20 | AL36: FY21 | AM36: ∆ R$/t | AN36: ∆ %
B37: HRC CIS - Domestic | C37: Q120 | D37: Q220 | E37: Q320 | F37: Q420 | G37: FY20 | L37: =Cálculo!C14/1000 -> -0.00038 | Q37: =Cálculo!F14/1000 -> 7106.5585 | U37: =-SUM(U33:U35)+U36 -> -30.862195 | V37: Mix Slab | X37: $/t ∆ | Y37: =Y36-Y26 -> -7.7608253 | Z37: =Z36-Z26 -> -192.06763 | AA37: =AA36-AA26 -> -4257.2096 | AF37: P&O | AG37: =Cálculo!O27-$AG$44 -> 0 | AH37: =Cálculo!F27/1000 -> 45.424208 | AI37: =AG37*AH37/1000 -> 0 | AK37: =Cálculo!D27*Cálculo!$E$152 -> 3905.6445 | AL37: =Cálculo!G27*Cálculo!$H$152 -> 3743.7877 | AM37: =AL37-AK37 -> -161.85682 | AN37: =AM37/AK37 -> -0.041441771
B38: Price $/t | C38: =[55]Planilha3!S5 -> 466.73077 | D38: =[55]Planilha3!T5 -> 374.42308 | E38: =[55]Planilha3!U5 -> 462.19231 | F38: =[55]Planilha3!V5 -> 487.34341 | G38: =G40/G39*1000 -> 447.22366 | J38: Calvert MRF10 | K38: $/t | L38: Kt | M38: $m | N38: =N32 -> % Mix | O38: Calvert Budget | P38: $/t | Q38: Kt | R38: $m | S38: =S32 -> % Mix | T38: $/t ∆ | U38: Mix $m | AF38: CRC | AG38: =Cálculo!O31-$AG$44 -> 56.689756 | AH38: =Cálculo!F31/1000 -> 286.12232 | AI38: =AG38*AH38/1000 -> 16.220205 | AK38: =Cálculo!D31*Cálculo!$E$152 -> 4256.3653 | AL38: =Cálculo!G31*Cálculo!$H$152 -> 4373.4123 | AM38: =AL38-AK38 -> 117.04702 | AN38: =AM38/AK38 -> 0.02749929
B39: Vol. Kt | C39: ='[3]Shipments & Prices'!Q112 -> 943.87067 | D39: ='[3]Shipments & Prices'!R112 -> 1003.2054 | E39: ='[3]Shipments & Prices'!S112 -> 1043.0363 | F39: ='[3]Shipments & Prices'!T112 -> 972.31133 | G39: =SUM(C39:F39) -> 3962.4237 | J39: Calvert | K39: 464.87561 | L39: 365.2513 | M39: 169796.42 | N39: =L39/$L$41 -> 0.65390101 | O39: =J39 -> Calvert | P39: 488.86483 | Q39: 1160 | R39: =P39*Q39 -> 567083.2 | S39: =Q39/$Q$41 -> 0.92063492 | T39: =P39-K39 -> 23.989221 | U39: =T39*Q39/1000 -> 27.827496 | V39: =(T39-$AA$5)*Q39/1000 -> -13.587007 | X39: Calvert | Y39: 47.17 | Z39: 1106 | AA39: =Y39*Z39 -> 52170.02 | AB39: =Y39-Y28 -> 0 | AC39: =AB39*Z39/1000 -> 0 | AF39: HDG | AG39: =Cálculo!O36-$AG$44 -> 63.768902 | AH39: =Cálculo!F36/1000 -> 438.61917 | AI39: =AG39*AH39/1000 -> 27.970263 | AK39: =Cálculo!D36*Cálculo!$E$152 -> 4583.428 | AL39: =Cálculo!G36*Cálculo!$H$152 -> 4723.5641 | AM39: =AL39-AK39 -> 140.13614 | AN39: =AM39/AK39 -> 0.030574527
B40: Sales $m | C40: =C39*C38/1000 -> 440.53348 | D40: =D39*D38/1000 -> 375.62327 | E40: =E39*E38/1000 -> 482.08335 | F40: =F39*F38/1000 -> 473.84952 | G40: =SUM(C40:F40) -> 1772.0896 | J40: Calvert USIBOR | K40: 539.9425 | L40: 193.32147 | M40: 104382.48 | N40: =L40/$L$41 -> 0.34609899 | O40: =J40 -> Calvert USIBOR | P40: 572 | Q40: 100 | R40: =P40*Q40 -> 57200 | S40: =Q40/$Q$41 -> 0.079365079 | T40: =P40-K40 -> 32.057505 | U40: =T40*Q40/1000 -> 3.2057505 | V40: =(T40-$AA$5)*Q40/1000 -> -0.36446528 | X40: Calvert USIBOR | Y40: 120.63 | Z40: 154 | AA40: =Y40*Z40 -> 18577.02 | AB40: =Y40-Y29 -> -0.29941709 | AF40: AlZn | AG40: =Cálculo!O39-$AG$44 -> 54.619373 | AH40: =Cálculo!F39/1000 -> 136.27179 | AI40: =AG40*AH40/1000 -> 7.4430797 | AK40: =Cálculo!D39*Cálculo!$E$152 -> 5254.3167 | AL40: =Cálculo!G39*Cálculo!$H$152 -> 5319.2901 | AM40: =AL40-AK40 -> 64.973401 | AN40: =AM40/AK40 -> 0.012365719
J41: Total | K41: =SUM(M39:M40)/SUM(L39:L40) -> 490.85618 | L41: =SUM(L39:L40) -> 558.57277 | O41: Total | P41: =SUM(R39:R40)/SUM(Q39:Q40) -> 495.46286 | Q41: =SUM(Q39:Q40) -> 1260 | R41: =SUM(R39:R40) -> 624283.2 | T41: =P41-K41 -> 4.6066762 | U41: =T41*Q41/1000 -> 5.804412 | X41: Total extra price | Y41: =AA41/Z41 -> 56.148444 | Z41: =SUM(Z39:Z40) -> 1260 | AA41: =SUM(AA39:AA40) -> 70747.04
B42: =B37 -> HRC CIS - Domestic | C42: Q121 | D42: Q221 | E42: Q321 | F42: Q421 | G42: FY21 | Q42: =Q41-L41 -> 701.42723 | R42: Kt ∆ | U42: =-(SUM(U39:U40)-U41) -> -25.228834 | V42: Mix Calvert | X42: $/t ∆ | Y42: =Y41-Y30 -> -16.549615 | Z42: =Z41-Z30 -> 701.42723 | AA42: =AA41-AA30 -> 30139.884 | AF42: Total | AI42: =SUM(AI37:AI40) -> 51.633547
B43: Price $/t | C43: =[55]Planilha3!X5 -> 484.76503 | D43: =[55]Planilha3!Y5 -> 470.17886 | E43: =[55]Planilha3!Z5 -> 458.80259 | F43: =[55]Planilha3!AA5 -> 458.06779 | G43: =G45/G44*1000 -> #REF!
B44: Vol. Kt | C44: =#REF! -> #REF! | D44: =#REF! -> #REF! | E44: =#REF! -> #REF! | F44: =#REF! -> #REF! | G44: =SUM(C44:F44) -> #REF! | AF44: HRC Industry | AG44: =Cálculo!AF24 -> 0
B45: Sales $m | C45: =C44*C43/1000 -> #REF! | D45: =D44*D43/1000 -> #REF! | E45: =E44*E43/1000 -> #REF! | F45: =F44*F43/1000 -> #REF! | G45: =SUM(C45:F45) -> #REF!
AF46: Industry Spreads | AG46: FY20 | AH46: FY21 | AI46: Price var | AJ46: Check
B47: Local pricing | AF47: P&O | AG47: 48 | AH47: 63 | AI47: =AH47-AG47 -> 15 | AJ47: =AI47-AG37 -> 15
AF48: CRC | AG48: 68 | AH48: 85 | AI48: =AH48-AG48 -> 17 | AJ48: =AI48-AG38 -> -39.689756
B49: Pricing | C49: =C5 -> FY20 | D49: =D5 -> FY21 | E49: Var | F49: kt | G49: MUSD | AF49: HDG | AG49: 150 | AH49: 154 | AI49: =AH49-AG49 -> 4 | AJ49: =AI49-AG39 -> -59.768902
B50: Auto price increase | E50: =G50/F50*1000 -> #REF! | F50: =AG23 -> 853.12059 | G50: =AG9 -> #REF! | H50: 62 | AF50: AlZn | AG50: 255 | AH50: 280 | AI50: =AH50-AG50 -> 25 | AJ50: =AI50-AG40 -> -29.619373
B51: Premium (Distribution) | E51: =G51/F51*1000 -> #REF! | F51: =AG22 -> 3133.2561 | G51: =AG8 -> #REF! | H51: 55
B52: Slab customer mix (Dofasco) | E52: =G52/F52*1000 -> -9.6946195 | F52: =Q27 -> 1237.8 | G52: -12 | H52: Considerado o menor volume para NA | AF52: Auto Spreads | AG52: =AG46 -> FY20 | AH52: =AH46 -> FY21 | AI52: ∆ | AJ52: Check
B53: Others | G53: -6
B54: Total | G54: =SUM(G50:G53)-1 -> #REF! | H54: 109 | I54: =H54-G54 -> #REF! | AF54: CRC | AG54: =AVERAGE(144,82,43,-26) -> 60.75 | AH54: =AVERAGE(21,82,86,78) -> 66.75 | AI54: =AH54-AG54 -> 6 | AJ54: =AI54-AG29+AG44 -> #REF!
AF55: HDG | AG55: =AVERAGE(148,97,49,-22) -> 68 | AH55: =AVERAGE(19,140,149,152) -> 115 | AI55: =AH55-AG55 -> 47 | AJ55: =AI55-AG30+AG44 -> #REF!
AF56: Usibor | AG56: =AVERAGE(137,115,120,124) -> 124 | AH56: =AVERAGE(138,151,150,148) -> 146.75 | AI56: =AH56-AG56 -> 22.75 | AJ56: =AI56-AG31+AG44 -> #REF!
B58: Others | G58: =SUM(G52:G54) -> #REF!
B64: Exports volumes to normalize 2020 | C64: ='[3]Shipments & Prices'!$O$111 -> 3269.9096 | D64: =K16 -> 2211.6246
B65: Input price reference
B67: Flat raw material basket
B69: Price $/t | C69: =C5 -> FY20 | D69: =D5 -> FY21 | E69: Var | F69: kt | G69: MUSD | I69: Ref. | J69: Bridge | K69: ∆
B70: Coal (1 quarter lag) | C70: =[55]Planilha3!$W$13 -> 132.02595 | D70: =[55]Planilha3!$AB$13 -> 148.75 | E70: =D70-C70 -> 16.724054 | F70: =(SUM(Cálculo!I128,Cálculo!I129)*Cálculo!G144) -> 4658.5493 | G70: =-E70*F70/1000 -> -77.909833 | I70: =G70 -> -77.909833 | J70: =SUM(Cálculo!J128:J129)/1000 -> -95.378798 | K70: =J70-I70 -> -17.468965
B71: Iron ore (on month lag) | C71: ='[56]Iron ore'!$Q$6 -> 101.61903 | D71: ='[56]Iron ore'!$Q$19 -> 101.66667 | E71: =D71-C71 -> 0.047636508 | F71: =(SUM(Cálculo!I132:I134)*Cálculo!G144) -> 10547.196 | G71: =-E71*F71/1000 -> -0.50243157 | I71: =G71+G84 -> -80.834373 | J71: =SUM(Cálculo!J132:J134)/1000 -> -54.073371 | K71: =J71-I71 -> 26.761002 | M71: Lag IO 62%
B72: Total | G72: =SUM(G70:G71) -> -78.412264 | K72: 26
K73: =SUM(K71:K72) -> 52.761002
B74: Ore premiums & other RM
I75: =H77-G77 -> 131.85678
B76: Price $/t | C76: =C69 -> FY20 | D76: =D69 -> FY21 | E76: Var | F76: kt | G76: MUSD | I76: =H78-G78 -> 5.8973778
B77: Pellet premium | C77: =AVERAGE('[56]Iron ore'!$Q$10) -> 33.375 | D77: ='[56]Iron ore'!$Q$23+0.3 -> 34.05 | E77: =D77-C77 -> 0.675 | F77: =(Cálculo!G144*Cálculo!I133) -> 5485.605 | G77: =-E77*F77/1000 -> -3.7027834 | H77: 128.154 | I77: =H79-G79 -> 5.2751316
B78: Lump premium | C78: ='[56]Iron ore'!$Q$11 -> 8.6736517 | D78: ='[56]Iron ore'!$Q$24+0.3 -> 10 | E78: =D78-C78 -> 1.3263483 | F78: =Cálculo!G144*Cálculo!I134 -> 1538.3797 | G78: =-E78*F78/1000 -> -2.0404272 | H78: 3.8569506
B79: =Box!#REF! -> #REF! | C79: ='[56]Iron ore'!$Q$7 -> 14.126945 | D79: ='[56]Iron ore'!$Q$20 -> 15.3502 | E79: =D79-C79 -> 1.2232546 | F79: =F71 -> 10547.196 | G79: =E79*F79/1000 -> 12.901906 | H79: 18.177038
B80: % Fe, Si, Al & P | G80: =Box!U12+Box!U13+Box!U14-G71-G77-G78-G79-1 -> -61.729635
B81: =Box!P9 -> Coke | G81: =Box!U9 -> -2.7166629
B82: =Box!P15 -> Alloys | G82: =Box!U15 -> -12.014339
B83: =Box!P18 -> Zinc | G83: =Box!U18 -> -11.03
B84: Total | G84: =SUM(G77:G83) -> -80.331941
B86: Total | G86: =G84+G72 -> -158.74421
B88: Iron ore (w/o lag) | C88: =[55]Planilha3!$W$10 -> 103.86394 | D88: =[55]Planilha3!$AB$10 -> 100 | E88: =D88-C88 -> -3.8639448 | F88: =SUM(Cálculo!I132:I134)*Cálculo!G144 -> 10547.196 | G88: =-E88*F88/1000 -> 40.753782
B91: * Flat RM basket = 1.6 (Iron Ore CFR China) + 0.6 (HCC CFR China***) + 0.15 (East Asia scrap)
B96: RM factors
B98: RM negotiations | C98: =C76 -> FY20 | D98: =D76 -> FY21 | E98: =E76 -> Var | F98: =F76 -> kt | G98: =G76 -> MUSD
B99: =Box!BE5 -> 0 | G99: =Box!BF5 -> 0
B100: Coal unload rate (TUIP) | C100: =(1.4*3+0.34)/4 -> 1.135 | D100: =0.34 -> 0.34 | E100: =D100-C100 -> -0.795 | F100: =SUM(Cálculo!I128:I131)*Cálculo!G144 -> 4756.6635 | G100: =-E100*F100/1000+0.4 -> 4.1815475 | J100: IO waste | O100: =Box!#REF! -> #REF!
B101: Coal specific basket | G101: =Box!#REF!+0.2 -> #REF!
B102: Total | G102: =SUM(G99:G101) -> #REF! | J102: =Box!P15 -> Alloys | O102: =Box!U15 -> -12.014339
J103: =Box!P18 -> Zinc | O103: =Box!U18 -> -11.03
J104: =Box!#REF! -> #REF! | O104: =Box!#REF! -> #REF!
B107: =Box!#REF! -> #REF! | G107: =Box!#REF! -> #REF!
B108: =Box!#REF! -> #REF! | G108: =Box!#REF! -> #REF!
B109: =Box!#REF! -> #REF! | G109: =Box!#REF! -> #REF!
B116: For information only - Coal
B118: =B111 -> 0 | C118: Q120 | D118: Q220 | E118: Q320 | F118: Q420 | G118: FY20
B119: Price $/t (1 quarter lag) | C119: ='[54]Raw materials - nominal USD'!Z65 -> 140.00079 | D119: ='[54]Raw materials - nominal USD'!AA65 -> 155.01172 | E119: ='[54]Raw materials - nominal USD'!AB65 -> 118.09127 | F119: ='[54]Raw materials - nominal USD'!AC65 -> 115 | G119: =G121/G120*1000 -> 130.3019
B120: Vol. Kt | C120: ='[57]FCF & OWCR - BUDGET'!B15 -> 1484.44 | D120: ='[57]FCF & OWCR - BUDGET'!C15 -> 865.963 | E120: ='[57]FCF & OWCR - BUDGET'!D15 -> 1068.176 | F120: ='[57]FCF & OWCR - BUDGET'!E15 -> 1486.883 | G120: =SUM(C120:F120) -> 4905.462
B121: $m | C121: =C120*C119/1000 -> 207.82278 | D121: =D120*D119/1000 -> 134.23441 | E121: =E120*E119/1000 -> 126.14226 | F121: =F120*F119/1000 -> 170.99154 | G121: =SUM(C121:F121) -> 639.191
B123: =B118 -> 0 | C123: Q121 | D123: Q221 | E123: Q321 | F123: Q421 | G123: FY21
B124: Price $/t (1 quarter lag) | C124: ='[54]Raw materials - nominal USD'!AD65 -> 145 | D124: ='[54]Raw materials - nominal USD'!AE65 -> 160 | E124: ='[54]Raw materials - nominal USD'!AF65 -> 150 | F124: ='[54]Raw materials - nominal USD'!AG65 -> 140 | G124: =G126/G125*1000 -> 148.85239
B125: Vol. Kt | C125: ='[57]FCF & OWCR - BUDGET'!$M$15 -> 1749.243 | D125: ='[57]FCF & OWCR - BUDGET'!$Q$15 -> 1728.598 | E125: ='[57]FCF & OWCR - BUDGET'!$U$15 -> 1636.709 | F125: ='[57]FCF & OWCR - BUDGET'!$Y$15 -> 1627.727 | G125: =SUM(C125:F125) -> 6742.277
B126: =B121 -> $m | C126: =C125*C124/1000 -> 253.64023 | D126: =D125*D124/1000 -> 276.57568 | E126: =E125*E124/1000 -> 245.50635 | F126: =F125*F124/1000 -> 227.88178 | G126: =SUM(C126:F126) -> 1003.604
B129: For information only - Iron ore
...

Sheet Footprint
B2: Footprint effect | H2: Conciliações
B3: CM | C3: Kt | D3: CM $/t | E3: $m | H3: Vol & Mix
B4: Volume | C4: =Cálculo!J114/1000 -> -125.77525 | D4: =E4/C4*1000 -> 3290.3056 | E4: =SUM(E5:E9) -> -413.839 | H4: Tradicional | I4: =SUM(Cálculo!C6:C7) -> -6.6803807
B5: Slab Others | C5: =Cálculo!F84/1000 -> 997.32708 | D5: =Cálculo!D84 -> 28.199955 | E5: =C5*D5/1000 -> 28.124579 | H5: Calvert | I5: =Box!#REF! -> #REF!
B6: Slab DM | C6: =Cálculo!F86/1000 -> 32.42416 | D6: =Cálculo!D86 -> 0.72748999 | E6: =C6*D6/1000 -> 0.023588252 | H6: Footprint | I6: =E4 -> -413.839
B7: Plates DM | C7: =Cálculo!F87/1000 -> 16.52916 | D7: =Cálculo!D87 -> 269.02612 | E7: =C7*D7/1000 -> 4.4467758 | H7: Auto | I7: =SUM(Cálculo!K89,Cálculo!K92,Cálculo!K94,Cálculo!K96,Cálculo!K99,Cálculo!K101,Cálculo!K107)/1000 -> 1.8211753
B8: BQ Asia | C8: ='Box Book'!Q26 -> 591.8 | D8: =-('Box Book'!P27-'Box Book'!P26)+Cálculo!D88 -> 19.299009 | E8: =C8*D8/1000 -> 11.421153 | H8: Others | I8: =I4-I5-I6-I7 -> #REF!
B9: BQ LATAM | C9: =C4-C5-C6-C7-C8 -> -1763.8557 | D9: =-('Box Book'!P27-'Box Book'!P25)+Cálculo!D89 -> 259.57628 | E9: =C9*D9/1000 -> -457.8551
H10: Usage
B11: Usage | C11: =C4 -> -125.77525 | D11: =E11/C11*1000 -> 32.538556 | E11: =Box!X5 -> -4.0925449 | H11: Tradicional | I11: =Cálculo!C10 -> -12.829343
B12: Fixed cost | E12: =Box!#REF! -> #REF! | H12: Footprint | I12: =E11 -> -4.0925449
B13: Logistic | C13: =C11 -> -125.77525 | D13: -8 | E13: =C13*D13/1000 -> 1.006202 | H13: Other RM | I13: =Box!#REF! -> #REF!
H14: Usage | I14: =I11-I12-I13 -> #REF!
B15: Total | C15: =C11 -> -125.77525 | D15: =E15/C15*1000 -> #REF! | E15: =SUM(E4,E11:E13) -> #REF!
H16: Custo fixo
H17: Tradicional | I17: =Cálculo!C8 -> -34.290559
H18: Footprint | I18: =Box!CG16 -> 0
H19: Inflação | I19: =Box!CD5 -> Sales Ind
H20: Sust. | I20: =Box!#REF! -> #REF!
H21: Non controllable | I21: =Box!#REF! -> #REF!
H22: Non recurrent | I22: =Box!#REF! -> #REF! | J22: =I17-SUM(I18:I22) -> #REF!
H25: Preço
H26: Tradicional | I26: =Cálculo!C5 -> 286.54894
H27: Corporate | I27: ='Box Book'!G9 -> #REF!
H28: Local market | I28: ='Box Book'!G54 -> #REF!
H29: Calvert | I29: =Box!#REF! -> #REF!
H30: Others | I30: =I26-I27-I28-I29 -> #REF!
H32: Input price
H33: Tradicional | I33: =Cálculo!C9 -> -177.47195
H34: Corporate | I34: ='Box Book'!G86 -> -158.74421
H35: Inflation | I35: =Box!CD6 -> Sales Auto
H36: Other RM | I36: =I33-I34-I35 -> #VALUE! | J36: =I36-'Box Book'!G102 -> #VALUE!

Sheet Premissas comercial B21
B2: PRICES ME | C2: NEGOTIATION TIME | D2: NOV 2020 | E2: DEC 2020 | F2: JAN 2021 | G2: FEB 2021 | H2: MAR 2021 | I2: APR 2021 | J2: MAY 2021 | K2: JUN 2021 | L2: JUL 2021 | M2: AUG 2021 | N2: SEP 2021 | O2: OCT 2021
C3: SHIPMENT PRICE (2 months lag) | D3: JAN 2021 | E3: FEB 2021 | F3: MAR 2021 | G3: APR 2021 | H3: MAY 2021 | I3: JUN 2021 | J3: JUL 2021 | K3: AUG 2021 | L3: SEP 2021 | M3: OCT 2021 | N3: NOV 2021 | O3: DEC 2021
B4: RMB | C4: IO China CFR | D4: 115 | E4: 115 | F4: 110 | G4: 110 | H4: 110 | I4: 100 | J4: 100 | K4: 100 | L4: 95 | M4: 95 | N4: 95 | O4: 95
C5: HCC China CFR | D5: 156 | E5: 156 | F5: 170.5 | G5: 170.5 | H5: 170.5 | I5: 158 | J5: 158 | K5: 158 | L5: 148 | M5: 148 | N5: 148 | O5: 156
C6: Scrap China CFR | D6: 311.0091 | E6: 311.0091 | F6: 331.3 | G6: 331.3 | H6: 331.3 | I6: 322 | J6: 322 | K6: 322 | L6: 319 | M6: 319 | N6: 319 | O6: 324
C7: RMB | D7: 324.25136 | E7: 324.25136 | F7: 327.995 | G7: 327.995 | H7: 327.995 | I7: 303.1 | J7: 303.1 | K7: 303.1 | L7: 288.65 | M7: 288.65 | N7: 288.65 | O7: 294.2
C8: VAT China | D8: - | E8: - | F8: - | G8: - | H8: - | I8: - | J8: - | K8: - | L8: - | M8: - | N8: - | O8: -
C9: Spread | D9: 172.4 | E9: 172.4 | F9: 161.7 | G9: 161.7 | H9: 161.7 | I9: 171.2 | J9: 171.2 | K9: 171.2 | L9: 172.2 | M9: 172.2 | N9: 172.2 | O9: 167.4
B10: HRC | C10: HRC CHINA FOB | D10: 496.65136 | E10: 496.65136 | F10: 489.695 | G10: 489.695 | H10: 489.695 | I10: 474.3 | J10: 474.3 | K10: 474.3 | L10: 460.85 | M10: 460.85 | N10: 460.85 | O10: 461.6
C11: HRC CIS FOB | D11: 487.34341 | E11: 487.34341 | F11: 484.76503 | G11: 484.76503 | H11: 484.76503 | I11: 470.17886 | J11: 470.17886 | K11: 470.17886 | L11: 458.80259 | M11: 458.80259 | N11: 458.80259 | O11: 458.06779
B12: SLAB | C12: SLAB CIS FOB | D12: 440.34341 | E12: 440.34341 | F12: 442.2091 | G12: 442.2091 | H12: 442.2091 | I12: 423.89921 | J12: 423.89921 | K12: 423.89921 | L12: 407.40561 | M12: 407.40561 | N12: 407.40561 | O12: 407.30569

Sheet Slab BR FOB
B2: 2019 | C2: 2019 | D2: 2020 | E2: 2020 | F2: 2020 | G2: 2020 | H2: 2020 | I2: 2020 | J2: 2020 | K2: 2020 | L2: 2020 | M2: 2020 | N2: 2020 | O2: 2020 | P2: 2021 | Q2: 2021 | R2: 2021 | S2: 2021 | T2: 2021 | U2: 2021 | V2: 2021 | W2: 2021 | X2: 2021 | Y2: 2021
B3: NOV | C3: DEC | D3: JAN | E3: FEB | F3: MAR | G3: APR | H3: MAY | I3: JUN | J3: JUL | K3: AUG | L3: SEP | M3: OCT | N3: NOV | O3: DEC | P3: JAN | Q3: FEB | R3: MAR | S3: APR | T3: MAY | U3: JUN | V3: JUL | W3: AUG | X3: SEP | Y3: OCT
A4: SLAB BR FOB | B4: 359.5 | C4: 395.63 | D4: 433.5 | E4: 465.625 | F4: 423.13 | G4: 333.75 | H4: 342 | I4: 373.75 | J4: 383.5 | K4: 421.88 | L4: 462.5 | M4: 460.34341 | N4: 455.34341 | O4: 455.34341 | P4: 457.2091 | Q4: 467.2091 | R4: 467.2091 | S4: 443.89921 | T4: 438.89921 | U4: 433.89921 | V4: 417.40561 | W4: 412.40561 | X4: 412.40561 | Y4: 422.30569

Sheet SV
B2: MRF10 / Budget | C2: Actual / MRF
A3: Inventory - MRF10 Q418 (R$m) | B3: 3500 | C3: =B3 -> 3500
A4: FX 2018 MRF10 / Actual | B4: ='[58]2018 - US$ EUA '!$M$54 -> 4 | C4: ='[59]2018 - US$ EUA '!$M$54 -> 3.885055 | I4: Rational Calculation
A5: Inventory - MRF10 Q418 ($m) | B5: =B3/B4 -> 875 | C5: =C3/C4 -> 900.88815
I6: Fixed Cost Impact - Stock Variation | J6: Budget | K6: MRF7
A7: Inventory - Actual Q418 (R$m) | B7: =B3 -> 3500 | C7: =C3 -> 3500 | I7: Production (Kt) | J7: ='[60]FCF & OWCR - BUDGET'!$Z$15 -> 6744.765 | K7: =Cálculo!G144 -> 6970.2857
A8: FX 2019 Budget/ MRF | B8: 3.54 | C8: 3.85 | I8: Fixed cost w/o SG&A R$m | J8: =Cálculo!L126 -> 0 | K8: =Cálculo!M126 -> 0
A9: =A7 -> Inventory - Actual Q418 (R$m) | B9: =B7/B8 -> 988.70056 | C9: =C7/C8 -> 909.09091 | I9: Fixed production cost R$/t | J9: =J8/J7 -> 0 | K9: =K8/K7 -> 0
A11: Delta | B11: =B5-B9 -> -113.70056 | C11: =C5-C9 -> -8.2027621 | I11: Shipments kt | J11: =Cálculo!C48/1000 -> 7232.3337 | K11: =Cálculo!F48/1000 -> 7106.5585
B12: A | C12: B | I12: Fixed cost w/o SG&A in EBITDA R$m | J12: =J9*J11 -> 0 | K12: =K9*K11 -> 0
A13: Inventory forex impact | B13: =C11-B11 -> 105.4978 | C13: A - B | J13: A | K13: B
I15: Var R$m | J15: =K12-J12 -> 0 | K15: A - B
A16: Ebitda Cost $m (40% in BRL) | B16: =[61]Q4!$H$89/1000 -> -356.45812 | I16: Var $m (/3,54) | J16: =J15/4 -> 0 | K16: C
A17: Forex MRF10 | B17: =B4 -> 4
A18: Forex Budget | B18: =B8 -> 3.54 | I18: Fixed cost impact w/o SG&A in Bridge | J18: =SUM(Cálculo!J116:J118) -> -34749.498 | K18: D
A19: Ebitda Cost $m (% in dollar Budget) | B19: =B16*B17/B18 -> -402.77754
A20: Delta FX - MRF10 vs Budget | B20: =B16-B19 -> 46.319417 | C20: C | I20: Fixed Cost Impact - Stock Variation | J20: =J16-J18 -> 34749.498 | K20: C - D
A22: FOREX Stock Variation Impact | B22: =B13-B20 -> 59.178386 | C22: (A - B) - C
A27: Stock variation
A29: Main drivers | B29: $m
A30: Fixed Costs | B30: =J20/1000 -> 34.749498
A31: FOREX | B31: =SV!B22 -> 59.178386
A32: Stock Variation total | B32: =SUM(B30:B31) -> 93.927884
B34: =Bridge!B36 -> 70.572859
B35: =B32-B34 -> 23.355026

Sheet Modelo
Q3: =SUM(O5:R5) -> 73.3
C4: 1 | D4: 2 | E4: 3 | F4: 4 | G4: 5 | H4: 6 | I4: 7 | K4: 8 | L4: 9 | M4: 10 | N4: 11
B5: 467 | C5: -106 | D5: =D8*D9/1000 -> -18 | E5: =SUM(B5:D5) -> 343 | F5: =J27 -> -286.568 | G5: =J33 -> 376.63 | H5: =K15 -> -86.8 | I5: =1+4+15-14 -> 6 | J5: =SUM(E5:I5) -> 352.262 | K5: -39 | L5: -35 | M5: -29 | N5: 82 | O5: =21 -> 21 | P5: 8 | Q5: =-Q7*Q8-2 -> 27.4 | R5: =-R7*R8-2 -> 16.9 | S5: -14 | T5: -21 | U5: =SUM(J5:T5) -> 369.562
B6: 2019 | C6: One time | D6: Stoppage | E6: 2019 MRF10 | F6: Price | G6: Inputprice | H6: Mix | I6: Other | J6: 2020 | K6: Calvert | L6: Inflation | M6: Usage | N6: Local | O6: DM vol | P6: FC | Q6: BF 1 & 3 | R6: BF 2 BD | S6: Legal | T6: SV | U6: 2020
B7: MRF10 | E7: Normalized | F7: Corporate | I7: w/o vol | J7: Expected | N7: price | Q7: -42 | R7: -27 | S7: Conting. | U7: Budget
B8: 6,3Mt | D8: 450 | E8: 6.7 | F8: 6.8 | H8: 5.4 | I8: effect | Q8: 0.7 | R8: 0.7
D9: -40
M10: calvert
H11: Additional slab export | J11: 343 | K11: 343 | M11: 415x391
H12: Average slab export | J12: 402 | K12: 405 | M12: =415-391 -> 24
H13: Delta price | J13: =J11-J12 -> -59 | K13: =K11-K12 -> -62
H14: Volume | J14: 1.4 | K14: 1.4
H15: Mix effect | J15: =J13*J14 -> -82.6 | K15: =K13*K14 -> -86.8
G21: 0.7 | H21: 0.7 | J21: 2020
D22: Full | E22: 6.8 | G22: -27 | H22: -42
G23: =G21*G22 -> -18.9 | H23: =H21*H22 -> -29.4
H24: =SUM(G23:H23) -> -48.3
F25: =Q8+G24 -> 0.7
G26: Price | H26: Export
D27: Comercial | E27: Price | F27: =2503+1400 -> 3903 | G27: -56 | H27: =G27*F27/1000 -> -218.568 | I27: -68 | J27: =SUM(H27:I27) -> -286.568 | K27: -211
D28: RM Basket | E28: Coal | F28: 3538 | G28: -24 | H28: =-G28*F28/1000 -> 84.912
E29: PCI | F29: 1473 | G29: -11 | H29: =-G29*F29/1000 -> 16.203
E30: IO | F30: 10775 | G30: -11 | H30: =-G30*F30/1000 -> 118.525
E31: Pellet premium | F31: 6572 | G31: -20 | H31: =-G31*F31/1000 -> 131.44
E32: Lump | H32: 4
E33: Freight | F33: =F30 -> 10775 | G33: -2 | H33: =-G33*F33/1000 -> 21.55 | J33: =SUM(H28:H33) -> 376.63 | K33: =174+87+4+15 -> 280
D35: * | E35: Volumes de consumo de MP considerando 2019 com produção normalizada
J36: =J27+J33 -> 90.062 | K36: =K27+K33 -> 69
